Workbook
Name ANALYSIS_DATE: Trading_comps!$D$4
Name BETA: '1'!$C$20
Name BETA: '2'!$C$20
Name BETA: '3'!$C$20
Name CASH_AND_ST_INVESTMENTS: '1'!$H$8
Name CASH_AND_ST_INVESTMENTS: '2'!$H$8
Name CASH_AND_ST_INVESTMENTS: '3'!$H$8
Name Circswitch: Info!$N$10
Name COMP_CALENDARIZE_PERCENTAGES: '1'!$I$79:$K$79
Name COMP_CALENDARIZE_PERCENTAGES: '2'!$I$79:$K$79
Name COMP_CALENDARIZE_PERCENTAGES: '3'!$I$79:$K$79
Name COMP_CALENDARIZE_PERCENTAGES: 'Factset codes'!$R$64:$V$64
Name COMP_EQ_VALUE: '1'!$H$6
Name COMP_EQ_VALUE: '2'!$H$6
Name COMP_EQ_VALUE: '3'!$H$6
Name COMP_EQ_VALUE: 'Factset codes'!$R$10
Name COMP_EV: '1'!$H$10
Name COMP_EV: '2'!$H$10
Name COMP_EV: '3'!$H$10
Name COMP_EV: 'Factset codes'!$L$10
Name COMP_FX: '1'!$C$15
Name COMP_FX: '2'!$C$15
Name COMP_FX: '3'!$C$15
Name COMP_MTR: '1'!$C$10
Name COMP_MTR: '2'!$C$10
Name COMP_MTR: '3'!$C$10
Name Comp_MTR: 'Factset codes'!$D$19
Name COMP_SHAREPRICE: '1'!$C$16
Name COMP_SHAREPRICE: '2'!$C$16
Name COMP_SHAREPRICE: '3'!$C$16
Name COMP_SHAREPRICE: 'Factset codes'!$D$13
Name COMPANY_NAME: '1'!$A$1
Name COMPANY_NAME: '2'!$A$1
Name COMPANY_NAME: '3'!$A$1
Name CREDIT_RATING: '1'!$C$19
Name CREDIT_RATING: '2'!$C$19
Name CREDIT_RATING: '3'!$C$19
Name DSO: '1'!$D$35
Name DSO: '2'!$D$35
Name DSO: '3'!$D$35
Name EBIT_CY1: '1'!$H$16
Name EBIT_CY1: '2'!$H$16
Name EBIT_CY1: '3'!$H$16
Name EBIT_CY2: '1'!$I$16
Name EBIT_CY2: '2'!$I$16
Name EBIT_CY2: '3'!$I$16
Name EBIT_CY3: '1'!$J$16
Name EBIT_CY3: '2'!$J$16
Name EBIT_CY3: '3'!$J$16
Name EBIT_CY4: '1'!$K$16
Name EBIT_CY4: '2'!$K$16
Name EBIT_CY4: '3'!$K$16
Name EBIT_LTM: '1'!$G$16
Name EBIT_LTM: '2'!$G$16
Name EBIT_LTM: '3'!$G$16
Name EBIT_LTM: 'Factset codes'!$J$14
Name EBITDA_CY1: '1'!$H$15
Name EBITDA_CY1: '2'!$H$15
Name EBITDA_CY1: '3'!$H$15
Name EBITDA_CY2: '1'!$I$15

Sheet Info
A1: Red Bull GmbH — Valuation & M&A Analysis
A2: Confidential — For Discussion Purposes Only
B4: Table of Contents | L4: Model Details
B5: # | C5: Tab | E5: Description | L5: Company | N5: Red Bull
B6: 1 | C6: Red Bull Model | E6: 3-statement financial forecast (IS / BS / CF) | L6: Analysis Date | N6: 46077
B7: 2 | C7: WACC | E7: Weighted average cost of capital | L7: Currency | N7: EUR / USD (as noted)
B8: 3 | C8: DCF | E8: Discounted cash flow valuation | L8: Units | N8: Millions
B9: 4 | C9: Trading Comps | E9: Public company comparable analysis | L9: Analyst | N9: Amgad Bashir
C10: 1 / 2 / 3 | E10: Individual company tearsheets | L10: Circular Switch | N10: 1
B11: 5 | C11: Transaction Comps | E11: Precedent transaction analysis
B12: 6 | C12: Valuation Summary | E12: Football field — consolidated valuation ranges | L12: Color Legend
B13: 7 | C13: Synergies | E13: Synergy value DCF analysis | L13: 123 | N13: Input cell — hardcoded assumption
B14: 8 | C14: M&A | E14: Acquisition scenario — accretion / dilution | L14: 123 | N14: Hardcoded value (no input shading)
B15: 9 | C15: LBO | E15: Leveraged buyout — IRR sensitivity | L15: 123 | N15: Formula / calculation
L16: 123 | N16: Cross-sheet link
L17: 123 | N17: Key assumption — review required

Sheet Red Bull Model
A1: ="Financial forecast for "&Info!N5 -> Financial forecast for Red Bull
C2: Actual | D2: Actual | E2: Actual | F2: Actual | G2: Actual / Est. | H2: Actual / Est. | I2: Projected | J2: Projected | K2: Projected | L2: Projected | M2: Projected | N2: Projected | O2: Projected | P2: Projected
C3: =EDATE(D3,-12) -> 44196 | D3: =EDATE(E3,-12) -> 44561 | E3: =EDATE(F3,-12) -> 44926 | F3: =EDATE(G3,-12) -> 45291 | G3: =EDATE(H3,-12) -> 45657 | H3: 46022 | I3: =EDATE(H3,12) -> 46387 | J3: =EDATE(I3,12) -> 46752 | K3: =EDATE(J3,12) -> 47118 | L3: =EDATE(K3,12) -> 47483 | M3: =EDATE(L3,12) -> 47848 | N3: =EDATE(M3,12) -> 48213 | O3: =EDATE(N3,12) -> 48579 | P3: =EDATE(O3,12) -> 48944
B4: All numbers in EURm unless otherwise stated
A6: Assumptions
B8: Revenue growth - Europe | D8: =D50/C50-1 -> 0.25744369 | E8: =E50/D50-1 -> 0.24401562 | F8: =F50/E50-1 -> 0.090999999 | G8: =G50/F50-1 -> 0.063768479 | H8: =H50/G50-1 -> 0.086309789 | I8: 0.085 | J8: 0.08 | K8: 0.075 | L8: 0.07 | M8: 0.065 | N8: 0.05 | O8: 0.03 | P8: 0.026
B9: Revenue growth - USA | D9: =D51/C51-1 -> 0.2166617 | E9: =E51/D51-1 -> 0.1787136 | F9: =F51/E51-1 -> 0.065999999 | G9: =G51/F51-1 -> 0.063768479 | H9: =H51/G51-1 -> 0.086309789 | I9: 0.075 | J9: 0.075 | K9: 0.07 | L9: 0.07 | M9: 0.065 | N9: 0.05 | O9: 0.03 | P9: 0.026
B10: Revenue growth - Americas excluding USA | D10: =D52/C52-1 -> 0.37622812 | E10: =E52/D52-1 -> 0.68187426 | F10: =F52/E52-1 -> 0.21999999 | G10: =G52/F52-1 -> 0.063768479 | H10: =H52/G52-1 -> 0.086309789 | I10: 0.15 | J10: 0.13 | K10: 0.11 | L10: 0.1 | M10: 0.08 | N10: 0.07 | O10: 0.05 | P10: 0.026
B11: Revenue growth - Rest of world | D11: =D53/C53-1 -> 0.21058521 | E11: =E53/D53-1 -> 0.23555449 | F11: =F53/E53-1 -> 0.084999996 | G11: =G53/F53-1 -> 0.063768479 | H11: =H53/G53-1 -> 0.086309789 | I11: 0.085 | J11: 0.082 | K11: 0.08 | L11: 0.08 | M11: 0.07 | N11: 0.055 | O11: 0.035 | P11: 0.026
B12: Total revenue growth | D12: =D54/C54-1 -> 0.23914094 | E12: =E54/D54-1 -> 0.23908278 | F12: =F54/E54-1 -> 0.08981377 | G12: =G54/F54-1 -> 0.063768479 | H12: =H54/G54-1 -> 0.086309789 | I12: =I54/H54-1 -> 0.086622267 | J12: =J54/I54-1 -> 0.082925779 | K12: =K54/J54-1 -> 0.076975775 | ... P12: =P54/O54-1 -> 0.026
B13: Total revenue check, CAGR 2024-2029 | M13: =(M54/H54)^(1/COLUMNS(I54:M54))-1 -> 0.077566836
B14: COGS as % of total revenue | C14: =-C55/C54 -> 0.27524088 | D14: =-D55/D54 -> 0.28381392 | E14: =-E55/E54 -> 0.3365439 | F14: =-F55/F54 -> 0.32733715 | G14: =-G55/G54 -> 0.32733715 | H14: =-H55/H54 -> 0.32733715 | I14: 0.32 | J14: 0.315 | K14: 0.31 | L14: 0.31 | M14: 0.31 | N14: 0.31 | O14: 0.31 | P14: 0.31
B15: SG&A as % of total revenue | C15: =-C58/C54 -> 0.16004422 | D15: =-D58/D54 -> 0.15133323 | E15: =-E58/E54 -> 0.14988937 | F15: =-F58/F54 -> 0.14578888 | G15: 0.145 | H15: 0.143 | I15: 0.142 | J15: 0.14 | K15: 0.138 | L15: 0.138 | M15: 0.138 | N15: 0.138 | O15: 0.138 | P15: 0.138
B16: Marketing expense as % of total revenue | C16: =-C59/C54 -> 0.25769865 | D16: =-D59/D54 -> 0.23826758 | E16: =-E59/E54 -> 0.23638673 | F16: =-F59/F54 -> 0.22991995 | G16: 0.227 | H16: 0.225 | I16: 0.223 | J16: 0.22 | K16: 0.218 | L16: 0.218 | M16: 0.218 | N16: 0.218 | O16: 0.218 | P16: 0.218
B17: Depreciation % beginning net PP&E | D17: =-D62/C80 -> 0.17934716 | E17: =-E62/D80 -> 0.20397502 | F17: =-F62/E80 -> 0.17411863 | G17: 0.17 | H17: 0.17 | I17: 0.17 | J17: 0.17 | K17: 0.17 | L17: 0.16 | M17: 0.16 | N17: 0.16 | O17: 0.16 | P17: 0.16
B18: Other financial income / expense amount | C18: =C67 -> 7.6356352 | D18: =D67 -> 4.348142 | E18: =E67 -> 7.239741 | F18: =F67 -> 7 | G18: 7.5 | H18: 7.5 | I18: 7.5 | J18: 7.5 | K18: 7.5 | L18: 7.5 | M18: 7.5 | N18: 7.5 | O18: 7.5 | P18: 7.5
B19: Effective tax rate | C19: =-C70/C68 -> 0.25736781 | D19: =-D70/D68 -> 0.25534236 | E19: =-E70/E68 -> 0.25835485 | F19: =-F70/F68 -> 0.22162687 | G19: 0.255 | H19: 0.255 | I19: 0.255 | J19: 0.255 | K19: 0.255 | L19: 0.255 | M19: 0.255 | N19: 0.255 | O19: 0.255 | P19: 0.255
B20: Marginal tax rate | F20: 0.24 | G20: 0.23 | H20: 0.23 | I20: 0.23 | J20: 0.23 | K20: 0.23 | L20: 0.23 | M20: 0.23 | N20: 0.23 | O20: 0.23 | P20: 0.23
B21: Dividend payout ratio % net income | D21: =+D45/D71*-1 -> 0.71258993 | E21: =+E45/E71*-1 -> 0.87774617 | F21: =+F45/F71*-1 -> 0.7912551 | G21: 0.6 | H21: 0.75 | I21: 0.75 | J21: 0.75 | K21: 0.75 | L21: 0.75 | M21: 0.75 | N21: 0.75 | O21: 0.75 | P21: 0.75
B23: Accounts receivable days | C23: =+C75/C54*365 -> 39.12377 | D23: =+D75/D54*365 -> 36.539804 | E23: =+E75/E54*365 -> 41.077387 | F23: =+F75/F54*365 -> 39.979199 | G23: 40 | H23: 40 | I23: 39 | J23: 39 | K23: 39 | L23: 39 | M23: 39 | N23: 39 | O23: 39 | P23: 39
B24: Inventory days | C24: =-C76/C55*365 -> 92.813518 | D24: =-D76/D55*365 -> 78.431642 | E24: =-E76/E55*365 -> 104.66439 | F24: =-F76/F55*365 -> 89.995045 | G24: 90 | H24: 90 | I24: 89 | J24: 90 | K24: 90 | L24: 90 | M24: 90 | N24: 90 | O24: 90 | P24: 90
B25: Other current assets as % of total revenue | C25: =+C77/C54 -> 0.056305307 | D25: =+D77/D54 -> 0.051816294 | E25: =+E77/E54 -> 0.060473152 | F25: =+F77/F54 -> 0.0519993 | G25: 0.053 | H25: 0.053 | I25: 0.052 | J25: 0.052 | K25: 0.051 | L25: 0.051 | M25: 0.051 | N25: 0.051 | O25: 0.051 | P25: 0.051
B26: Capital expenditure % of total revenue | C26: =C38/C54 -> 0.059327908 | D26: =D38/D54 -> 0.069950089 | E26: =E38/E54 -> 0.06828807 | F26: =F38/F54 -> 0.075772304 | G26: 0.068 | H26: 0.068 | I26: 0.068 | J26: 0.062 | K26: 0.062 | L26: 0.062 | M26: 0.055 | N26: 0.055 | O26: 0.051 | P26: 0.051
B27: Financial assets amount | C27: =+C81 -> 523.84919 | D27: =+D81 -> 751.47739 | E27: =+E81 -> 1162.6034 | F27: =+F81 -> 1205.8 | G27: 1200 | H27: 1200 | I27: 1200 | J27: 1200 | K27: 1200 | L27: 1200 | M27: 1200 | N27: 1200 | O27: 1200 | P27: 1200
B28: Accounts payable days | C28: =-C85/C55*365 -> 252.23162 | D28: =-D85/D55*365 -> 261.46575 | E28: =-E85/E55*365 -> 245.70742 | F28: =-F85/F55*365 -> 250.99933 | G28: 259 | H28: 259 | I28: 259 | J28: 259 | K28: 259 | L28: 259 | M28: 259 | N28: 259 | O28: 259 | P28: 259
B30: Long term debt issuance (repayment) | D30: =D88-C88 -> 5.9601356 | E30: =E88-D88 -> 40.856667 | F30: =F88-E88 -> -21.216398 | G30: 0 | H30: -11.2 | I30: 0 | J30: 0 | K30: 0 | L30: 0 | M30: 0 | N30: 0 | O30: 0 | P30: 0
B31: Interest rate on revolver | G31: 0.05 | H31: 0.04 | I31: 0.04 | J31: 0.032 | K31: 0.032 | L31: 0.032 | M31: 0.032 | N31: 0.032 | O31: 0.032 | P31: 0.032
B32: Interest rate on long term debt | G32: 0.06 | H32: 0.06 | I32: 0.06 | J32: 0.06 | K32: 0.06 | L32: 0.06 | M32: 0.06 | N32: 0.06 | O32: 0.06 | P32: 0.06
B33: Interest rate on cash | G33: 0.038 | H33: 0.03 | I33: 0.03 | J33: 0.022 | K33: 0.022 | L33: 0.022 | M33: 0.022 | N33: 0.022 | O33: 0.022 | P33: 0.022
A35: Calculations
B36: Net PP&E
B37: Beginning | G37: =F40 -> 2601.2 | H37: =G40 -> 2922.432 | I37: =H40 -> 3254.9466 | J37: =I40 -> 3602.7719 | K37: =J40 -> 3880.0884 | L37: =K40 -> 4178.7532 | M37: =L40 -> 4539.5859 | N37: =M40 -> 4787.7956 | ... P37: =O40 -> 5222.5285
B38: Capital expenditure | C38: 374.19874 | D38: 546.70401 | E38: 661.31618 | F38: 799.7 | G38: =G26*G54 -> 763.436 | H38: =H26*H54 -> 829.328 | I38: =I26*I54 -> 901.16627 | J38: =J26*J54 -> 889.7877 | K38: =K26*K54 -> 958.2798 | L38: =L26*L54 -> 1029.4333 | M38: =M26*M54 -> 974.54341 | N38: =N26*N54 -> 1025.9269 | ... P38: =P26*P54 -> 1008.0259
B39: Depreciation | G39: =G17*G37*-1 -> -442.204 | H39: =H17*H37*-1 -> -496.81344 | I39: =I17*I37*-1 -> -553.34092 | J39: =J17*J37*-1 -> -612.47123 | K39: =K17*K37*-1 -> -659.61503 | L39: =L17*L37*-1 -> -668.60051 | M39: =M17*M37*-1 -> -726.33375 | N39: =N17*N37*-1 -> -766.04729 | ... P39: =P17*P37*-1 -> -835.60457
B40: Ending | F40: =F80 -> 2601.2 | G40: =SUM(G37:G39) -> 2922.432 | H40: =SUM(H37:H39) -> 3254.9466 | I40: =SUM(I37:I39) -> 3602.7719 | J40: =SUM(J37:J39) -> 3880.0884 | K40: =SUM(K37:K39) -> 4178.7532 | L40: =SUM(L37:L39) -> 4539.5859 | M40: =SUM(M37:M39) -> 4787.7956 | N40: =SUM(N37:N39) -> 5047.6752 | ... P40: =SUM(P37:P39) -> 5394.9498
B42: Equity
B43: Beginning | G43: =F46 -> 4112.4 | H43: =G46 -> 4990.5842 | I43: =H46 -> 5593.7631 | J43: =I46 -> 6273.5727 | K43: =J46 -> 7032.6984 | L43: =K46 -> 7877.741 | M43: =L46 -> 8794.6556 | N43: =M46 -> 9772.7599 | ... P43: =O46 -> 11870.076
B44: Net income | G44: =G71 -> 2195.4604 | H44: =H71 -> 2412.7158 | I44: =I71 -> 2719.2384 | J44: =J71 -> 3036.5028 | K44: =K71 -> 3380.1703 | L44: =L71 -> 3667.6582 | M44: =M71 -> 3912.4175 | N44: =N71 -> 4127.3666 | ... P44: =P71 -> 4380.4176
B45: Dividends | D45: -1220.1393 | E45: -1510.7227 | F45: -1701 | G45: =G21*G44*-1 -> -1317.2762 | H45: =H21*H44*-1 -> -1809.5369 | I45: =I21*I44*-1 -> -2039.4288 | J45: =J21*J44*-1 -> -2277.3771 | K45: =K21*K44*-1 -> -2535.1277 | L45: =L21*L44*-1 -> -2750.7437 | M45: =M21*M44*-1 -> -2934.3131 | N45: =N21*N44*-1 -> -3095.525 | ... P45: =P21*P44*-1 -> -3285.3132
B46: Ending | F46: =F91 -> 4112.4 | G46: =SUM(G43:G45) -> 4990.5842 | H46: =SUM(H43:H45) -> 5593.7631 | I46: =SUM(I43:I45) -> 6273.5727 | J46: =SUM(J43:J45) -> 7032.6984 | K46: =SUM(K43:K45) -> 7877.741 | L46: =SUM(L43:L45) -> 8794.6556 | M46: =SUM(M43:M45) -> 9772.7599 | N46: =SUM(N43:N45) -> 10804.602 | ... P46: =SUM(P43:P45) -> 12965.181
A48: Income statement
B49: Revenue
B50: Europe | C50: 2249.6705 | D50: 2828.834 | E50: 3519.1137 | F50: 3839.3531 | G50: =(F50/F54)*G54 -> 4084.1828 | H50: =(F50/$F$54)*H54 -> 4436.6877 | I50: =(I8+1)*H50 -> 4813.8062 | J50: =(J8+1)*I50 -> 5198.9107 | K50: =(K8+1)*J50 -> 5588.829 | L50: =(L8+1)*K50 -> 5980.047 | M50: =(M8+1)*L50 -> 6368.7501 | N50: =(N8+1)*M50 -> 6687.1876 | O50: =(O8+1)*N50 -> 6887.8032 | P50: =(P8+1)*O50 -> 7066.8861
B51: USA | C51: 2981.1378 | D51: 3627.0362 | E51: 4275.2369 | F51: 4557.4026 | G51: =(F51/F54)*G54 -> 4848.0212 | H51: =(F51/$F$54)*H54 -> 5266.4529 | I51: =(I9+1)*H51 -> 5661.4369 | J51: =(J9+1)*I51 -> 6086.0446 | K51: =(K9+1)*J51 -> 6512.0677 | L51: =(L9+1)*K51 -> 6967.9125 | M51: =(M9+1)*L51 -> 7420.8268 | N51: =(N9+1)*M51 -> 7791.8681 | O51: =(O9+1)*N51 -> 8025.6242 | P51: =(P9+1)*O51 -> 8234.2904
B52: Americas excluding USA | C52: 341.56912 | D52: 470.07702 | E52: 790.61045 | F52: 964.54474 | G52: =(F52/F54)*G54 -> 1026.0523 | H52: =(F52/$F$54)*H54 -> 1114.6106 | I52: =(I10+1)*H52 -> 1281.8022 | J52: =(J10+1)*I52 -> 1448.4365 | K52: =(K10+1)*J52 -> 1607.7646 | L52: =(L10+1)*K52 -> 1768.541 | M52: =(M10+1)*L52 -> 1910.0243 | N52: =(N10+1)*M52 -> 2043.726 | O52: =(O10+1)*N52 -> 2145.9123 | P52: =(P10+1)*O52 -> 2201.706
B53: Rest of world | C53: 734.91954 | D53: 889.68272 | E53: 1099.2515 | F53: 1192.6879 | G53: =(F53/F54)*G54 -> 1268.7437 | H53: =(F53/$F$54)*H54 -> 1378.2487 | I53: =(I11+1)*H53 -> 1495.3999 | J53: =(J11+1)*I53 -> 1618.0227 | K53: =(K11+1)*J53 -> 1747.4645 | L53: =(L11+1)*K53 -> 1887.2617 | M53: =(M11+1)*L53 -> 2019.37 | N53: =(N11+1)*M53 -> 2130.4353 | O53: =(O11+1)*N53 -> 2205.0006 | P53: =(P11+1)*O53 -> 2262.3306
B54: Total revenue | C54: =SUM(C50:C53) -> 6307.297 | D54: =SUM(D50:D53) -> 7815.63 | E54: =SUM(E50:E53) -> 9684.2126 | F54: =SUM(F50:F53) -> 10553.988 | G54: 11227 | H54: 12196 | I54: =SUM(I50:I53) -> 13252.445 | J54: =SUM(J50:J53) -> 14351.415 | K54: =SUM(K50:K53) -> 15456.126 | L54: =SUM(L50:L53) -> 16603.762 | M54: =SUM(M50:M53) -> 17718.971 | N54: =SUM(N50:N53) -> 18653.217 | O54: =SUM(O50:O53) -> 19264.34 | P54: =SUM(P50:P53) -> 19765.213
B55: Cost of goods sold | C55: -1736.026 | D55: =-552.611255-1665.573346 -> -2218.1846 | E55: =-879.353942-2379.808727 -> -3259.1627 | F55: =E55*(1.06) -> -3454.7124 | G55: =(F55/F54)*G54 -> -3675.0142 | H55: =(F55/F54)*H54 -> -3992.2039 | I55: =I14*I54*-1 -> -4240.7825 | J55: =J14*J54*-1 -> -4520.6956 | K55: =K14*K54*-1 -> -4791.399 | L55: =L14*L54*-1 -> -5147.1663 | M55: =M14*M54*-1 -> -5492.881 | N55: =N14*N54*-1 -> -5782.4973 | O55: =O14*O54*-1 -> -5971.9455 | P55: =P14*P54*-1 -> -6127.216
B56: Gross profit | C56: =SUM(C54:C55) -> 4571.271 | D56: =SUM(D54:D55) -> 5597.4454 | E56: =SUM(E54:E55) -> 6425.0499 | F56: =SUM(F54:F55) -> 7099.2758 | G56: =SUM(G54:G55) -> 7551.9858 | H56: =SUM(H54:H55) -> 8203.7961 | I56: =SUM(I54:I55) -> 9011.6627 | J56: =SUM(J54:J55) -> 9830.7189 | ... P56: =SUM(P54:P55) -> 13637.997
B58: Selling, general & admin expenses | C58: -1009.4464 | D58: -1182.7646 | E58: -1451.5605 | F58: =E58*1.06 -> -1538.6541 | G58: =G15*G54*-1 -> -1627.915 | H58: =H15*H54*-1 -> -1744.028 | I58: =I15*I54*-1 -> -1881.8472 | J58: =J15*J54*-1 -> -2009.198 | K58: =K15*K54*-1 -> -2132.9454 | L58: =L15*L54*-1 -> -2291.3192 | M58: =M15*M54*-1 -> -2445.218 | N58: =N15*N54*-1 -> -2574.1439 | ... P58: =P15*P54*-1 -> -2727.5994
B59: Marketing expenses | C59: -1625.382 | D59: -1862.2113 | E59: -2289.2193 | F59: =E59*1.06 -> -2426.5725 | G59: =G16*G54*-1 -> -2548.529 | H59: =H16*H54*-1 -> -2744.1 | I59: =I16*I54*-1 -> -2955.2953 | J59: =J16*J54*-1 -> -3157.3112 | K59: =K16*K54*-1 -> -3369.4354 | L59: =L16*L54*-1 -> -3619.6201 | M59: =M16*M54*-1 -> -3862.7357 | N59: =N16*N54*-1 -> -4066.4013 | ... P59: =P16*P54*-1 -> -4308.8164
B60: EBITDA | C60: =SUM(C58:C59,C56) -> 1936.4426 | D60: =SUM(D58:D59,D56) -> 2552.4696 | E60: =SUM(E58:E59,E56) -> 2684.2701 | F60: =SUM(F58:F59,F56) -> 3134.0492 | G60: =SUM(G58:G59,G56) -> 3375.5418 | H60: =SUM(H58:H59,H56) -> 3715.6681 | I60: =SUM(I58:I59,I56) -> 4174.5202 | J60: =SUM(J58:J59,J56) -> 4664.2097 | ... P60: =SUM(P58:P59,P56) -> 6601.5812
B62: Depreciation | C62: -314.22114 | D62: -289.48076 | E62: -392.71517 | F62: -400 | G62: =G39 -> -442.204 | H62: =H39 -> -496.81344 | I62: =I39 -> -553.34092 | J62: =J39 -> -612.47123 | K62: =K39 -> -659.61503 | L62: =L39 -> -668.60051 | M62: =M39 -> -726.33375 | N62: =N39 -> -766.04729 | ... P62: =P39 -> -835.60457
B63: EBIT | C63: =SUM(C62,C60) -> 1622.2215 | D63: =SUM(D62,D60) -> 2262.9888 | E63: =SUM(E62,E60) -> 2291.5549 | F63: =SUM(F62,F60) -> 2734.0492 | G63: =SUM(G62,G60) -> 2933.3378 | H63: =SUM(H62,H60) -> 3218.8547 | I63: =SUM(I62,I60) -> 3621.1793 | J63: =SUM(J62,J60) -> 4051.7385 | ... P63: =SUM(P62,P60) -> 5765.9766
B65: Interest income | C65: 10.136564 | D65: 56.465197 | E65: 52.646693 | F65: 55 | G65: =IF(Circswitch=1,G120,0) -> 34.504891 | H65: =IF(Circswitch=1,H120,0) -> 40.270089 | I65: =IF(Circswitch=1,I120,0) -> 49.049154 | J65: =IF(Circswitch=1,J120,0) -> 44.348255 | K65: =IF(Circswitch=1,K120,0) -> 54.654314 | L65: =IF(Circswitch=1,L120,0) -> 66.219098 | M65: =IF(Circswitch=1,M120,0) -> 80.008519 | N65: =IF(Circswitch=1,N120,0) -> 96.206224 | ... P65: =IF(Circswitch=1,P120,0) -> 134.02254
B66: Interest expense | C66: -20.268681 | D66: -24.409698 | E66: -30.7379 | F66: -34.2 | G66: =IF(Circswitch=1,G118+G119,0) -> -28.416 | H66: =IF(Circswitch=1,H118+H119,0) -> -28.08 | I66: =IF(Circswitch=1,I118+I119,0) -> -27.744 | J66: =IF(Circswitch=1,J118+J119,0) -> -27.744 | K66: =IF(Circswitch=1,K118+K119,0) -> -27.744 | L66: =IF(Circswitch=1,L118+L119,0) -> -27.744 | M66: =IF(Circswitch=1,M118+M119,0) -> -27.744 | N66: =IF(Circswitch=1,N118+N119,0) -> -27.744 | ... P66: =IF(Circswitch=1,P118+P119,0) -> -27.744
B67: Other financial income / (expense) | C67: 7.6356352 | D67: 4.348142 | E67: 7.239741 | F67: 7 | G67: =G18 -> 7.5 | H67: =H18 -> 7.5 | I67: =I18 -> 7.5 | J67: =J18 -> 7.5 | K67: =K18 -> 7.5 | L67: =L18 -> 7.5 | M67: =M18 -> 7.5 | N67: =N18 -> 7.5 | ... P67: =P18 -> 7.5
B68: Profit before tax | C68: =SUM(C65:C67,C63) -> 1619.725 | D68: =SUM(D65:D67,D63) -> 2299.3924 | E68: =SUM(E65:E67,E63) -> 2320.7035 | F68: =SUM(F65:F67,F63) -> 2761.8492 | G68: =SUM(G65:G67,G63) -> 2946.9267 | H68: =SUM(H65:H67,H63) -> 3238.5448 | I68: =SUM(I65:I67,I63) -> 3649.9845 | J68: =SUM(J65:J67,J63) -> 4075.8427 | ... P68: =SUM(P65:P67,P63) -> 5879.7551
B70: Tax expense | C70: -416.86508 | D70: -587.13229 | E70: -599.56499 | F70: -612.1 | G70: =G19*G68*-1 -> -751.46631 | H70: =H19*H68*-1 -> -825.82891 | I70: =I19*I68*-1 -> -930.74604 | J70: =J19*J68*-1 -> -1039.3399 | K70: =K19*K68*-1 -> -1156.971 | L70: =L19*L68*-1 -> -1255.3729 | M70: =M19*M68*-1 -> -1339.1496 | N70: =N19*N68*-1 -> -1412.7228 | ... P70: =P19*P68*-1 -> -1499.3376
B71: Net income | C71: =SUM(C68,C70) -> 1202.8599 | D71: =SUM(D68,D70) -> 1712.2602 | E71: =SUM(E68,E70) -> 1721.1385 | F71: =SUM(F68,F70) -> 2149.7492 | G71: =SUM(G68,G70) -> 2195.4604 | H71: =SUM(H68,H70) -> 2412.7158 | I71: =SUM(I68,I70) -> 2719.2384 | J71: =SUM(J68,J70) -> 3036.5028 | ... P71: =SUM(P68,P70) -> 4380.4176
A73: Balance sheet
B74: Cash | C74: 1082.7167 | D74: 1104.4759 | E74: 277.82339 | F74: 598.1 | G74: =MAX(0,G115) -> 1217.9469 | H74: =MAX(0,H115) -> 1466.7257 | I74: =MAX(0,I115) -> 1803.2179 | J74: =MAX(0,J115) -> 2228.4417 | K74: =MAX(0,K115) -> 2740.1323 | L74: =MAX(0,L115) -> 3279.7857 | M74: =MAX(0,M115) -> 3993.7161 | N74: =MAX(0,N115) -> 4752.3043 | ... P74: =MAX(0,P115) -> 6549.6903
B75: Accounts receivable | C75: 676.06915 | D75: 782.41531 | E75: 1089.8689 | F75: 1156 | G75: =G23*G54/365 -> 1230.3562 | H75: =H23*H54/365 -> 1336.5479 | I75: =I23*I54/365 -> 1416.0147 | J75: =J23*J54/365 -> 1533.4388 | K75: =K23*K54/365 -> 1651.4765 | L75: =L23*L54/365 -> 1774.1006 | M75: =M23*M54/365 -> 1893.2599 | N75: =N23*N54/365 -> 1993.0835 | ... P75: =P23*P54/365 -> 2111.8995
B76: Inventories | C76: 441.44296 | D76: 476.64619 | E76: 934.57057 | F76: 851.8 | G76: =G24*G55*-1/365 -> 906.16788 | H76: =H24*H55*-1/365 -> 984.37904 | I76: =I24*I55*-1/365 -> 1034.0538 | J76: =J24*J55*-1/365 -> 1114.6921 | K76: =K24*K55*-1/365 -> 1181.4408 | L76: =L24*L55*-1/365 -> 1269.1643 | M76: =M24*M55*-1/365 -> 1354.409 | N76: =N24*N55*-1/365 -> 1425.8212 | ... P76: =P24*P55*-1/365 -> 1510.8204
B77: Other current assets | C77: 355.1343 | D77: 404.97698 | E77: 585.63486 | F77: 548.8 | G77: =G25*G54 -> 595.031 | H77: =H25*H54 -> 646.388 | I77: =I25*I54 -> 689.12715 | J77: =J25*J54 -> 746.27355 | K77: =K25*K54 -> 788.26241 | L77: =L25*L54 -> 846.79187 | M77: =M25*M54 -> 903.66753 | N77: =N25*N54 -> 951.31407 | ... P77: =P25*P54 -> 1008.0259
B78: Total current assets | C78: =SUM(C74:C77) -> 2555.3631 | D78: =SUM(D74:D77) -> 2768.5144 | E78: =SUM(E74:E77) -> 2887.8977 | F78: =SUM(F74:F77) -> 3154.7 | G78: =SUM(G74:G77) -> 3949.502 | H78: =SUM(H74:H77) -> 4434.0407 | I78: =SUM(I74:I77) -> 4942.4136 | J78: =SUM(J74:J77) -> 5622.8461 | ... P78: =SUM(P74:P77) -> 11180.436
B80: Net PP&E | C80: 1614.0805 | D80: =501.556062+1423.754 -> 1925.3101 | E80: =565.62743+1731.656911 -> 2297.2843 | F80: 2601.2 | G80: =G40 -> 2922.432 | H80: =H40 -> 3254.9466 | I80: =I40 -> 3602.7719 | J80: =J40 -> 3880.0884 | K80: =K40 -> 4178.7532 | L80: =L40 -> 4539.5859 | M80: =M40 -> 4787.7956 | N80: =N40 -> 5047.6752 | ... P80: =P40 -> 5394.9498
B81: Financial assets | C81: 523.84919 | D81: =420.025524+157.010166+174.441697 -> 751.47739 | E81: =764.563889+214.306234+183.733265 -> 1162.6034 | F81: 1205.8 | G81: =G27 -> 1200 | H81: =H27 -> 1200 | I81: =I27 -> 1200 | J81: =J27 -> 1200 | K81: =K27 -> 1200 | L81: =L27 -> 1200 | M81: =M27 -> 1200 | N81: =N27 -> 1200 | ... P81: =P27 -> 1200
B82: Total assets | C82: =SUM(C80:C81,C78) -> 4693.2928 | D82: =SUM(D80:D81,D78) -> 5445.3018 | E82: =SUM(E80:E81,E78) -> 6347.7855 | F82: =SUM(F80:F81,F78) -> 6961.7 | G82: =SUM(G80:G81,G78) -> 8071.934 | H82: =SUM(H80:H81,H78) -> 8888.9872 | I82: =SUM(I80:I81,I78) -> 9745.1855 | J82: =SUM(J80:J81,J78) -> 10702.934 | ... P82: =SUM(P80:P81,P78) -> 17775.386
B84: Revolver | C84: 0 | D84: 0 | E84: 0 | F84: 0 | G84: =-MIN(G115,0) -> 0 | H84: =-MIN(H115,0) -> 0 | I84: =-MIN(I115,0) -> 0 | J84: =-MIN(J115,0) -> 0 | K84: =-MIN(K115,0) -> 0 | L84: =-MIN(L115,0) -> 0 | M84: =-MIN(M115,0) -> 0 | N84: =-MIN(N115,0) -> 0 | ... P84: =-MIN(P115,0) -> 0
B85: Accounts payable | C85: 1199.673 | D85: 1588.9844 | E85: 2193.9738 | F85: 2375.7 | G85: =G28*G55*-1/365 -> 2607.7498 | H85: =H28*H55*-1/365 -> 2832.8241 | I85: =I28*I55*-1/365 -> 3009.2128 | J85: =J28*J55*-1/365 -> 3207.836 | K85: =K28*K55*-1/365 -> 3399.9242 | L85: =L28*L55*-1/365 -> 3652.3728 | M85: =M28*M55*-1/365 -> 3897.6882 | N85: =N28*N55*-1/365 -> 4103.1967 | ... P85: =P28*P55*-1/365 -> 4347.8054
B86: Total current liabilities | C86: =SUM(C84:C85) -> 1199.673 | D86: =SUM(D84:D85) -> 1588.9844 | E86: =SUM(E84:E85) -> 2193.9738 | F86: =SUM(F84:F85) -> 2375.7 | G86: =SUM(G84:G85) -> 2607.7498 | H86: =SUM(H84:H85) -> 2832.8241 | I86: =SUM(I84:I85) -> 3009.2128 | J86: =SUM(J84:J85) -> 3207.836 | ... P86: =SUM(P84:P85) -> 4347.8054
B88: Long term debt | C88: 447.9996 | D88: 453.95973 | E88: 494.8164 | F88: 473.6 | G88: =G30+F88 -> 473.6 | H88: =H30+G88 -> 462.4 | I88: =I30+H88 -> 462.4 | J88: =J30+I88 -> 462.4 | K88: =K30+J88 -> 462.4 | L88: =L30+K88 -> 462.4 | M88: =M30+L88 -> 462.4 | N88: =N30+M88 -> 462.4 | ... P88: =P30+O88 -> 462.4
B89: Total liabilities | C89: =SUM(C88,C86) -> 1647.6726 | D89: =SUM(D88,D86) -> 2042.9441 | E89: =SUM(E88,E86) -> 2688.7902 | F89: =SUM(F88,F86) -> 2849.3 | G89: =SUM(G88,G86) -> 3081.3498 | H89: =SUM(H88,H86) -> 3295.2241 | I89: =SUM(I88,I86) -> 3471.6128 | J89: =SUM(J88,J86) -> 3670.236 | ... P89: =SUM(P88,P86) -> 4810.2054
B91: Equity | C91: 3045.6202 | D91: 3402.3577 | E91: 3658.9952 | F91: 4112.4 | G91: =G46 -> 4990.5842 | H91: =H46 -> 5593.7631 | I91: =I46 -> 6273.5727 | J91: =J46 -> 7032.6984 | K91: =K46 -> 7877.741 | L91: =L46 -> 8794.6556 | M91: =M46 -> 9772.7599 | N91: =N46 -> 10804.602 | ... P91: =P46 -> 12965.181
B92: Total liabilities and equity | C92: =SUM(C91,C89) -> 4693.2928 | D92: =SUM(D91,D89) -> 5445.3018 | E92: =SUM(E91,E89) -> 6347.7855 | F92: =SUM(F91,F89) -> 6961.7 | G92: =SUM(G91,G89) -> 8071.934 | H92: =SUM(H91,H89) -> 8888.9872 | I92: =SUM(I91,I89) -> 9745.1855 | J92: =SUM(J91,J89) -> 10702.934 | ... P92: =SUM(P91,P89) -> 17775.386
B94: Check | C94: =IF(ROUND(C92,2)=ROUND(C82,2),"OK",C82-C92) -> OK | D94: =IF(ROUND(D92,2)=ROUND(D82,2),"OK",D82-D92) -> OK | E94: =IF(ROUND(E92,2)=ROUND(E82,2),"OK",E82-E92) -> OK | F94: =IF(ROUND(F92,2)=ROUND(F82,2),"OK",F82-F92) -> OK | G94: =IF(ROUND(G92,2)=ROUND(G82,2),"OK",G82-G92) -> OK | H94: =IF(ROUND(H92,2)=ROUND(H82,2),"OK",H82-H92) -> OK | I94: =IF(ROUND(I92,2)=ROUND(I82,2),"OK",I82-I92) -> OK | J94: =IF(ROUND(J92,2)=ROUND(J82,2),"OK",J82-J92) -> OK | ... P94: =IF(ROUND(P92,2)=ROUND(P82,2),"OK",P82-P92) -> OK
A96: Cash flow statement
B97: Net income | G97: =G71 -> 2195.4604 | H97: =H71 -> 2412.7158 | I97: =I71 -> 2719.2384 | J97: =J71 -> 3036.5028 | K97: =K71 -> 3380.1703 | L97: =L71 -> 3667.6582 | M97: =M71 -> 3912.4175 | N97: =N71 -> 4127.3666 | ... P97: =P71 -> 4380.4176
B98: =B62 -> Depreciation | G98: =G62*-1 -> 442.204 | H98: =H62*-1 -> 496.81344 | I98: =I62*-1 -> 553.34092 | J98: =J62*-1 -> 612.47123 | K98: =K62*-1 -> 659.61503 | L98: =L62*-1 -> 668.60051 | M98: =M62*-1 -> 726.33375 | N98: =N62*-1 -> 766.04729 | ... P98: =P62*-1 -> 835.60457
B99: Change in accounts receivable | G99: =F75-G75 -> -74.356164 | H99: =G75-H75 -> -106.19178 | I99: =H75-I75 -> -79.466743 | J99: =I75-J75 -> -117.42412 | K99: =J75-K75 -> -118.03764 | L99: =K75-L75 -> -122.62416 | M99: =L75-M75 -> -119.15931 | N99: =M75-N75 -> -99.823534 | ... P99: =O75-P75 -> -53.51792
B100: Change in inventories | G100: =F76-G76 -> -54.367882 | H100: =G76-H76 -> -78.211159 | I100: =H76-I76 -> -49.674763 | J100: =I76-J76 -> -80.638255 | K100: =J76-K76 -> -66.748788 | L100: =K76-L76 -> -87.723439 | M100: =L76-M76 -> -85.24474 | N100: =M76-N76 -> -71.41222 | ... P100: =O76-P76 -> -38.285897
B101: Change in other current assets | G101: =F77-G77 -> -46.231 | H101: =G77-H77 -> -51.357 | I101: =H77-I77 -> -42.739148 | J101: =I77-J77 -> -57.146406 | K101: =J77-K77 -> -41.98886 | L101: =K77-L77 -> -58.529456 | M101: =L77-M77 -> -56.875657 | N101: =M77-N77 -> -47.64654 | ... P101: =O77-P77 -> -25.544515
B102: Change in accounts payable | G102: =G85-F85 -> 232.04979 | H102: =H85-G85 -> 225.07433 | I102: =I85-H85 -> 176.38863 | J102: =J85-I85 -> 198.62328 | K102: =K85-J85 -> 192.08818 | L102: =L85-K85 -> 252.44856 | M102: =M85-L85 -> 245.31542 | N102: =N85-M85 -> 205.5085 | ... P102: =P85-O85 -> 110.1783
B103: Cash flow from operations | G103: =SUM(G97:G102) -> 2694.7591 | H103: =SUM(H97:H102) -> 2898.8437 | I103: =SUM(I97:I102) -> 3277.0873 | J103: =SUM(J97:J102) -> 3592.3886 | K103: =SUM(K97:K102) -> 4005.0982 | L103: =SUM(L97:L102) -> 4319.8302 | M103: =SUM(M97:M102) -> 4622.787 | N103: =SUM(N97:N102) -> 4880.0401 | ... P103: =SUM(P97:P102) -> 5208.8521
B105: (Capital expenditure) | G105: =G38*-1 -> -763.436 | H105: =H38*-1 -> -829.328 | I105: =I38*-1 -> -901.16627 | J105: =J38*-1 -> -889.7877 | K105: =K38*-1 -> -958.2798 | L105: =L38*-1 -> -1029.4333 | M105: =M38*-1 -> -974.54341 | N105: =N38*-1 -> -1025.9269 | ... P105: =P38*-1 -> -1008.0259
B106: Change in financial assets | G106: =F81-G81 -> 5.8 | H106: =G81-H81 -> 0 | I106: =H81-I81 -> 0 | J106: =I81-J81 -> 0 | K106: =J81-K81 -> 0 | L106: =K81-L81 -> 0 | M106: =L81-M81 -> 0 | N106: =M81-N81 -> 0 | ... P106: =O81-P81 -> 0
B107: Cash flow from investing activities | G107: =SUM(G105:G106) -> -757.636 | H107: =SUM(H105:H106) -> -829.328 | I107: =SUM(I105:I106) -> -901.16627 | J107: =SUM(J105:J106) -> -889.7877 | K107: =SUM(K105:K106) -> -958.2798 | L107: =SUM(L105:L106) -> -1029.4333 | M107: =SUM(M105:M106) -> -974.54341 | N107: =SUM(N105:N106) -> -1025.9269 | ... P107: =SUM(P105:P106) -> -1008.0259
B109: Dividends | G109: =G45 -> -1317.2762 | H109: =H45 -> -1809.5369 | I109: =I45 -> -2039.4288 | J109: =J45 -> -2277.3771 | K109: =K45 -> -2535.1277 | L109: =L45 -> -2750.7437 | M109: =M45 -> -2934.3131 | N109: =N45 -> -3095.525 | ... P109: =P45 -> -3285.3132
B110: Change in long term debt | G110: =G88-F88 -> 0 | H110: =H88-G88 -> -11.2 | I110: =I88-H88 -> 0 | J110: =J88-I88 -> 0 | K110: =K88-J88 -> 0 | L110: =L88-K88 -> 0 | M110: =M88-L88 -> 0 | N110: =N88-M88 -> 0 | ... P110: =P88-O88 -> 0
B111: Cash flow from financing activities | G111: =SUM(G109:G110) -> -1317.2762 | H111: =SUM(H109:H110) -> -1820.7369 | I111: =SUM(I109:I110) -> -2039.4288 | J111: =SUM(J109:J110) -> -2277.3771 | K111: =SUM(K109:K110) -> -2535.1277 | L111: =SUM(L109:L110) -> -2750.7437 | M111: =SUM(M109:M110) -> -2934.3131 | N111: =SUM(N109:N110) -> -3095.525 | ... P111: =SUM(P109:P110) -> -3285.3132
B113: Beginning cash, net of revolver | G113: =F115 -> 598.1 | H113: =G115 -> 1217.9469 | I113: =H115 -> 1466.7257 | J113: =I115 -> 1803.2179 | K113: =J115 -> 2228.4417 | L113: =K115 -> 2740.1323 | M113: =L115 -> 3279.7857 | N113: =M115 -> 3993.7161 | ... P113: =O115 -> 5634.1773
B114: Net cash flow | G114: =SUM(G103,G107,G111) -> 619.8469 | H114: =SUM(H103,H107,H111) -> 248.7788 | I114: =SUM(I103,I107,I111) -> 336.49222 | J114: =SUM(J103,J107,J111) -> 425.22374 | K114: =SUM(K103,K107,K111) -> 511.69068 | L114: =SUM(L103,L107,L111) -> 539.65331 | M114: =SUM(M103,M107,M111) -> 713.93042 | N114: =SUM(N103,N107,N111) -> 758.58822 | ... P114: =SUM(P103,P107,P111) -> 915.51306
B115: Ending cash, net of revolver | F115: =F74-F84 -> 598.1 | G115: =SUM(G113:G114) -> 1217.9469 | H115: =SUM(H113:H114) -> 1466.7257 | I115: =SUM(I113:I114) -> 1803.2179 | J115: =SUM(J113:J114) -> 2228.4417 | K115: =SUM(K113:K114) -> 2740.1323 | L115: =SUM(L113:L114) -> 3279.7857 | M115: =SUM(M113:M114) -> 3993.7161 | N115: =SUM(N113:N114) -> 4752.3043 | ... P115: =SUM(P113:P114) -> 6549.6903
A117: Interest calculation
B118: Interest on revolver | G118: =AVERAGE(F84:G84)*G31*-1 -> 0 | H118: =AVERAGE(G84:H84)*H31*-1 -> 0 | I118: =AVERAGE(H84:I84)*I31*-1 -> 0 | J118: =AVERAGE(I84:J84)*J31*-1 -> 0 | K118: =AVERAGE(J84:K84)*K31*-1 -> 0 | L118: =AVERAGE(K84:L84)*L31*-1 -> 0 | M118: =AVERAGE(L84:M84)*M31*-1 -> 0 | N118: =AVERAGE(M84:N84)*N31*-1 -> 0 | ... P118: =AVERAGE(O84:P84)*P31*-1 -> 0
B119: Interest on long term debt | G119: =AVERAGE(F88:G88)*G32*-1 -> -28.416 | H119: =AVERAGE(G88:H88)*H32*-1 -> -28.08 | I119: =AVERAGE(H88:I88)*I32*-1 -> -27.744 | J119: =AVERAGE(I88:J88)*J32*-1 -> -27.744 | K119: =AVERAGE(J88:K88)*K32*-1 -> -27.744 | L119: =AVERAGE(K88:L88)*L32*-1 -> -27.744 | M119: =AVERAGE(L88:M88)*M32*-1 -> -27.744 | N119: =AVERAGE(M88:N88)*N32*-1 -> -27.744 | ... P119: =AVERAGE(O88:P88)*P32*-1 -> -27.744
B120: Interest on cash | G120: =AVERAGE(F74:G74)*G33 -> 34.504891 | H120: =AVERAGE(G74:H74)*H33 -> 40.270089 | I120: =AVERAGE(H74:I74)*I33 -> 49.049154 | J120: =AVERAGE(I74:J74)*J33 -> 44.348255 | K120: =AVERAGE(J74:K74)*K33 -> 54.654314 | L120: =AVERAGE(K74:L74)*L33 -> 66.219098 | M120: =AVERAGE(L74:M74)*M33 -> 80.008519 | N120: =AVERAGE(M74:N74)*N33 -> 96.206224 | ... P120: =AVERAGE(O74:P74)*P33 -> 134.02254
A122: Income statement operating statistics
B123: EBIT margin | C123: =C63/C54 -> 0.25719757 | D123: =D63/D54 -> 0.28954656 | E123: =E63/E54 -> 0.2366279 | F123: =F63/F54 -> 0.25905365 | G123: =G63/G54 -> 0.2612753 | H123: =H63/H54 -> 0.26392708 | I123: =I63/I54 -> 0.27324613 | J123: =J63/J54 -> 0.28232329 | ... P123: =P63/P54 -> 0.29172347
...

Sheet WACC
A1: ="Weighted average cost of capital for "&Info!N5 -> Weighted average cost of capital for Red Bull
A2: All figures in USDm unless otherwise stated
F4: Total | G4: Debt / | H4: Historical | I4: Credit | K4: Debt % | L4: Debt % | M4: Unlevered
C5: Company | D5: Ticker | E5: Market Cap | F5: Debt | G5: LTM EBITDA | H5: Beta | I5: Rating | J5: MTR | K5: Capital | L5: Equity | M5: Beta
B7: 1 | C7: =Trading_comps!C11 -> Coca-Cola Company | D7: =Trading_comps!BH11 -> KO-US | E7: =Trading_comps!G11 -> 344591.76 | F7: =Trading_comps!BG11 -> 45492 | G7: =Trading_comps!BD11 -> 2.8320986 | H7: =Trading_comps!BE11 -> 0.57 | I7: =Trading_comps!BF11 -> A+ | J7: 0.21 | K7: =F7/(F7+E7) -> 0.11662111 | L7: =K7/(1-K7) -> 0.13201708 | M7: =H7/(1+(1-J7)*L7) -> 0.51616713
B8: 2 | C8: =Trading_comps!C12 -> Keurig Dr Pepper | D8: =Trading_comps!BH12 -> KDP-US | E8: =Trading_comps!G12 -> 40504.205 | F8: =Trading_comps!BG12 -> 16839 | G8: =Trading_comps!BD12 -> 3.7172185 | H8: =Trading_comps!BE12 -> 0.55 | I8: =Trading_comps!BF12 -> BBB | J8: 0.21 | K8: =F8/(F8+E8) -> 0.29365293 | L8: =K8/(1-K8) -> 0.41573461 | M8: =H8/(1+(1-J8)*L8) -> 0.41402246
B9: 3 | C9: =Trading_comps!C13 -> Monster Beverage | D9: =Trading_comps!BH13 -> MNST-US | E9: =Trading_comps!G13 -> 83024.655 | F9: =Trading_comps!BG13 -> 0 | G9: =Trading_comps!BD13 -> 0 | H9: =Trading_comps!BE13 -> 0.63 | I9: =Trading_comps!BF13 -> N/A | J9: 0.21 | K9: =F9/(F9+E9) -> 0 | L9: =K9/(1-K9) -> 0 | M9: =H9/(1+(1-J9)*L9) -> 0.63
B10: 4 | C10: =Trading_comps!C14 -> PepsiCo | D10: =Trading_comps!BH14 -> PEP-US | E10: =Trading_comps!G14 -> 226465.5 | F10: =Trading_comps!BG14 -> 49182 | G10: =Trading_comps!BD14 -> 2.6783205 | H10: =Trading_comps!BE14 -> 0.6 | I10: =Trading_comps!BF14 -> A+ | J10: 0.21 | K10: =F10/(F10+E10) -> 0.17842353 | L10: =K10/(1-K10) -> 0.21717215 | M10: =H10/(1+(1-J10)*L10) -> 0.51213504
B11: 7 | C11: =Trading_comps!C17 -> Fevertree Drinks | D11: =Trading_comps!BH17 -> FEVR-GB | E11: =Trading_comps!G17 -> 1350 | F11: =Trading_comps!BG17 -> 0 | G11: =Trading_comps!BD17 -> 0 | H11: =Trading_comps!BE17 -> 1.100264 | I11: =Trading_comps!BF17 -> N/A | J11: 0.25 | K11: =F11/(F11+E11) -> 0 | L11: =K11/(1-K11) -> 0 | M11: =H11/(1+(1-J11)*L11) -> 1.100264
C13: Industry average | K13: =AVERAGE(K7:K11) -> 0.11773951 | M13: =AVERAGE(M7:M11) -> 0.63451773
C17: Risk free rate | D17: 0.027
C18: Market risk premium (incl. country risk premium) | D18: =4.23%+0.35% -> 0.0458
C19: Industry average unlevered beta | D19: =M13 -> 0.63451773
C20: Red Bull MTR | D20: ='Red Bull Model'!G20 -> 0.23
C21: Industry average implied debt % of equity | D21: =K13/(1-K13) -> 0.1334521
C22: Relevered beta | D22: =D19*(1+D21*(1-D20)) -> 0.69971957
C23: Cost of equity | D23: =D17+D18*D22 -> 0.059047156
C24: Equity % of capital | D24: =1-K13 -> 0.88226049
C26: Corporate spread | D26: 0.0118
C27: Cost of debt | D27: =D26+D17 -> 0.0388
C28: After tax cost of debt | D28: =D27*(1-D20) -> 0.029876
C29: Debt % of capital | D29: =K13 -> 0.11773951
C31: WACC | D31: =D23*D24+D28*D29 -> 0.055612559
A33: End

Sheet DCF
A1: ="Discounted cashflow valuation for "&Info!N5 -> Discounted cashflow valuation for Red Bull
C2: ='Red Bull Model'!C2 -> Actual | D2: ='Red Bull Model'!D2 -> Actual | E2: ='Red Bull Model'!E2 -> Actual | F2: ='Red Bull Model'!F2 -> Actual | G2: ='Red Bull Model'!G2 -> Actual / Est. | H2: ='Red Bull Model'!H2 -> Actual / Est. | I2: ='Red Bull Model'!I2 -> Projected | J2: ='Red Bull Model'!J2 -> Projected | ... P2: ='Red Bull Model'!P2 -> Projected
C3: ='Red Bull Model'!C3 -> 44196 | D3: =EDATE(C3,12) -> 44561 | E3: =EDATE(D3,12) -> 44926 | F3: =EDATE(E3,12) -> 45291 | G3: =EDATE(F3,12) -> 45657 | H3: =EDATE(G3,12) -> 46022 | I3: =EDATE(H3,12) -> 46387 | J3: =EDATE(I3,12) -> 46752 | K3: =EDATE(J3,12) -> 47118 | ... P3: =EDATE(O3,12) -> 48944
A4: All numbers in EURm unless otherwise stated
A6: Free cash flows
B7: EBITDA | C7: ='Red Bull Model'!C60 -> 1936.4426 | D7: ='Red Bull Model'!D60 -> 2552.4696 | E7: ='Red Bull Model'!E60 -> 2684.2701 | F7: ='Red Bull Model'!F60 -> 3134.0492 | G7: ='Red Bull Model'!G60 -> 3375.5418 | H7: ='Red Bull Model'!H60 -> 3715.6681 | I7: ='Red Bull Model'!I60 -> 4174.5202 | J7: ='Red Bull Model'!J60 -> 4664.2097 | ... P7: ='Red Bull Model'!P60 -> 6601.5812
B8: EBIT | C8: ='Red Bull Model'!C63 -> 1622.2215 | D8: ='Red Bull Model'!D63 -> 2262.9888 | E8: ='Red Bull Model'!E63 -> 2291.5549 | F8: ='Red Bull Model'!F63 -> 2734.0492 | G8: ='Red Bull Model'!G63 -> 2933.3378 | H8: ='Red Bull Model'!H63 -> 3218.8547 | I8: ='Red Bull Model'!I63 -> 3621.1793 | J8: ='Red Bull Model'!J63 -> 4051.7385 | ... P8: ='Red Bull Model'!P63 -> 5765.9766
B9: Long-term effective tax rate | C9: ='Red Bull Model'!C19 -> 0.25736781 | D9: ='Red Bull Model'!D19 -> 0.25534236 | E9: ='Red Bull Model'!E19 -> 0.25835485 | F9: ='Red Bull Model'!F19 -> 0.22162687 | G9: ='Red Bull Model'!G19 -> 0.255 | H9: ='Red Bull Model'!H19 -> 0.255 | I9: ='Red Bull Model'!I19 -> 0.255 | J9: ='Red Bull Model'!J19 -> 0.255 | ... P9: ='Red Bull Model'!P19 -> 0.255
B11: Net operating profit after tax (NOPAT) | E11: =E8*(1-E9) -> 1699.5206 | F11: =F8*(1-F9) -> 2128.1104 | G11: =G8*(1-G9) -> 2185.3367 | H11: =H8*(1-H9) -> 2398.0467 | I11: =I8*(1-I9) -> 2697.7786 | J11: =J8*(1-J9) -> 3018.5452 | K11: =K8*(1-K9) -> 3354.5346 | L11: =L8*(1-L9) -> 3633.4068 | ... P11: =P8*(1-P9) -> 4295.6526
B12: Depreciation & amortization | I12: ='Red Bull Model'!I98 -> 553.34092 | J12: ='Red Bull Model'!J98 -> 612.47123 | K12: ='Red Bull Model'!K98 -> 659.61503 | L12: ='Red Bull Model'!L98 -> 668.60051 | M12: ='Red Bull Model'!M98 -> 726.33375 | N12: ='Red Bull Model'!N98 -> 766.04729 | O12: ='Red Bull Model'!O98 -> 807.62803 | P12: ='Red Bull Model'!P98 -> 835.60457
B13: (Increase) decrease in operating working capital | I13: =SUM('Red Bull Model'!I99:I102) -> 4.5079714 | J13: =SUM('Red Bull Model'!J99:J102) -> -56.585502 | K13: =SUM('Red Bull Model'!K99:K102) -> -34.68711 | L13: =SUM('Red Bull Model'!L99:L102) -> -16.428493 | M13: =SUM('Red Bull Model'!M99:M102) -> -15.964293 | N13: =SUM('Red Bull Model'!N99:N102) -> -13.373794 | O13: =SUM('Red Bull Model'!O99:O102) -> -8.7482706 | P13: =SUM('Red Bull Model'!P99:P102) -> -7.1700291
B14: ='Red Bull Model'!B105 -> (Capital expenditure) | I14: ='Red Bull Model'!I105 -> -901.16627 | J14: ='Red Bull Model'!J105 -> -889.7877 | K14: ='Red Bull Model'!K105 -> -958.2798 | L14: ='Red Bull Model'!L105 -> -1029.4333 | M14: ='Red Bull Model'!M105 -> -974.54341 | N14: ='Red Bull Model'!N105 -> -1025.9269 | O14: ='Red Bull Model'!O105 -> -982.48135 | P14: ='Red Bull Model'!P105 -> -1008.0259
B15: Unlevered free cash flow | I15: =SUM(I11:I14) -> 2354.4612 | J15: =SUM(J11:J14) -> 2684.6432 | K15: =SUM(K11:K14) -> 3021.1827 | L15: =SUM(L11:L14) -> 3256.1455 | M15: =SUM(M11:M14) -> 3603.719 | N15: =SUM(N11:N14) -> 3797.5213 | O15: =SUM(O11:O14) -> 4008.2613 | P15: =SUM(P11:P14) -> 4116.0612
A17: Key ratios
B18: Revenue growth | D18: ='Red Bull Model'!D12 -> 0.23914094 | E18: ='Red Bull Model'!E12 -> 0.23908278 | F18: ='Red Bull Model'!F12 -> 0.08981377 | G18: ='Red Bull Model'!G12 -> 0.063768479 | H18: ='Red Bull Model'!H12 -> 0.086309789 | I18: ='Red Bull Model'!I12 -> 0.086622267 | J18: ='Red Bull Model'!J12 -> 0.082925779 | K18: ='Red Bull Model'!K12 -> 0.076975775 | ... P18: ='Red Bull Model'!P12 -> 0.026
B19: EBIT margin | C19: ='Red Bull Model'!C123 -> 0.25719757 | D19: ='Red Bull Model'!D123 -> 0.28954656 | E19: ='Red Bull Model'!E123 -> 0.2366279 | F19: ='Red Bull Model'!F123 -> 0.25905365 | G19: ='Red Bull Model'!G123 -> 0.2612753 | H19: ='Red Bull Model'!H123 -> 0.26392708 | I19: ='Red Bull Model'!I123 -> 0.27324613 | J19: ='Red Bull Model'!J123 -> 0.28232329 | ... P19: ='Red Bull Model'!P123 -> 0.29172347
B20: Cash conversion ratio | I20: =I15/I11 -> 0.87274071 | J20: =J15/J11 -> 0.88938314 | K20: =K15/K11 -> 0.90062649 | L20: =L15/L11 -> 0.89616873 | M20: =M15/M11 -> 0.93170081 | N20: =N15/N11 -> 0.93287434 | O20: =O15/O11 -> 0.95620048 | P20: =P15/P11 -> 0.95819231
B22: Invested capital | G22: ='Red Bull Model'!G84+'Red Bull Model'!G88+'Red Bull Model'!G91-'Red Bull Model'!G74-'Red Bull Model'!G81 -> 3046.2373 | H22: ='Red Bull Model'!H84+'Red Bull Model'!H88+'Red Bull Model'!H91-'Red Bull Model'!H74-'Red Bull Model'!H81 -> 3389.4374 | I22: ='Red Bull Model'!I84+'Red Bull Model'!I88+'Red Bull Model'!I91-'Red Bull Model'!I74-'Red Bull Model'!I81 -> 3732.7548 | J22: ='Red Bull Model'!J84+'Red Bull Model'!J88+'Red Bull Model'!J91-'Red Bull Model'!J74-'Red Bull Model'!J81 -> 4066.6568 | K22: ='Red Bull Model'!K84+'Red Bull Model'!K88+'Red Bull Model'!K91-'Red Bull Model'!K74-'Red Bull Model'!K81 -> 4400.0087 | L22: ='Red Bull Model'!L84+'Red Bull Model'!L88+'Red Bull Model'!L91-'Red Bull Model'!L74-'Red Bull Model'!L81 -> 4777.2699 | M22: ='Red Bull Model'!M84+'Red Bull Model'!M88+'Red Bull Model'!M91-'Red Bull Model'!M74-'Red Bull Model'!M81 -> 5041.4439 | N22: ='Red Bull Model'!N84+'Red Bull Model'!N88+'Red Bull Model'!N91-'Red Bull Model'!N74-'Red Bull Model'!N81 -> 5314.6973 | ... P22: ='Red Bull Model'!P84+'Red Bull Model'!P88+'Red Bull Model'!P91-'Red Bull Model'!P74-'Red Bull Model'!P81 -> 5677.8902
B23: Invested capital growth rate | H23: =H22/G22-1 -> 0.11266364 | I23: =I22/H22-1 -> 0.10129037 | J23: =J22/I22-1 -> 0.089451891 | K23: =K22/J22-1 -> 0.081971973 | L23: =L22/K22-1 -> 0.085741022 | M23: =M22/L22-1 -> 0.055298102 | N23: =N22/M22-1 -> 0.054201424 | O23: =O22/N22-1 -> 0.03454601 | P23: =P22/O22-1 -> 0.032663071
B24: Return on average invested capital | H24: =H11/AVERAGE(G22:H22) -> 0.74523554 | I24: =I11/AVERAGE(H22:I22) -> 0.75756972 | J24: =J11/AVERAGE(I22:J22) -> 0.77404433 | K24: =K11/AVERAGE(J22:K22) -> 0.79240986 | L24: =L11/AVERAGE(K22:L22) -> 0.79182663 | M24: =M11/AVERAGE(L22:M22) -> 0.78786143 | N24: =N11/AVERAGE(M22:N22) -> 0.78615668 | O24: =O11/AVERAGE(N22:O22) -> 0.7753379 | P24: =P11/AVERAGE(O22:P22) -> 0.76871508
B25: Return on new capital invested | H25: =(H11-G11)/(H22-G22) -> 0.61978426 | I25: =(I11-H11)/(I22-H22) -> 0.87304596 | J25: =(J11-I11)/(J22-I22) -> 0.96066094 | K25: =(K11-J11)/(K22-J22) -> 1.0079121 | L25: =(L11-K11)/(L22-K22) -> 0.73920178 | M25: =(M11-L11)/(M22-L22) -> 0.88762035 | N25: =(N11-M11)/(N22-M22) -> 0.74246756 | O25: =(O11-N11)/(O22-N22) -> 0.65951573 | P25: =(P11-O11)/(P22-O22) -> 0.57792141
A27: Terminal value
B28: Long term growth rate | H28: 0.026
B29: WACC | H29: =WACC!D31 -> 0.055612559
B30: Terminal value using long term growth rate | P30: =P15*(1+ltg)/(WACC-ltg) -> 142611.08
B31: Implied terminal EBITDA LTM multiple | P31: =(P30*(1+WACC)^0.5)/P7 -> 22.195123
A33: Discounting
B34: Year | I34: 0.5 | J34: =I34+1 -> 1.5 | K34: =J34+1 -> 2.5 | L34: =K34+1 -> 3.5 | M34: =L34+1 -> 4.5 | N34: =M34+1 -> 5.5 | O34: =N34+1 -> 6.5 | P34: =O34+1 -> 7.5
B35: Discount factor | I35: =1/(1+WACC)^I34 -> 0.97330225 | J35: =1/(1+WACC)^J34 -> 0.92202602 | K35: =1/(1+WACC)^K34 -> 0.87345117 | L35: =1/(1+WACC)^L34 -> 0.82743537 | M35: =1/(1+WACC)^M34 -> 0.78384381 | N35: =1/(1+WACC)^N34 -> 0.74254877 | O35: =1/(1+WACC)^O34 -> 0.70342927 | P35: =1/(1+WACC)^P34 -> 0.66637069
B36: Present value of free cash flows | I36: =I35*I15 -> 2291.6024 | J36: =J35*J15 -> 2475.3109 | K36: =K35*K15 -> 2638.8556 | L36: =L35*L15 -> 2694.25 | M36: =M35*M15 -> 2824.7528 | N36: =N35*N15 -> 2819.8448 | O36: =O35*O15 -> 2819.5283 | P36: =P35*P15 -> 2742.8226
B37: Sum of present value of free cash flows | H37: =SUM(I36:P36) -> 21306.967
B38: Present value of terminal value | H38: =P30*P35 -> 95031.841
B39: Enterprise value | H39: =SUM(H37:H38) -> 116338.81
B41: Cash and other financial assets | H41: ='Red Bull Model'!H74+'Red Bull Model'!H81 -> 2666.7257
B42: Debt and revolver | H42: ='Red Bull Model'!H84+'Red Bull Model'!H88 -> 462.4
B43: Implied equity value | H43: =H39+H41-H42 -> 118543.13
B44: ="Implied "&YEAR(H3)&" EBITDA multiple" -> Implied 2025 EBITDA multiple | H44: =H39/H7 -> 31.310334
B45: ="Implied forward "&YEAR(I3)&" EBITDA multiple" -> Implied forward 2026 EBITDA multiple | H45: =H39/I7 -> 27.868785
B46: ="Implied forward "&YEAR(J3)&" EBITDA multiple" -> Implied forward 2027 EBITDA multiple | H46: =H39/J7 -> 24.942877
A48: Sensitivity
B49: WACC increment | H49: 0.001
B50: Long term growth rate increment | H50: 0.001
B51: WACC (for sensitivity data tables only, not connected to DCF model) | H51: =WACC!D31 -> 0.055612559
C53: Implied enterprise value
H54: Long-term growth rate
E55: =H39 -> 116338.81 | F55: =G55-$H$50 -> 0.024 | G55: =H55-$H$50 -> 0.025 | H55: 0.026 | I55: =H55+$H$50 -> 0.027 | J55: =I55+$H$50 -> 0.028
E56: =E57+$H$49 -> 0.057612559 | F56: 103522.92 | G56: 106131.91 | H56: 108905.97 | I56: 111861.25 | J56: 115016.14
E57: =E58+$H$49 -> 0.056612559 | F57: 106736.16 | G57: 109527.32 | H57: 112500.84 | I57: 115675.18 | J57: 119071.41
D58: WACC | E58: =H51 -> 0.055612559 | F58: 110153 | G58: 113144.87 | H58: 116338.81 | I58: 119756 | J58: 123420.71
E59: =E58-$H$49 -> 0.054612559 | F59: 113793.38 | G59: 117007.06 | H59: 120445.37 | I59: 124132.72 | J59: 128097.18
E60: =E59-$H$49 -> 0.053612559 | F60: 117679.97 | G60: 121139.55 | H60: 124849.71 | I60: 128838.69 | J60: 133139.16
C62: =B44 -> Implied 2025 EBITDA multiple
H63: Long-term growth rate
E64: =H44 -> 31.310334 | F64: =G64-$H$50 -> 0.024 | G64: =H64-$H$50 -> 0.025 | H64: =H55 -> 0.026 | I64: =H64+$H$50 -> 0.027 | J64: =I64+$H$50 -> 0.028
E65: =E66+$H$49 -> 0.057612559 | F65: 27.861187 | G65: 28.563346 | H65: 29.309928 | I65: 30.105286 | J65: 30.954362
E66: =E67+$H$49 -> 0.056612559 | F66: 28.725968 | G66: 29.477154 | H66: 30.277418 | I66: 31.131731 | J66: 32.045759
D67: WACC | E67: =$E$58 -> 0.055612559 | F67: 29.645542 | G67: 30.450747 | H67: 31.310334 | I67: 32.230005 | J67: 33.216289
E68: =E67-$H$49 -> 0.054612559 | F68: 30.625282 | G68: 31.490181 | H68: 32.415535 | I68: 33.407914 | J68: 34.474872
E69: =E68-$H$49 -> 0.053612559 | F69: 31.671282 | G69: 32.60236 | H69: 33.600877 | I69: 34.674435 | J69: 35.831824
C71: Implied terminal EBITDA multiple
H72: Long-term growth rate
E73: =P31 -> 22.195123 | F73: =G73-$H$50 -> 0.024 | G73: =H73-$H$50 -> 0.025 | H73: =H64 -> 0.026 | I73: =H73+$H$50 -> 0.027 | J73: =I73+$H$50 -> 0.028
E74: =E75+$H$49 -> 0.057612559 | F74: 19.534196 | G74: 20.152835 | H74: 20.810613 | I74: 21.511365 | J74: 22.259445
E75: =E76+$H$49 -> 0.056612559 | F75: 20.123653 | G75: 20.780499 | H75: 21.480257 | I75: 22.227277 | J75: 23.026512
D76: WACC | E76: =$E$58 -> 0.055612559 | F76: 20.750399 | G76: 21.449164 | H76: 22.195123 | I76: 22.993225 | J76: 23.849133
E77: =E76-$H$49 -> 0.054612559 | F77: 21.418086 | G77: 22.162985 | H77: 22.959953 | I77: 23.814646 | J77: 24.73357
E78: =E77-$H$49 -> 0.053612559 | F78: 22.130863 | G78: 22.926697 | H78: 23.780175 | I78: 24.697793 | J78: 25.687065
A80: End

Sheet Trading_comps
A1: Trading comparables
C3: Main currency | D3: USD | F3: EUR/USD | G3: 1.1804
C4: Analysis date | D4: 46076 | F4: GBP/USD | G4: 1.3496
C5: Calendarization date | D5: 46022
C7: ="All data in "&D3&"m unless otherwise stated, as of "&TEXT(D4,"dd-mmm-yy") -> All data in USDm unless otherwise stated, as of 23-Feb-26
E8: Share price | F8: Share price | I8: P/E | L8: Revenue | P8: EBITDA | T8: EBIT | X8: EBITDAR | AB8: EBITR | AF8: EV / Revenue | AJ8: EV / EBITDA | AN8: EV / EBIT | AR8: EVR / EBITDAR | AV8: EVR / EBITR | AY8: LTM EBITDA | AZ8: LT EPS | BA8: Post tax | BB8: CY1 Revenue | BC8: CY2 Revenue | BD8: Debt / | BE8: Historical | BF8: Credit | BG8: Total
C9: Company | D9: Share price $ | E9: 52 week high $ | F9: % of high | G9: Market Cap | H9: EV | I9: 2026e | J9: 2027e | K9: LTM | L9: =I9 -> 2026e | M9: =+J9 -> 2027e | O9: LTM | P9: =L9 -> 2026e | Q9: =M9 -> 2027e | S9: LTM | T9: =P9 -> 2026e | U9: =Q9 -> 2027e | W9: LTM | X9: =L9 -> 2026e | Y9: =M9 -> 2027e | AA9: LTM | AB9: =X9 -> 2026e | AC9: =Y9 -> 2027e | AE9: LTM | AF9: =L9 -> 2026e | AG9: =M9 -> 2027e | AI9: LTM | AJ9: =P9 -> 2026e | AK9: =Q9 -> 2027e | AM9: LTM | AN9: =T9 -> 2026e | AO9: =U9 -> 2027e | AQ9: LTM | AR9: =AJ9 -> 2026e | AS9: =AK9 -> 2027e | AU9: LTM | AV9: =AN9 -> 2026e | AW9: =AO9 -> 2027e | AY9: margin | AZ9: growth (%) | BA9: ROIC | BB9: growth | BC9: growth | BD9: LTM EBITDA | BE9: Beta | BF9: Rating | BG9: Debt | BH9: Ticker
A10: Trading comparables longlist
B11: 1 | C11: {=INDIRECT($B11&"!"&C$70)} -> Coca-Cola Company | D11: {=INDIRECT($B11&"!"&D$70)} -> 79.84 | E11: =INDIRECT($B11&"!"&E$70)*INDIRECT($B11&"!"&E$71) -> 80.41 | F11: =D11/E11 -> 0.99291133 | G11: {=INDIRECT($B11&"!"&G$70)} -> 344591.76 | H11: {=INDIRECT($B11&"!"&H$70)} -> 356148.76 | I11: =INDIRECT($B11&"!"&I$70) -> 24.718266 | J11: =INDIRECT($B11&"!"&J$70) -> 23.075145 | K11: =INDIRECT($B11&"!"&K$70) -> 48062 | L11: =INDIRECT($B11&"!"&L$70) -> 49005 | M11: =INDIRECT($B11&"!"&M$70) -> 49824.7 | O11: =INDIRECT($B11&"!"&O$70) -> 16063 | P11: =INDIRECT($B11&"!"&P$70) -> 17272.8 | Q11: =INDIRECT($B11&"!"&Q$70) -> 18252.1 | S11: =INDIRECT($B11&"!"&S$70) -> 15013 | T11: =INDIRECT($B11&"!"&T$70) -> 16172.8 | U11: =INDIRECT($B11&"!"&U$70) -> 17152.1 | W11: =INDIRECT($B11&"!"&W$70) -> 16452 | X11: =INDIRECT($B11&"!"&X$70) -> 17669.432 | Y11: =INDIRECT($B11&"!"&Y$70) -> 18655.367 | AA11: =INDIRECT($B11&"!"&AA$70) -> 15142.537 | AB11: =INDIRECT($B11&"!"&AB$70) -> 16304.879 | AC11: =INDIRECT($B11&"!"&AC$70) -> 17286.388 | AE11: =IFERROR($H11/K11,"N/A ") -> 7.4101944 | AF11: =IFERROR($H11/L11,"N/A ") -> 7.2676005 | AG11: =IFERROR($H11/M11,"N/A ") -> 7.1480363 | AI11: =IFERROR($H11/O11,"N/A ") -> 22.171996 | AJ11: =IFERROR($H11/P11,"N/A ") -> 20.619052 | AK11: =IFERROR($H11/Q11,"N/A ") -> 19.512756 | AM11: =IFERROR($H11/S11,"N/A ") -> 23.722691 | AN11: =IFERROR($H11/T11,"N/A ") -> 22.021466 | AO11: =IFERROR($H11/U11,"N/A ") -> 20.764149 | AQ11: =IFERROR(INDIRECT($B11&"!"&AQ$70)/W11,"N/A ") -> 21.752417 | AR11: =IFERROR(INDIRECT($B11&"!"&AR$70)/X11,"N/A ") -> 20.253665 | AS11: =IFERROR(INDIRECT($B11&"!"&AS$70)/Y11,"N/A ") -> 19.183261 | AU11: =IFERROR(INDIRECT($B11&"!"&AU$70)/AA11,"N/A ") -> 23.633475 | AV11: =IFERROR(INDIRECT($B11&"!"&AV$70)/AB11,"N/A ") -> 21.948692 | AW11: =IFERROR(INDIRECT($B11&"!"&AW$70)/AC11,"N/A ") -> 20.702461 | AY11: =O11/K11 -> 0.33421414 | AZ11: =INDIRECT($B11&"!"&AZ$70) -> 0.065 | BA11: =INDIRECT($B11&"!"&BA$70) -> 0.26677723 | BB11: =+L11/K11-1 -> 0.01962049 | BC11: =+M11/L11-1 -> 0.016726865 | BD11: =INDIRECT("'"&$B11&"'!"&BD$70)/INDIRECT("'"&$B11&"'!"&BD$71) -> 2.8320986 | BE11: =INDIRECT("'"&$B11&"'!"&BE$70) -> 0.57 | BF11: =INDIRECT("'"&$B11&"'!"&BF$70) -> A+ | BG11: =INDIRECT("'"&$B11&"'!"&BG$70) -> 45492 | BH11: =INDIRECT("'"&$B11&"'!"&BH$70) -> KO-US
B12: 2 | C12: {=INDIRECT($B12&"!"&C$70)} -> Keurig Dr Pepper | D12: {=INDIRECT($B12&"!"&D$70)*INDIRECT($B12&"!"&D$71)} -> 29.54 | E12: =INDIRECT($B12&"!"&E$70)*INDIRECT($B12&"!"&E$71) -> 36.12 | F12: =D12/E12 -> 0.81782946 | G12: =INDIRECT($B12&"!"&G$70) -> 40504.205 | H12: =INDIRECT($B12&"!"&H$70) -> 55157.205 | I12: =INDIRECT($B12&"!"&I$70) -> 13.612903 | J12: =INDIRECT($B12&"!"&J$70) -> 12.787879 | K12: =INDIRECT($B12&"!"&K$70) -> 16174 | L12: =INDIRECT($B12&"!"&L$70) -> 17216.2 | M12: =INDIRECT($B12&"!"&M$70) -> 17827 | O12: =INDIRECT($B12&"!"&O$70) -> 4530 | P12: =INDIRECT($B12&"!"&P$70) -> 5066.4 | Q12: =INDIRECT($B12&"!"&Q$70) -> 5298.7 | S12: =INDIRECT($B12&"!"&S$70) -> 3948 | T12: =INDIRECT($B12&"!"&T$70) -> 4466.4 | U12: =INDIRECT($B12&"!"&U$70) -> 4698.7 | W12: =INDIRECT($B12&"!"&W$70) -> 4709 | X12: =INDIRECT($B12&"!"&X$70) -> 5257.0556 | Y12: =INDIRECT($B12&"!"&Y$70) -> 5496.1197 | AA12: =INDIRECT($B12&"!"&AA$70) -> 4007.607 | AB12: =INDIRECT($B12&"!"&AB$70) -> 4529.8883 | AC12: =INDIRECT($B12&"!"&AC$70) -> 4764.4408 | AE12: =IFERROR($H12/K12,"N/A ") -> 3.410239 | AF12: =IFERROR($H12/L12,"N/A ") -> 3.2037967 | AG12: =IFERROR($H12/M12,"N/A ") -> 3.0940262 | AI12: =IFERROR($H12/O12,"N/A ") -> 12.175983 | AJ12: =IFERROR($H12/P12,"N/A ") -> 10.886863 | AK12: =IFERROR($H12/Q12,"N/A ") -> 10.409573 | AM12: =IFERROR($H12/S12,"N/A ") -> 13.970923 | AN12: =IFERROR($H12/T12,"N/A ") -> 12.349365 | AO12: =IFERROR($H12/U12,"N/A ") -> 11.738822 | AQ12: =IFERROR(INDIRECT($B12&"!"&AQ$70)/W12,"N/A ") -> 11.908092 | AR12: =IFERROR(INDIRECT($B12&"!"&AR$70)/X12,"N/A ") -> 10.666656 | AS12: =IFERROR(INDIRECT($B12&"!"&AS$70)/Y12,"N/A ") -> 10.20269 | AU12: =IFERROR(INDIRECT($B12&"!"&AU$70)/AA12,"N/A ") -> 13.992192 | AV12: =IFERROR(INDIRECT($B12&"!"&AV$70)/AB12,"N/A ") -> 12.378938 | AW12: =IFERROR(INDIRECT($B12&"!"&AW$70)/AC12,"N/A ") -> 11.769525 | AY12: =O12/K12 -> 0.28007914 | AZ12: =INDIRECT($B12&"!"&AZ$70) -> 0.065 | BA12: =INDIRECT($B12&"!"&BA$70) -> 0.075943968 | BB12: =+L12/K12-1 -> 0.06443675 | BC12: =+M12/L12-1 -> 0.035478212 | BD12: =INDIRECT("'"&$B12&"'!"&BD$70)/INDIRECT("'"&$B12&"'!"&BD$71) -> 3.7172185 | BE12: =INDIRECT("'"&$B12&"'!"&BE$70) -> 0.55 | BF12: =INDIRECT("'"&$B12&"'!"&BF$70) -> BBB | BG12: =INDIRECT("'"&$B12&"'!"&BG$70) -> 16839 | BH12: =INDIRECT("'"&$B12&"'!"&BH$70) -> KDP-US
B13: 3 | C13: {=INDIRECT($B13&"!"&C$70)} -> Monster Beverage | D13: {=INDIRECT($B13&"!"&D$70)} -> 83.76 | E13: =INDIRECT($B13&"!"&E$70)*INDIRECT($B13&"!"&E$71) -> 83.98 | F13: =D13/E13 -> 0.99738033 | G13: {=INDIRECT($B13&"!"&G$70)} -> 83024.655 | H13: {=INDIRECT($B13&"!"&H$70)} -> 80086.151 | I13: =INDIRECT($B13&"!"&I$70) -> 37.061947 | J13: =INDIRECT($B13&"!"&J$70) -> 32.847059 | K13: =INDIRECT($B13&"!"&K$70) -> 7975.331 | L13: =INDIRECT($B13&"!"&L$70) -> 9006.9 | M13: =INDIRECT($B13&"!"&M$70) -> 9819.6 | O13: =INDIRECT($B13&"!"&O$70) -> 2552.979 | P13: =INDIRECT($B13&"!"&P$70) -> 2914.6 | Q13: =INDIRECT($B13&"!"&Q$70) -> 3212.8 | S13: =INDIRECT($B13&"!"&S$70) -> 2450.344 | T13: =INDIRECT($B13&"!"&T$70) -> 2834.6 | U13: =INDIRECT($B13&"!"&U$70) -> 3132.8 | W13: =INDIRECT($B13&"!"&W$70) -> 2568.775 | X13: =INDIRECT($B13&"!"&X$70) -> 2933.5882 | Y13: =INDIRECT($B13&"!"&Y$70) -> 3233.5015 | AA13: =INDIRECT($B13&"!"&AA$70) -> 2455.6041 | AB13: =INDIRECT($B13&"!"&AB$70) -> 2840.9231 | AC13: =INDIRECT($B13&"!"&AC$70) -> 3139.6936 | AE13: =IFERROR($H13/K13,"N/A ") -> 10.041734 | AF13: =IFERROR($H13/L13,"N/A ") -> 8.8916443 | AG13: =IFERROR($H13/M13,"N/A ") -> 8.1557447 | AI13: =IFERROR($H13/O13,"N/A ") -> 31.369686 | AJ13: =IFERROR($H13/P13,"N/A ") -> 27.477579 | AK13: =IFERROR($H13/Q13,"N/A ") -> 24.927213 | AM13: =IFERROR($H13/S13,"N/A ") -> 32.683636 | AN13: =IFERROR($H13/T13,"N/A ") -> 28.253069 | AO13: =IFERROR($H13/U13,"N/A ") -> 25.563761 | AQ13: =IFERROR(INDIRECT($B13&"!"&AQ$70)/W13,"N/A ") -> 31.198738 | AR13: =IFERROR(INDIRECT($B13&"!"&AR$70)/X13,"N/A ") -> 27.318946 | AS13: =IFERROR(INDIRECT($B13&"!"&AS$70)/Y13,"N/A ") -> 24.785063 | AU13: =IFERROR(INDIRECT($B13&"!"&AU$70)/AA13,"N/A ") -> 32.636588 | AV13: =IFERROR(INDIRECT($B13&"!"&AV$70)/AB13,"N/A ") -> 28.210034 | AW13: =IFERROR(INDIRECT($B13&"!"&AW$70)/AC13,"N/A ") -> 25.525592 | AY13: =O13/K13 -> 0.32010947 | AZ13: =INDIRECT($B13&"!"&AZ$70) -> 0.125 | BA13: =INDIRECT($B13&"!"&BA$70) -> 0.40274074 | BB13: =+L13/K13-1 -> 0.12934498 | BC13: =+M13/L13-1 -> 0.090230823 | BD13: =INDIRECT("'"&$B13&"'!"&BD$70)/INDIRECT("'"&$B13&"'!"&BD$71) -> 0 | BE13: =INDIRECT("'"&$B13&"'!"&BE$70) -> 0.63 | BF13: =INDIRECT("'"&$B13&"'!"&BF$70) -> N/A | BG13: =INDIRECT("'"&$B13&"'!"&BG$70) -> 0 | BH13: =INDIRECT("'"&$B13&"'!"&BH$70) -> MNST-US
B14: 4 | C14: PepsiCo | D14: 164.94 | E14: 171.48 | F14: =D14/E14 -> 0.96186144 | G14: 226465.5 | H14: 262775.5 | I14: 19.1 | J14: =D14/9.2 -> 17.928261 | K14: 93925 | L14: 98553.2 | M14: 101645.2 | O14: 18363 | P14: 19494.6 | Q14: 20515.6 | S14: =O14-3451 -> 14912 | T14: =P14-3451 -> 16043.6 | U14: =Q14-3451 -> 17064.6 | AE14: =IFERROR($H14/K14,"N/A ") -> 2.7977163 | AF14: =IFERROR($H14/L14,"N/A ") -> 2.6663315 | AG14: =IFERROR($H14/M14,"N/A ") -> 2.5852229 | AI14: =IFERROR($H14/O14,"N/A ") -> 14.310053 | AJ14: =IFERROR($H14/P14,"N/A ") -> 13.479399 | AK14: =IFERROR($H14/Q14,"N/A ") -> 12.80857 | AM14: =IFERROR($H14/S14,"N/A ") -> 17.621748 | AN14: =IFERROR($H14/T14,"N/A ") -> 16.378836 | AO14: =IFERROR($H14/U14,"N/A ") -> 15.398867 | AY14: =O14/K14 -> 0.19550705 | AZ14: 0.078 | BA14: 0.14 | BB14: =+L14/K14-1 -> 0.049275486 | BC14: =+M14/L14-1 -> 0.031373918 | BD14: =BG14/O14 -> 2.6783205 | BE14: 0.6 | BF14: A+ | BG14: 49182 | BH14: PEP-US
B15: 5 | C15: Danone | D15: =73.6*G3 -> 86.87744 | E15: =80.14*G3 -> 94.597256 | F15: =D15/E15 -> 0.91839281 | G15: =47110*G3 -> 55608.644 | H15: =55640*G3 -> 65677.456 | I15: 18.36 | J15: =D15/(4.34*G3) -> 16.958525 | K15: 32204.853 | L15: 33183.877 | M15: 34531.894 | O15: 5542.5682 | P15: 5872.608 | Q15: 6176.0889 | S15: =O15-1168 -> 4374.5682 | T15: =P15-1168 -> 4704.608 | U15: =Q15-1168 -> 5008.0889 | AE15: =IFERROR($H15/K15,"N/A ") -> 2.0393652 | AF15: =IFERROR($H15/L15,"N/A ") -> 1.9791978 | AG15: =IFERROR($H15/M15,"N/A ") -> 1.9019361 | AI15: =IFERROR($H15/O15,"N/A ") -> 11.849643 | AJ15: =IFERROR($H15/P15,"N/A ") -> 11.183695 | AK15: =IFERROR($H15/Q15,"N/A ") -> 10.63415 | AM15: =IFERROR($H15/S15,"N/A ") -> 15.013472 | AN15: =IFERROR($H15/T15,"N/A ") -> 13.96024 | AO15: =IFERROR($H15/U15,"N/A ") -> 13.114275 | AY15: =O15/K15 -> 0.17210351 | AZ15: 0.05 | BA15: 0.055 | BB15: =+L15/K15-1 -> 0.030399883 | BC15: =+M15/L15-1 -> 0.040622643 | BD15: =BG15/O15 -> 2.8147601 | BE15: 0.5 | BF15: BBB+ | BG15: =10447+5154 -> 15601 | BH15: BN-FR
B16: 6 | C16: National Beverage | D16: 37.01 | E16: 47.89 | F16: =D16/E16 -> 0.7728127 | G16: 3467.8 | H16: 3198.7 | I16: 18.1 | J16: =D16/2.06 -> 17.966019 | K16: 1119.5 | L16: 1198.4 | M16: 1209.3 | O16: 260.2 | P16: 257.7 | Q16: 257.1 | S16: =O16-20.801 -> 239.399 | T16: =P16-20.801 -> 236.899 | U16: =Q16-20.801 -> 236.299 | AE16: =IFERROR($H16/K16,"N/A ") -> 2.8572577 | AF16: =IFERROR($H16/L16,"N/A ") -> 2.6691422 | AG16: =IFERROR($H16/M16,"N/A ") -> 2.6450839 | AI16: =IFERROR($H16/O16,"N/A ") -> 12.293236 | AJ16: =IFERROR($H16/P16,"N/A ") -> 12.412495 | AK16: =IFERROR($H16/Q16,"N/A ") -> 12.441462 | AM16: =IFERROR($H16/S16,"N/A ") -> 13.361376 | AN16: =IFERROR($H16/T16,"N/A ") -> 13.502379 | AO16: =IFERROR($H16/U16,"N/A ") -> 13.536663 | AY16: =O16/K16 -> 0.23242519 | AZ16: N/A | BA16: 0.39888127 | BB16: =+L16/K16-1 -> 0.070477892 | BC16: =+M16/L16-1 -> 0.0090954606 | BD16: =BG16/O16 -> 0 | BE16: 0.588622 | BF16: N/A | BG16: 0 | BH16: FIZZ-US
B17: 7 | C17: Fevertree Drinks | D17: =9.48*G4 -> 12.794208 | E17: =10.2*G4 -> 13.76592 | F17: =D17/E17 -> 0.92941176 | G17: 1350 | H17: 1180 | I17: =D17/(0.28*G4) -> 33.857143 | J17: =D17/(0.37*G4) -> 25.621622 | K17: =375.3*G4 -> 506.50488 | L17: =395.6*G4 -> 533.90176 | M17: =436.7*G4 -> 589.37032 | O17: 59.78728 | P17: 67.48 | Q17: 86.91424 | S17: =O17-6.5-3.1 -> 50.18728 | T17: =P17-6.5-3.1 -> 57.88 | U17: =Q17-6.5-3.1 -> 77.31424 | AE17: =IFERROR($H17/K17,"N/A ") -> 2.3296913 | AF17: =IFERROR($H17/L17,"N/A ") -> 2.2101444 | AG17: =IFERROR($H17/M17,"N/A ") -> 2.0021368 | AI17: =IFERROR($H17/O17,"N/A ") -> 19.73664 | AJ17: =IFERROR($H17/P17,"N/A ") -> 17.486663 | AK17: =IFERROR($H17/Q17,"N/A ") -> 13.576601 | AM17: =IFERROR($H17/S17,"N/A ") -> 23.511934 | AN17: =IFERROR($H17/T17,"N/A ") -> 20.387008 | AO17: =IFERROR($H17/U17,"N/A ") -> 15.262389 | AY17: =O17/K17 -> 0.1180389 | AZ17: 0.152 | BA17: 0.04969722 | BB17: =+L17/K17-1 -> 0.054090061 | BC17: =+M17/L17-1 -> 0.10389282 | BD17: =BG17/O17 -> 0 | BE17: 1.100264 | BF17: N/A | BG17: 0 | BH17: FEVR-GB
B18: 8 | C18: Celsius | D18: 48.32 | E18: 66.74 | F18: =D18/E18 -> 0.7240036 | G18: 12662.3 | H18: 13579.5 | I18: =D18/1.5 -> 32.213333 | J18: =D18/1.83 -> 26.404372 | K18: 2125.9 | L18: 2443.1 | M18: 3227.7 | O18: 547.9 | P18: 601.5 | Q18: 736.1 | S18: =O18-7.274 -> 540.626 | T18: =P18-7.274 -> 594.226 | U18: =Q18-7.274 -> 728.826 | AE18: =IFERROR($H18/K18,"N/A ") -> 6.3876476 | AF18: =IFERROR($H18/L18,"N/A ") -> 5.5583071 | AG18: =IFERROR($H18/M18,"N/A ") -> 4.2071754 | AI18: =IFERROR($H18/O18,"N/A ") -> 24.784632 | AJ18: =IFERROR($H18/P18,"N/A ") -> 22.57606 | AK18: =IFERROR($H18/Q18,"N/A ") -> 18.447901 | AM18: =IFERROR($H18/S18,"N/A ") -> 25.118104 | AN18: =IFERROR($H18/T18,"N/A ") -> 22.852416 | AO18: =IFERROR($H18/U18,"N/A ") -> 18.632019 | AY18: =O18/K18 -> 0.25772614 | AZ18: 0.2 | BA18: 0.232 | BB18: =+L18/K18-1 -> 0.14920739 | BC18: =+M18/L18-1 -> 0.32114936 | BD18: =BG18/O18 -> 3.144917 | BE18: 1.57426 | BF18: N/A | BG18: 1723.1 | BH18: CELH-US
C20: Median | AY20: =MEDIAN(AY11:AY18) -> 0.24507566 | BB20: =MEDIAN(BB11:BB18) -> 0.059263406 | BC20: =MEDIAN(BC11:BC18) -> 0.038050428
C21: Average | AY21: =AVERAGE((AY11:AY18)) -> 0.23877544 | BB21: =AVERAGE((BB11:BB18)) -> 0.070856617 | BC21: =AVERAGE((BC11:BC18)) -> 0.081071263
C23: Red Bull | K23: ='Red Bull Model'!F54 -> 10553.988 | L23: ='Red Bull Model'!G54 -> 11227 | M23: ='Red Bull Model'!H54 -> 12196 | O23: ='Red Bull Model'!F60 -> 3134.0492 | P23: ='Red Bull Model'!G60 -> 3375.5418 | Q23: ='Red Bull Model'!H60 -> 3715.6681 | S23: ='Red Bull Model'!F63 -> 2734.0492 | T23: ='Red Bull Model'!G63 -> 2933.3378 | U23: ='Red Bull Model'!H63 -> 3218.8547 | AY23: ='Red Bull Model'!F60/'Red Bull Model'!F54 -> 0.29695402 | BB23: ='Red Bull Model'!G12 -> 0.063768479 | BC23: ='Red Bull Model'!H12 -> 0.086309789
I25: P/E | AF25: EV / Revenue | AJ25: EV / EBITDA | AN25: EV / EBIT | AR25: EVR / EBITDAR | AV25: EVR / EBITR | AY25: LTM EBITDA / | AZ25: LT EPS
C26: Company | I26: =+AN9 -> 2026e | J26: =+AO9 -> 2027e | AE26: =AE9 -> LTM | AF26: =AF9 -> 2026e | AG26: =AG9 -> 2027e | AI26: =AI9 -> LTM | AJ26: =AJ9 -> 2026e | AK26: =AK9 -> 2027e | AM26: =AM9 -> LTM | AN26: =AN9 -> 2026e | AO26: =AO9 -> 2027e | AQ26: =AQ9 -> LTM | AR26: =AR9 -> 2026e | AS26: =AS9 -> 2027e | AU26: =AU9 -> LTM | AV26: =AV9 -> 2026e | AW26: =AW9 -> 2027e | AY26: Revenue | AZ26: growth (%)
A27: Trading comparables shortlist
B28: =B11 -> 1 | C28: =OFFSET(C$10,$B28,0) -> Coca-Cola Company | I28: =OFFSET(I$10,$B28,0) -> 24.718266 | J28: =OFFSET(J$10,$B28,0) -> 23.075145 | AE28: =OFFSET(AE$10,$B28,0) -> 7.4101944 | AF28: =OFFSET(AF$10,$B28,0) -> 7.2676005 | AG28: =OFFSET(AG$10,$B28,0) -> 7.1480363 | AI28: =OFFSET(AI$10,$B28,0) -> 22.171996 | AJ28: =OFFSET(AJ$10,$B28,0) -> 20.619052 | AK28: =OFFSET(AK$10,$B28,0) -> 19.512756 | AM28: =OFFSET(AM$10,$B28,0) -> 23.722691 | AN28: =OFFSET(AN$10,$B28,0) -> 22.021466 | AO28: =OFFSET(AO$10,$B28,0) -> 20.764149 | AQ28: =AQ11 -> 21.752417 | AR28: =AR11 -> 20.253665 | AS28: =AS11 -> 19.183261 | AU28: =AU11 -> 23.633475 | AV28: =AV11 -> 21.948692 | AW28: =AW11 -> 20.702461 | AY28: =OFFSET(AY$10,$B28,0) -> 0.33421414 | AZ28: =OFFSET(AZ$10,$B28,0) -> 0.065
B29: 3 | C29: =OFFSET(C$10,$B29,0) -> Monster Beverage | I29: =OFFSET(I$10,$B29,0) -> 37.061947 | J29: =OFFSET(J$10,$B29,0) -> 32.847059 | AE29: =OFFSET(AE$10,$B29,0) -> 10.041734 | AF29: =OFFSET(AF$10,$B29,0) -> 8.8916443 | AG29: =OFFSET(AG$10,$B29,0) -> 8.1557447 | AI29: =OFFSET(AI$10,$B29,0) -> 31.369686 | AJ29: =OFFSET(AJ$10,$B29,0) -> 27.477579 | AK29: =OFFSET(AK$10,$B29,0) -> 24.927213 | AM29: =OFFSET(AM$10,$B29,0) -> 32.683636 | AN29: =OFFSET(AN$10,$B29,0) -> 28.253069 | AO29: =OFFSET(AO$10,$B29,0) -> 25.563761 | AY29: =OFFSET(AY$10,$B29,0) -> 0.32010947 | AZ29: =OFFSET(AZ$10,$B29,0) -> 0.125
B30: 4 | C30: =OFFSET(C$10,$B30,0) -> PepsiCo | I30: =OFFSET(I$10,$B30,0) -> 19.1 | J30: =OFFSET(J$10,$B30,0) -> 17.928261 | AE30: =OFFSET(AE$10,$B30,0) -> 2.7977163 | AF30: =OFFSET(AF$10,$B30,0) -> 2.6663315 | AG30: =OFFSET(AG$10,$B30,0) -> 2.5852229 | AI30: =OFFSET(AI$10,$B30,0) -> 14.310053 | AJ30: =OFFSET(AJ$10,$B30,0) -> 13.479399 | AK30: =OFFSET(AK$10,$B30,0) -> 12.80857 | AM30: =OFFSET(AM$10,$B30,0) -> 17.621748 | AN30: =OFFSET(AN$10,$B30,0) -> 16.378836 | AO30: =OFFSET(AO$10,$B30,0) -> 15.398867 | AY30: =OFFSET(AY$10,$B30,0) -> 0.19550705 | AZ30: =OFFSET(AZ$10,$B30,0) -> 0.078
C32: Median | J32: =MEDIAN(J28:J30) -> 23.075145 | AK32: =MEDIAN(AK28:AK30) -> 19.512756
C34: Red Bull 2027 net income | J34: ='Red Bull Model'!H71 -> 2412.7158
C35: Implied equity value | J35: =J34*J32 -> 55673.767
C37: Red Bull 2027 EBITDA | AK37: ='Red Bull Model'!J60 -> 4664.2097
C38: Implied enterprise value | AK38: =AK37*AK32 -> 91011.584
C39: Net debt/(cash) | AK39: ='Red Bull Model'!J136 -> -1766.0417
C40: Implied equity value | AK40: =AK38-AK39 -> 92777.625
A42: End
A69: DO NOT DELETE
C70: COMPANY_NAME | D70: COMP_SHAREPRICE | E70: SHAREPRICE_HIGH | G70: COMP_EQ_VALUE | H70: COMP_EV | I70: PE_CY1 | J70: PE_CY2 | K70: SALES_LTM | L70: SALES_CY1 | M70: SALES_CY2 | O70: EBITDA_LTM | P70: EBITDA_CY1 | Q70: EBITDA_CY2 | S70: EBIT_LTM | T70: EBIT_CY1 | U70: EBIT_CY2 | W70: EBITDAR_LTM | X70: EBITDAR_CY1 | Y70: EBITDAR_CY2 | AA70: EBITR_LTM | AB70: EBITR_CY1 | AC70: EBITR_CY2 | AQ70: EVR | AR70: EVR | AS70: EVR | AU70: EVR | AV70: EVR | AW70: EVR | AZ70: EPS_5YR_GROWTH | BA70: ROIC | BD70: TOTAL_DEBT | BE70: BETA | BF70: CREDIT_RATING | BG70: TOTAL_DEBT | BH70: Ticker
D71: COMP_FX | E71: COMP_FX | G71: PE_CY1 | H71: PE_CY2 | BD71: EBITDA_LTM

Sheet 1
A1: Coca-Cola Company
E2: Analyst name | G2: Amgad Bashir
A4: Key data | E4: Enterprise value summary
B5: Ticker | C5: KO-US | E5: ="Enterprise value calculation in "&MAIN_CURRENCY&" MM" -> Enterprise value calculation in USD MM
B6: Country | C6: United States | E6: + Diluted equity value | H6: =D36*'1'!COMP_FX -> 344591.76
B7: Analysis date | C7: =ANALYSIS_DATE -> 46076 | E7: + Debt | H7: =SUM(G31:G33)*'1'!COMP_FX -> 45492
B8: Calendarize to | C8: =Trading_comps!D5 -> 46022 | E8: - Cash and ST investments | H8: =SUM(J31:J32)*'1'!COMP_FX -> 15806
B9: Currency / FX | C9: =MAIN_CURRENCY -> USD | E9: - Other adjustments | H9: =(SUM(J33:J37)-SUM(G34:G37))*'1'!COMP_FX -> 18129
B10: Marginal tax rate | C10: 0.223 | E10: = Enterprise value | H10: ='1'!COMP_EQ_VALUE+'1'!TOTAL_DEBT-H8-H9 -> 356148.76
B11: Historical year end | C11: 46022
B12: Last filing date US format | C12: 12/31/2025 | E12: Calendarized key numbers
B13: Last filing date Intl format | C13: =DATE(RIGHT(C12,4),LEFT(C12,2),MID(C12,4,2)) -> 46022 | E13: ="Numbers in "&MAIN_CURRENCY&" MM" -> Numbers in USD MM | G13: LTM | H13: =YEAR($C$8)+1&"e" -> 2026e | I13: =YEAR($C$8)+2&"e" -> 2027e | J13: =YEAR($C$8)+3&"e" -> 2028e | K13: =YEAR($C$8)+4&"e" -> 2029e
B14: Home currency | C14: USD | E14: Revenue | G14: =G44*'1'!COMP_FX -> 48062 | H14: =IF(I$80>0,SUMPRODUCT('1'!COMP_CALENDARIZE_PERCENTAGES,H44:J44)*I$81*'1'!COMP_FX,"N/A") -> 49005 | I14: =IF(J$80>0,SUMPRODUCT('1'!COMP_CALENDARIZE_PERCENTAGES,I44:K44)*J$81*'1'!COMP_FX,"N/A") -> 49824.7 | J14: =IF(K$80>0,SUMPRODUCT('1'!COMP_CALENDARIZE_PERCENTAGES,J44:L44)*K$81*'1'!COMP_FX,"N/A") -> 52528.6 | K14: =IF(L$80>0,SUMPRODUCT('1'!COMP_CALENDARIZE_PERCENTAGES,K44:M44)*L$81*'1'!COMP_FX,"N/A") -> N/A
B15: FX rate | C15: 1 | E15: EBITDA | G15: =G55*'1'!COMP_FX -> 16063 | H15: =IF(I$80>0,SUMPRODUCT('1'!COMP_CALENDARIZE_PERCENTAGES,H55:J55)*I$81*'1'!COMP_FX,"N/A") -> 17272.8 | I15: =IF(J$80>0,SUMPRODUCT('1'!COMP_CALENDARIZE_PERCENTAGES,I55:K55)*J$81*'1'!COMP_FX,"N/A") -> 18252.1 | J15: =IF(K$80>0,SUMPRODUCT('1'!COMP_CALENDARIZE_PERCENTAGES,J55:L55)*K$81*'1'!COMP_FX,"N/A") -> 19728.3 | K15: =IF(L$80>0,SUMPRODUCT('1'!COMP_CALENDARIZE_PERCENTAGES,K55:M55)*L$81*'1'!COMP_FX,"N/A") -> N/A
B16: Last closing price | C16: 79.84 | E16: EBIT | G16: =G53*'1'!COMP_FX -> 15013 | H16: =IF(I$80>0,SUMPRODUCT('1'!COMP_CALENDARIZE_PERCENTAGES,H53:J53)*I$81*'1'!COMP_FX,"N/A") -> 16172.8 | I16: =IF(J$80>0,SUMPRODUCT('1'!COMP_CALENDARIZE_PERCENTAGES,I53:K53)*J$81*'1'!COMP_FX,"N/A") -> 17152.1 | J16: =IF(K$80>0,SUMPRODUCT('1'!COMP_CALENDARIZE_PERCENTAGES,J53:L53)*K$81*'1'!COMP_FX,"N/A") -> 18628.3 | K16: =IF(L$80>0,SUMPRODUCT('1'!COMP_CALENDARIZE_PERCENTAGES,K53:M53)*L$81*'1'!COMP_FX,"N/A") -> N/A
B17: 52 week low | C17: 65.35 | E17: EPS | H17: =IF(I$80>0,SUMPRODUCT('1'!COMP_CALENDARIZE_PERCENTAGES,H56:J56)*I$81*'1'!COMP_FX,"N/A") -> 3.23 | I17: =IF(J$80>0,SUMPRODUCT('1'!COMP_CALENDARIZE_PERCENTAGES,I56:K56)*J$81*'1'!COMP_FX,"N/A") -> 3.46 | J17: =IF(K$80>0,SUMPRODUCT('1'!COMP_CALENDARIZE_PERCENTAGES,J56:L56)*K$81*'1'!COMP_FX,"N/A") -> 3.7 | K17: =IF(L$80>0,SUMPRODUCT('1'!COMP_CALENDARIZE_PERCENTAGES,K56:M56)*L$81*'1'!COMP_FX,"N/A") -> N/A
B18: 52 week high | C18: 80.41
B19: Credit rating | C19: A+ | E19: Calendarized multiples to December 31
B20: Beta | C20: 0.57 | G20: =G13 -> LTM | H20: =H13 -> 2026e | I20: =I13 -> 2027e | J20: =J13 -> 2028e | K20: =K13 -> 2029e
B21: 5 year EPS forward growth | C21: 0.065 | E21: EV / Revenue | G21: =IF(G14<>0,$H$10/G14,"N/A") -> 7.4101944 | H21: =IF(ISNUMBER(H14),$H$10/H14,"N/A") -> 7.2676005 | I21: =IF(ISNUMBER(I14),$H$10/I14,"N/A") -> 7.1480363 | J21: =IF(ISNUMBER(J14),$H$10/J14,"N/A") -> 6.7800925 | K21: =IFERROR($H$10/K14,"N/A") -> N/A
B22: LTM EBIT margin | C22: =G53/G44 -> 0.31236736 | E22: EV / EBITDA | G22: =IF(G15<>0,$H$10/G15,"N/A") -> 22.171996 | H22: =IF(ISNUMBER(H15),$H$10/H15,"N/A") -> 20.619052 | I22: =IF(ISNUMBER(I15),$H$10/I15,"N/A") -> 19.512756 | J22: =IF(ISNUMBER(J15),$H$10/J15,"N/A") -> 18.052684 | K22: =IFERROR($H$10/K15,"N/A") -> N/A
B23: Return on invested capital | C23: =G53*(1-'1'!COMP_MTR)/D39 -> 0.26677723 | E23: EV / EBIT | G23: =IF(G16<>0,$H$10/G16,"N/A") -> 23.722691 | H23: =IF(ISNUMBER(H16),$H$10/H16,"N/A") -> 22.021466 | I23: =IF(ISNUMBER(I16),$H$10/I16,"N/A") -> 20.764149 | J23: =IF(ISNUMBER(J16),$H$10/J16,"N/A") -> 19.118694 | K23: =IFERROR($H$10/K16,"N/A") -> N/A
E24: PE | H24: =IF(ISNUMBER(H17),($C$16*'1'!COMP_FX)/H17,"N/A") -> 24.718266 | I24: =IF(ISNUMBER(I17),($C$16*'1'!COMP_FX)/I17,"N/A") -> 23.075145 | J24: =IF(ISNUMBER(J17),($C$16*'1'!COMP_FX)/J17,"N/A") -> 21.578378 | K24: =IFERROR(($C$16*'1'!COMP_FX)/K17,"N/A") -> N/A
E25: P / BV | G25: =D36/D37 -> 10.71192
E26: Total debt / LTM EBITDA | G26: =IF(G15=0,"N/A",H7/G15) -> 2.8320986
A28: Enterprise value calculation (home currency) | M28: Share options and RSUs
M29: Tranche | N29: Number | O29: Strike | P29: New shares
B30: Equity valuation | E30: Financial liabilities calculation | H30: Financial assets calculation | M30: Options | N30: 27 | O30: 55.74 | P30: =MAX(('1'!COMP_SHAREPRICE-O30)/'1'!COMP_SHAREPRICE*N30,0) -> 8.1500501
B31: Shares outstanding as of | D31: 46071 | E31: Debt - short term | G31: 1551 | H31: Cash and ST investments | J31: =10270+3602 -> 13872 | M31: Performance share units | N31: 2.62 | O31: 0 | P31: =MAX(('1'!COMP_SHAREPRICE-O31)/'1'!COMP_SHAREPRICE*N31,0) -> 2.62
B32: Basic shares outstanding | D32: 4300.7231 | E32: Debt - current maturities | G32: 1822 | H32: Marketable securities | J32: 1934 | M32: Time based RSUs | N32: 4.536 | O32: 0 | P32: =MAX(('1'!COMP_SHAREPRICE-O32)/'1'!COMP_SHAREPRICE*N32,0) -> 4.536
B33: Other adjustments | D33: 0 | E33: Debt - long term | G33: 42119 | H33: Equity method investments | J33: 20235 | M33: Tranche 4 | N33: 0 | O33: 0 | P33: =MAX(('1'!COMP_SHAREPRICE-O33)/'1'!COMP_SHAREPRICE*N33,0) -> 0
B34: Dilution from share options | D34: =P38 -> 15.30605 | E34: Preferred equity | G34: 0 | H34: Other investments | J34: 0 | M34: Tranche 5 | N34: 0 | O34: 0 | P34: =MAX(('1'!COMP_SHAREPRICE-O34)/'1'!COMP_SHAREPRICE*N34,0) -> 0
B35: Diluted shares outstanding | D35: =SUM(D32:D34) -> 4316.0291 | E35: NCI | G35: 2106 | H35: Other | J35: 0 | M35: Tranche 6 | N35: 0 | O35: 0 | P35: =MAX(('1'!COMP_SHAREPRICE-O35)/'1'!COMP_SHAREPRICE*N35,0) -> 0
B36: Diluted equity value | D36: =D35*'1'!COMP_SHAREPRICE -> 344591.76 | E36: Other | G36: 0 | H36: Other | J36: 0 | M36: Tranche 7 | N36: 0 | O36: 0 | P36: =MAX(('1'!COMP_SHAREPRICE-O36)/'1'!COMP_SHAREPRICE*N36,0) -> 0
B37: Shareholders' equity | D37: 32169 | E37: Other | G37: 0 | H37: Other | J37: 0 | M37: Tranche 8 | N37: 0 | O37: 0 | P37: =MAX(('1'!COMP_SHAREPRICE-O37)/'1'!COMP_SHAREPRICE*N37,0) -> 0
B38: Net debt and other adjustments | D38: =G39-J39 -> 11557 | M38: Total | P38: =SUM(P30:P37) -> 15.30605
B39: Invested capital | D39: =D37+D38 -> 43726 | E39: Total financial liabilities | G39: =SUM(G31:G37) -> 47598 | H39: Total financial assets | J39: =SUM(J31:J37) -> 36041
A41: Earnings (home currency) | I41: Consensus estimates
C42: Annual | D42: Old 10-Q/Interim | E42: New 10-Q/interim | F42: Other adjustments | G42: Adj. LTM | H42: Fiscal Year | I42: FY +1 | J42: FY +2 | K42: FY +3 | L42: FY +4
B43: Date | C43: =C11 -> 46022 | D43: 0 | E43: 0 | G43: =C13 -> 46022 | H43: =C43 -> 46022 | I43: =EDATE(C43,12) -> 46387 | J43: =EDATE(I43,12) -> 46752 | K43: =EDATE(J43,12) -> 47118 | L43: =EDATE(K43,12) -> 47483
B44: Revenue | C44: 48062 | D44: 0 | E44: 0 | F44: 0 | G44: =C44-D44+E44+F44 -> 48062 | H44: =C44 -> 48062 | I44: 49005 | J44: 49824.7 | K44: 52528.6 | L44: N/A | N44: Source: Felix 23rd February 2026
B45: CapIQ EBIT | C45: 13318 | D45: 0 | E45: 0
B46: Adjusted operating profit | C46: 15013 | D46: 0 | E46: 0
B47: Further adjustments | C47: 0 | D47: 0 | E47: 0
B48: Further adjustments | C48: 0 | D48: 0 | E48: 0
B49: Further adjustments | C49: 0 | D49: 0 | E49: 0
A50: 1 | B50: Further adjustments | C50: 0 | D50: 0 | E50: 0
B51: Further adjustments | C51: 0 | D51: 0 | E51: 0
B52: Further adjustments | C52: 0 | D52: 0 | E52: 0
B53: EBIT | C53: =SUM(C46:C52) -> 15013 | D53: =SUM(D46:D52) -> 0 | E53: =SUM(E46:E52) -> 0 | F53: =SUM(F46:F52) -> 0 | G53: =C53-D53+E53+F53 -> 15013 | H53: =C53 -> 15013 | I53: =I55-I54 -> 16172.8 | J53: =J55-J54 -> 17152.1 | K53: =K55-K54 -> 18628.3 | L53: N/A
B54: Depreciation and amortization | C54: 1050 | D54: 0 | E54: 0 | F54: 0 | G54: =C54-D54+E54+F54 -> 1050 | H54: =C54 -> 1050 | I54: 1100 | J54: 1100 | K54: 1100 | L54: N/A
B55: EBITDA (consolidated) | C55: =C53+C54 -> 16063 | D55: =D53+D54 -> 0 | E55: =E53+E54 -> 0 | G55: =C55-D55+E55+F55 -> 16063 | H55: =C55 -> 16063 | I55: 17272.8 | J55: 18252.1 | K55: 19728.3 | L55: N/A | N55: Source: Felix 23rd February 2026
B56: EPS | H56: 3 | I56: 3.23 | J56: 3.46 | K56: 3.7 | L56: N/A | N56: Source: Felix 23rd February 2026
A58: Lease adjustments for US and IFRS comparability
C59: =C42 -> Annual | D59: =D42 -> Old 10-Q/Interim | E59: =E42 -> New 10-Q/interim | F59: =F42 -> Other adjustments | G59: =G42 -> Adj. LTM | H59: =H42 -> Fiscal Year | I59: =I42 -> FY +1 | J59: =J42 -> FY +2 | ... L59: =L42 -> FY +4
C60: =C43 -> 46022 | D60: =D43 -> 0 | E60: =E43 -> 0 | G60: =C13 -> 46022 | H60: =C60 -> 46022 | I60: =EDATE(C60,12) -> 46387 | J60: =EDATE(I60,12) -> 46752 | K60: =EDATE(J60,12) -> 47118 | L60: =EDATE(K60,12) -> 47483
B61: Lease interest % lease rental expense (from S&P) | C61: 0.333
B62: Operating lease rental expense in home currency | C62: 389 | D62: 0 | E62: 0 | G62: =C62-D62+E62+F62 -> 389 | H62: =C62 -> 389 | I62: =H62/H44*I44 -> 396.63237 | J62: =I62/I44*J44 -> 403.26679 | K62: =J62/J44*K44 -> 425.15138 | L62: N/A
B63: EBITDAR (adj for op lease rental expense) in home currency | C63: =C55+C62 -> 16452 | D63: =D55+D62 -> 0 | E63: =E55+E62 -> 0 | G63: =C63-D63+E63+F63 -> 16452 | H63: =C63 -> 16452 | I63: =I55+I62 -> 17669.432 | J63: =J55+J62 -> 18655.367 | K63: =K55+K62 -> 20153.451 | L63: N/A
B64: EBITR (adj for op lease interest) in home currency | C64: =C53+$C$61*C62 -> 15142.537 | D64: =D53+$C$61*D62 -> 0 | E64: =E53+$C$61*E62 -> 0 | G64: =C64-D64+E64+F64 -> 15142.537 | H64: =C64 -> 15142.537 | I64: =I53+$C$61*I62 -> 16304.879 | J64: =J53+$C$61*J62 -> 17286.388 | K64: =K53+$C$61*K62 -> 18769.875 | L64: N/A
B65: Operating lease liabilities in home currency | G65: 1722
B67: ="Calendarized EBITDAR in "&MAIN_CURRENCY&" MM" -> Calendarized EBITDAR in USD MM | G67: =G63*COMP_FX -> 16452 | I67: =IF(I$80>0,SUMPRODUCT('1'!COMP_CALENDARIZE_PERCENTAGES,H63:J63)*I$81*'1'!COMP_FX,"N/A") -> 17669.432 | J67: =IF(J$80>0,SUMPRODUCT('1'!COMP_CALENDARIZE_PERCENTAGES,I63:K63)*J$81*'1'!COMP_FX,"N/A") -> 18655.367 | K67: =IF(K$80>0,SUMPRODUCT('1'!COMP_CALENDARIZE_PERCENTAGES,J63:L63)*K$81*'1'!COMP_FX,"N/A") -> 20153.451
B68: ="Calendarized EBITR in "&MAIN_CURRENCY&" MM" -> Calendarized EBITR in USD MM | G68: =G64*COMP_FX -> 15142.537 | I68: =IF(I$80>0,SUMPRODUCT('1'!COMP_CALENDARIZE_PERCENTAGES,H64:J64)*I$81*'1'!COMP_FX,"N/A") -> 16304.879 | J68: =IF(J$80>0,SUMPRODUCT('1'!COMP_CALENDARIZE_PERCENTAGES,I64:K64)*J$81*'1'!COMP_FX,"N/A") -> 17286.388 | K68: =IF(K$80>0,SUMPRODUCT('1'!COMP_CALENDARIZE_PERCENTAGES,J64:L64)*K$81*'1'!COMP_FX,"N/A") -> 18769.875
B69: ="Operating lease liabilities in "&MAIN_CURRENCY&" MM" -> Operating lease liabilities in USD MM | G69: =G65*COMP_FX -> 1722
B71: ="EVR in "&MAIN_CURRENCY&" MM" -> EVR in USD MM | G71: =COMP_EV+(G69*COMP_FX) -> 357870.76
B72: EVR / EBITDAR | G72: =IF(ISNUMBER(G67),EVR/G67,"N/A") -> 21.752417 | I72: =IF(ISNUMBER(I67),EVR/I67,"N/A") -> 20.253665 | J72: =IF(ISNUMBER(J67),EVR/J67,"N/A") -> 19.183261 | K72: =IF(ISNUMBER(K67),EVR/K67,"N/A") -> 17.757294 | L72: N/A
B73: EVR / EBITR | G73: =IF(ISNUMBER(G68),EVR/G68,"N/A") -> 23.633475 | I73: =IF(ISNUMBER(I68),EVR/I68,"N/A") -> 21.948692 | J73: =IF(ISNUMBER(J68),EVR/J68,"N/A") -> 20.702461 | K73: =IF(ISNUMBER(K68),EVR/K68,"N/A") -> 19.06623 | L73: N/A
E76: Calendarization workings
E78: Fiscal year | G78: =C11 -> 46022 | I78: % last year | J78: % curr. year | K78: % next year
E79: Calendarize to | G79: =C8 -> 46022 | I79: =-MIN((G79-G78)/365,0) -> 0 | J79: =1-I79-K79 -> 1 | K79: =MAX((G79-G78)/365,0) -> 0
E80: Calendarize? | I80: =IF(SUMPRODUCT('1'!COMP_CALENDARIZE_PERCENTAGES,H81:J81)=1,1,0) -> 1 | J80: =IF(SUMPRODUCT('1'!COMP_CALENDARIZE_PERCENTAGES,I81:K81)=1,1,0) -> 1 | K80: =IF(SUMPRODUCT('1'!COMP_CALENDARIZE_PERCENTAGES,J81:L81)=1,1,0) -> 1 | L80: =IF(SUMPRODUCT('1'!COMP_CALENDARIZE_PERCENTAGES,K81:M81)=1,1,0) -> 0
E81: Data? | H81: =IF(OR(H44=0,H44="N/A"),0,1) -> 1 | I81: =IF(OR(I44=0,I44="N/A"),0,1) -> 1 | J81: =IF(OR(J44=0,J44="N/A"),0,1) -> 1 | K81: =IF(OR(K44=0,K44="N/A"),0,1) -> 1 | L81: =IF(OR(L44=0,L44="N/A"),0,1) -> 0
A83: End

Sheet 2
A1: Keurig Dr Pepper
E2: Analyst name | G2: Amgad Bashir
A4: Key data | E4: Enterprise value summary
B5: Ticker | C5: KDP-US | E5: ="Enterprise value calculation in "&MAIN_CURRENCY&" MM" -> Enterprise value calculation in USD MM
B6: Country | C6: United States | E6: + Diluted equity value | H6: =D36*'2'!COMP_FX -> 40504.205
B7: Analysis date | C7: =ANALYSIS_DATE -> 46076 | E7: + Debt | H7: =SUM(G31:G36)*'2'!COMP_FX -> 16839
B8: Calendarize to | C8: =Trading_comps!D5 -> 46022 | E8: - Cash and ST investments | H8: =SUM(J31:J32)*'2'!COMP_FX -> 569
B9: Currency / FX | C9: =MAIN_CURRENCY -> USD | E9: - Other adjustments | H9: =(SUM(J33:J37)-SUM(G37))*'2'!COMP_FX -> 1617
B10: Marginal tax rate | C10: 0.231 | E10: = Enterprise value | H10: ='2'!COMP_EQ_VALUE+'2'!TOTAL_DEBT-H8-H9 -> 55157.205
B11: Historical year end | C11: 45657
B12: Last filing date US format | C12: 09/30/2025 | E12: Calendarized key numbers
B13: Last filing date Intl format | C13: =DATE(RIGHT(C12,4),LEFT(C12,2),MID(C12,4,2)) -> 45930 | E13: ="Numbers in "&MAIN_CURRENCY&" MM" -> Numbers in USD MM | G13: LTM | H13: =YEAR($C$8)+1&"e" -> 2026e | I13: =YEAR($C$8)+2&"e" -> 2027e | J13: =YEAR($C$8)+3&"e" -> 2028e | K13: =YEAR($C$8)+4&"e" -> 2029e
B14: Home currency | C14: USD | E14: Revenue | G14: =G44*'2'!COMP_FX -> 16174 | H14: =IF(I$80>0,SUMPRODUCT('2'!COMP_CALENDARIZE_PERCENTAGES,H44:J44)*I$81*'2'!COMP_FX,"N/A") -> 17216.2 | I14: =IF(J$80>0,SUMPRODUCT('2'!COMP_CALENDARIZE_PERCENTAGES,I44:K44)*J$81*'2'!COMP_FX,"N/A") -> 17827 | J14: =IF(K$80>0,SUMPRODUCT('2'!COMP_CALENDARIZE_PERCENTAGES,J44:L44)*K$81*'2'!COMP_FX,"N/A") -> N/A | K14: =IF(L$80>0,SUMPRODUCT('2'!COMP_CALENDARIZE_PERCENTAGES,K44:M44)*L$81*'2'!COMP_FX,"N/A") -> N/A
B15: FX rate | C15: 1 | E15: EBITDA | G15: =G55*'2'!COMP_FX -> 4530 | H15: =IF(I$80>0,SUMPRODUCT('2'!COMP_CALENDARIZE_PERCENTAGES,H55:J55)*I$81*'2'!COMP_FX,"N/A") -> 5066.4 | I15: =IF(J$80>0,SUMPRODUCT('2'!COMP_CALENDARIZE_PERCENTAGES,I55:K55)*J$81*'2'!COMP_FX,"N/A") -> 5298.7 | J15: =IF(K$80>0,SUMPRODUCT('2'!COMP_CALENDARIZE_PERCENTAGES,J55:L55)*K$81*'2'!COMP_FX,"N/A") -> N/A | K15: =IF(L$80>0,SUMPRODUCT('2'!COMP_CALENDARIZE_PERCENTAGES,K55:M55)*L$81*'2'!COMP_FX,"N/A") -> N/A
B16: Last closing price | C16: 29.54 | E16: EBIT | G16: =G53*'2'!COMP_FX -> 3948 | H16: =IF(I$80>0,SUMPRODUCT('2'!COMP_CALENDARIZE_PERCENTAGES,H53:J53)*I$81*'2'!COMP_FX,"N/A") -> 4466.4 | I16: =IF(J$80>0,SUMPRODUCT('2'!COMP_CALENDARIZE_PERCENTAGES,I53:K53)*J$81*'2'!COMP_FX,"N/A") -> 4698.7 | J16: =IF(K$80>0,SUMPRODUCT('2'!COMP_CALENDARIZE_PERCENTAGES,J53:L53)*K$81*'2'!COMP_FX,"N/A") -> N/A | K16: =IF(L$80>0,SUMPRODUCT('2'!COMP_CALENDARIZE_PERCENTAGES,K53:M53)*L$81*'2'!COMP_FX,"N/A") -> N/A
B17: 52 week low | C17: 25.03 | E17: EPS | H17: =IF(I$80>0,SUMPRODUCT('2'!COMP_CALENDARIZE_PERCENTAGES,H56:J56)*I$81*'2'!COMP_FX,"N/A") -> 2.17 | I17: =IF(J$80>0,SUMPRODUCT('2'!COMP_CALENDARIZE_PERCENTAGES,I56:K56)*J$81*'2'!COMP_FX,"N/A") -> 2.31 | J17: =IF(K$80>0,SUMPRODUCT('2'!COMP_CALENDARIZE_PERCENTAGES,J56:L56)*K$81*'2'!COMP_FX,"N/A") -> N/A | K17: =IF(L$80>0,SUMPRODUCT('2'!COMP_CALENDARIZE_PERCENTAGES,K56:M56)*L$81*'2'!COMP_FX,"N/A") -> N/A
B18: 52 week high | C18: 36.12
B19: Credit rating | C19: BBB | E19: Calendarized multiples to December 31
B20: Beta | C20: 0.55 | G20: =G13 -> LTM | H20: =H13 -> 2026e | I20: =I13 -> 2027e | J20: =J13 -> 2028e | K20: =K13 -> 2029e
B21: 5 year EPS forward growth | C21: 0.065 | E21: EV / Revenue | G21: =IF(G14<>0,$H$10/G14,"N/A") -> 3.410239 | H21: =IF(ISNUMBER(H14),$H$10/H14,"N/A") -> 3.2037967 | I21: =IF(ISNUMBER(I14),$H$10/I14,"N/A") -> 3.0940262 | J21: =IF(ISNUMBER(J14),$H$10/J14,"N/A") -> N/A | K21: =IFERROR($H$10/K14,"N/A") -> N/A
B22: LTM EBIT margin | C22: =G53/G44 -> 0.24409546 | E22: EV / EBITDA | G22: =IF(G15<>0,$H$10/G15,"N/A") -> 12.175983 | H22: =IF(ISNUMBER(H15),$H$10/H15,"N/A") -> 10.886863 | I22: =IF(ISNUMBER(I15),$H$10/I15,"N/A") -> 10.409573 | J22: =IF(ISNUMBER(J15),$H$10/J15,"N/A") -> N/A | K22: =IFERROR($H$10/K15,"N/A") -> N/A
B23: Return on invested capital | C23: =G53*(1-'2'!COMP_MTR)/D39 -> 0.075943968 | E23: EV / EBIT | G23: =IF(G16<>0,$H$10/G16,"N/A") -> 13.970923 | H23: =IF(ISNUMBER(H16),$H$10/H16,"N/A") -> 12.349365 | I23: =IF(ISNUMBER(I16),$H$10/I16,"N/A") -> 11.738822 | J23: =IF(ISNUMBER(J16),$H$10/J16,"N/A") -> N/A | K23: =IFERROR($H$10/K16,"N/A") -> N/A
E24: PE | H24: =IF(ISNUMBER(H17),($C$16*'2'!COMP_FX)/H17,"N/A") -> 13.612903 | I24: =IF(ISNUMBER(I17),($C$16*'2'!COMP_FX)/I17,"N/A") -> 12.787879 | J24: =IF(ISNUMBER(J17),($C$16*'2'!COMP_FX)/J17,"N/A") -> N/A | K24: =IFERROR(($C$16*'2'!COMP_FX)/K17,"N/A") -> N/A
E25: P / BV | G25: =D36/D37 -> 1.5994395
E26: Total debt / LTM EBITDA | G26: =IF(G15=0,"N/A",H7/G15) -> 3.7172185
A28: Enterprise value calculation (home currency) | M28: Share options and RSUs
M29: Tranche | N29: Number | O29: Strike | P29: New shares
B30: Equity valuation | E30: Financial liabilities calculation | H30: Financial assets calculation | M30: Options | N30: 0 | O30: 0 | P30: =MAX(('2'!COMP_SHAREPRICE-O30)/'2'!COMP_SHAREPRICE*N30,0) -> 0
B31: Shares outstanding as of | D31: 45953 | E31: Debt - short term | G31: 2285 | H31: Cash and ST investments | J31: =516+53 -> 569 | M31: Performance share units | N31: 0.461726 | O31: 0 | P31: =MAX(('2'!COMP_SHAREPRICE-O31)/'2'!COMP_SHAREPRICE*N31,0) -> 0.461726
B32: Basic shares outstanding | D32: 1358.5831 | E32: Finance lease liabilities | G32: 150 | H32: Marketable securities | J32: 0 | M32: Time based RSUs | N32: 12.119846 | O32: 0 | P32: =MAX(('2'!COMP_SHAREPRICE-O32)/'2'!COMP_SHAREPRICE*N32,0) -> 12.119846
B33: Other adjustments | D33: 0 | E33: Finance lease liabilities | G33: 704 | H33: Equity method investments | J33: 1617 | M33: Tranche 4 | N33: 0 | O33: 0 | P33: =MAX(('2'!COMP_SHAREPRICE-O33)/'2'!COMP_SHAREPRICE*N33,0) -> 0
B34: Dilution from share options | D34: =P38 -> 12.581572 | E34: Debt - long term | G34: 13531 | H34: Other | J34: 0 | M34: Tranche 5 | N34: 0 | O34: 0 | P34: =MAX(('2'!COMP_SHAREPRICE-O34)/'2'!COMP_SHAREPRICE*N34,0) -> 0
B35: Diluted shares outstanding | D35: =SUM(D32:D34) -> 1371.1647 | E35: Structured payables | G35: 30 | H35: Other | J35: 0 | M35: Tranche 6 | N35: 0 | O35: 0 | P35: =MAX(('2'!COMP_SHAREPRICE-O35)/'2'!COMP_SHAREPRICE*N35,0) -> 0
B36: Diluted equity value | D36: =D35*'2'!COMP_SHAREPRICE -> 40504.205 | E36: Unamortized debt discount / original issue discount | G36: 139 | H36: Other | J36: 0 | M36: Tranche 7 | N36: 0 | O36: 0 | P36: =MAX(('2'!COMP_SHAREPRICE-O36)/'2'!COMP_SHAREPRICE*N36,0) -> 0
B37: Shareholders' equity | D37: 25324 | E37: NCI | G37: 0 | H37: Other | J37: 0 | M37: Tranche 8 | N37: 0 | O37: 0 | P37: =MAX(('2'!COMP_SHAREPRICE-O37)/'2'!COMP_SHAREPRICE*N37,0) -> 0
B38: Net debt and other adjustments | D38: =G39-J39 -> 14653 | M38: Total | P38: =SUM(P30:P37) -> 12.581572
B39: Invested capital | D39: =D37+D38 -> 39977 | E39: Total financial liabilities | G39: =SUM(G31:G37) -> 16839 | H39: Total financial assets | J39: =SUM(J31:J37) -> 2186
A41: Earnings (home currency) | I41: Consensus estimates
C42: Annual | D42: Last 9 months 2024 | E42: Last 9 months 2025 | F42: Other adjustments | G42: Adj. LTM | H42: Fiscal Year | I42: FY +1 | J42: FY +2 | K42: FY +3 | L42: FY +4
B43: Date | C43: =C11 -> 45657 | D43: 45565 | E43: 45930 | G43: =C13 -> 45930 | H43: =C43 -> 45657 | I43: =EDATE(C43,12) -> 46022 | J43: =EDATE(I43,12) -> 46387 | K43: =EDATE(J43,12) -> 46752 | L43: =EDATE(K43,12) -> 47118
B44: Revenue | C44: 15351 | D44: 11281 | E44: 12104 | F44: 0 | G44: =C44-D44+E44+F44 -> 16174 | H44: =C44 -> 15351 | I44: 16465.6 | J44: 17216.2 | K44: 17827 | L44: N/A | N44: Source: Felix 23rd February 2026
B45: CapIQ EBIT | C45: 3140 | D45: 0 | E45: 0
B46: Adjusted operating profit | C46: 3974 | D46: 2845 | E46: 2966
B47: Amortization of intangibles added back by management | C47: -133 | D47: -100 | E47: -101
B48: Stock compensation expense added back by management | C48: -14 | D48: -11 | E48: -10
B49: Further adjustments | C49: 0 | D49: 0 | E49: 0
A50: 1 | B50: Further adjustments | C50: 0 | D50: 0 | E50: 0
B51: Further adjustments | C51: 0 | D51: 0 | E51: 0
B52: Further adjustments | C52: 0 | D52: 0 | E52: 0
B53: EBIT | C53: =SUM(C46:C52) -> 3827 | D53: =SUM(D46:D52) -> 2734 | E53: =SUM(E46:E52) -> 2855 | F53: =SUM(F46:F52) -> 0 | G53: =C53-D53+E53+F53 -> 3948 | H53: =C53 -> 3827 | I53: =I55-I54 -> 4200.2 | J53: =J55-J54 -> 4466.4 | K53: =K55-K54 -> 4698.7 | L53: N/A
B54: Depreciation and amortization | C54: =422+133 -> 555 | D54: =310+100 -> 410 | E54: =336+101 -> 437 | F54: 0 | G54: =C54-D54+E54+F54 -> 582 | H54: =C54 -> 555 | I54: 600 | J54: 600 | K54: 600 | L54: N/A
B55: EBITDA (consolidated) | C55: =C53+C54 -> 4382 | D55: =D53+D54 -> 3144 | E55: =E53+E54 -> 3292 | G55: =C55-D55+E55+F55 -> 4530 | H55: =C55 -> 4382 | I55: 4800.2 | J55: 5066.4 | K55: 5298.7 | L55: N/A | N55: Source: Felix 23rd February 2026
B56: EPS | H56: 1.85 | I56: 2.04 | J56: 2.17 | K56: 2.31 | L56: N/A | N56: Source: Felix 23rd February 2026
A58: Lease adjustments for US and IFRS comparability
C59: =C42 -> Annual | D59: =D42 -> Last 9 months 2024 | E59: =E42 -> Last 9 months 2025 | F59: =F42 -> Other adjustments | G59: =G42 -> Adj. LTM | H59: =H42 -> Fiscal Year | I59: =I42 -> FY +1 | J59: =J42 -> FY +2 | ... L59: =L42 -> FY +4
C60: =C43 -> 45657 | D60: =D43 -> 45565 | E60: =E43 -> 45930 | G60: =C13 -> 45930 | H60: =C60 -> 45657 | I60: =EDATE(C60,12) -> 46022 | J60: =EDATE(I60,12) -> 46387 | K60: =EDATE(J60,12) -> 46752 | L60: =EDATE(K60,12) -> 47118
B61: Lease interest % lease rental expense (from S&P) | C61: 0.333
B62: Operating lease rental expense in home currency | C62: 170 | D62: 127 | E62: 136 | G62: =C62-D62+E62+F62 -> 179 | H62: =C62 -> 170 | I62: =H62/H44*I44 -> 182.3433 | J62: =I62/I44*J44 -> 190.65559 | K62: =J62/J44*K44 -> 197.41971 | L62: N/A
B63: EBITDAR (adj for op lease rental expense) in home currency | C63: =C55+C62 -> 4552 | D63: =D55+D62 -> 3271 | E63: =E55+E62 -> 3428 | G63: =C63-D63+E63+F63 -> 4709 | H63: =C63 -> 4552 | I63: =I55+I62 -> 4982.5433 | J63: =J55+J62 -> 5257.0556 | K63: =K55+K62 -> 5496.1197 | L63: N/A
B64: EBITR (adj for op lease interest) in home currency | C64: =C53+$C$61*C62 -> 3883.61 | D64: =D53+$C$61*D62 -> 2776.291 | E64: =E53+$C$61*E62 -> 2900.288 | G64: =C64-D64+E64+F64 -> 4007.607 | H64: =C64 -> 3883.61 | I64: =I53+$C$61*I62 -> 4260.9203 | J64: =J53+$C$61*J62 -> 4529.8883 | K64: =K53+$C$61*K62 -> 4764.4408 | L64: N/A
B65: Operating lease liabilities in home currency | G65: =790+128 -> 918
B67: ="Calendarized EBITDAR in "&MAIN_CURRENCY&" MM" -> Calendarized EBITDAR in USD MM | G67: =G63*COMP_FX -> 4709 | I67: =IF(I$80>0,SUMPRODUCT('2'!COMP_CALENDARIZE_PERCENTAGES,H63:J63)*I$81*'2'!COMP_FX,"N/A") -> 5257.0556 | J67: =IF(J$80>0,SUMPRODUCT('2'!COMP_CALENDARIZE_PERCENTAGES,I63:K63)*J$81*'2'!COMP_FX,"N/A") -> 5496.1197 | K67: =IF(K$80>0,SUMPRODUCT('2'!COMP_CALENDARIZE_PERCENTAGES,J63:L63)*K$81*'2'!COMP_FX,"N/A") -> N/A
B68: ="Calendarized EBITR in "&MAIN_CURRENCY&" MM" -> Calendarized EBITR in USD MM | G68: =G64*COMP_FX -> 4007.607 | I68: =IF(I$80>0,SUMPRODUCT('2'!COMP_CALENDARIZE_PERCENTAGES,H64:J64)*I$81*'2'!COMP_FX,"N/A") -> 4529.8883 | J68: =IF(J$80>0,SUMPRODUCT('2'!COMP_CALENDARIZE_PERCENTAGES,I64:K64)*J$81*'2'!COMP_FX,"N/A") -> 4764.4408 | K68: =IF(K$80>0,SUMPRODUCT('2'!COMP_CALENDARIZE_PERCENTAGES,J64:L64)*K$81*'2'!COMP_FX,"N/A") -> N/A
B69: ="Operating lease liabilities in "&MAIN_CURRENCY&" MM" -> Operating lease liabilities in USD MM | G69: =G65*COMP_FX -> 918
B71: ="EVR in "&MAIN_CURRENCY&" MM" -> EVR in USD MM | G71: =COMP_EV+(G69*COMP_FX) -> 56075.205
B72: EVR / EBITDAR | G72: =IF(ISNUMBER(G67),EVR/G67,"N/A") -> 11.908092 | I72: =IF(ISNUMBER(I67),EVR/I67,"N/A") -> 10.666656 | J72: =IF(ISNUMBER(J67),EVR/J67,"N/A") -> 10.20269 | K72: =IF(ISNUMBER(K67),EVR/K67,"N/A") -> N/A | L72: N/A
B73: EVR / EBITR | G73: =IF(ISNUMBER(G68),EVR/G68,"N/A") -> 13.992192 | I73: =IF(ISNUMBER(I68),EVR/I68,"N/A") -> 12.378938 | J73: =IF(ISNUMBER(J68),EVR/J68,"N/A") -> 11.769525 | K73: =IF(ISNUMBER(K68),EVR/K68,"N/A") -> N/A | L73: N/A
E76: Calendarization workings
E78: Fiscal year | G78: =C11 -> 45657 | I78: % last year | J78: % curr. year | K78: % next year
E79: Calendarize to | G79: =C8 -> 46022 | I79: =-MIN((G79-G78)/365,0) -> 0 | J79: =1-I79-K79 -> 0 | K79: =MAX((G79-G78)/365,0) -> 1
E80: Calendarize? | I80: =IF(SUMPRODUCT('2'!COMP_CALENDARIZE_PERCENTAGES,H81:J81)=1,1,0) -> 1 | J80: =IF(SUMPRODUCT('2'!COMP_CALENDARIZE_PERCENTAGES,I81:K81)=1,1,0) -> 1 | K80: =IF(SUMPRODUCT('2'!COMP_CALENDARIZE_PERCENTAGES,J81:L81)=1,1,0) -> 0 | L80: =IF(SUMPRODUCT('2'!COMP_CALENDARIZE_PERCENTAGES,K81:M81)=1,1,0) -> 0
E81: Data? | H81: =IF(OR(H44=0,H44="N/A"),0,1) -> 1 | I81: =IF(OR(I44=0,I44="N/A"),0,1) -> 1 | J81: =IF(OR(J44=0,J44="N/A"),0,1) -> 1 | K81: =IF(OR(K44=0,K44="N/A"),0,1) -> 1 | L81: =IF(OR(L44=0,L44="N/A"),0,1) -> 0
A83: End

Sheet 3
A1: Monster Beverage
E2: Analyst name | G2: Amgad Bashir
A4: Key data | E4: Enterprise value summary
B5: Ticker | C5: MNST-US | E5: ="Enterprise value calculation in "&MAIN_CURRENCY&" MM" -> Enterprise value calculation in USD MM
B6: Country | C6: United States | E6: + Diluted equity value | H6: =D36*'3'!COMP_FX -> 83024.655
B7: Analysis date | C7: =ANALYSIS_DATE -> 46076 | E7: + Debt | H7: =SUM(G31:G33)*'3'!COMP_FX -> 0
B8: Calendarize to | C8: =Trading_comps!D5 -> 46022 | E8: - Cash and ST investments | H8: =SUM(J31:J32)*'3'!COMP_FX -> 2579.33
B9: Currency / FX | C9: =MAIN_CURRENCY -> USD | E9: - Other adjustments | H9: =(SUM(J33:J37)-SUM(G34:G37))*'3'!COMP_FX -> 359.174
B10: Marginal tax rate | C10: 0.21 | E10: = Enterprise value | H10: ='3'!COMP_EQ_VALUE+'3'!TOTAL_DEBT-H8-H9 -> 80086.151
B11: Historical year end | C11: 45657
B12: Last filing date US format | C12: 09/30/2025 | E12: Calendarized key numbers
B13: Last filing date Intl format | C13: =DATE(RIGHT(C12,4),LEFT(C12,2),MID(C12,4,2)) -> 45930 | E13: ="Numbers in "&MAIN_CURRENCY&" MM" -> Numbers in USD MM | G13: LTM | H13: =YEAR($C$8)+1&"e" -> 2026e | I13: =YEAR($C$8)+2&"e" -> 2027e | J13: =YEAR($C$8)+3&"e" -> 2028e | K13: =YEAR($C$8)+4&"e" -> 2029e
B14: Home currency | C14: USD | E14: Revenue | G14: =G44*'3'!COMP_FX -> 7975.331 | H14: =IF(I$80>0,SUMPRODUCT('3'!COMP_CALENDARIZE_PERCENTAGES,H44:J44)*I$81*'3'!COMP_FX,"N/A") -> 9006.9 | I14: =IF(J$80>0,SUMPRODUCT('3'!COMP_CALENDARIZE_PERCENTAGES,I44:K44)*J$81*'3'!COMP_FX,"N/A") -> 9819.6 | J14: =IF(K$80>0,SUMPRODUCT('3'!COMP_CALENDARIZE_PERCENTAGES,J44:L44)*K$81*'3'!COMP_FX,"N/A") -> N/A | K14: =IF(L$80>0,SUMPRODUCT('3'!COMP_CALENDARIZE_PERCENTAGES,K44:M44)*L$81*'3'!COMP_FX,"N/A") -> N/A
B15: FX rate | C15: 1 | E15: EBITDA | G15: =G55*'3'!COMP_FX -> 2552.979 | H15: =IF(I$80>0,SUMPRODUCT('3'!COMP_CALENDARIZE_PERCENTAGES,H55:J55)*I$81*'3'!COMP_FX,"N/A") -> 2914.6 | I15: =IF(J$80>0,SUMPRODUCT('3'!COMP_CALENDARIZE_PERCENTAGES,I55:K55)*J$81*'3'!COMP_FX,"N/A") -> 3212.8 | J15: =IF(K$80>0,SUMPRODUCT('3'!COMP_CALENDARIZE_PERCENTAGES,J55:L55)*K$81*'3'!COMP_FX,"N/A") -> N/A | K15: =IF(L$80>0,SUMPRODUCT('3'!COMP_CALENDARIZE_PERCENTAGES,K55:M55)*L$81*'3'!COMP_FX,"N/A") -> N/A
B16: Last closing price | C16: 83.76 | E16: EBIT | G16: =G53*'3'!COMP_FX -> 2450.344 | H16: =IF(I$80>0,SUMPRODUCT('3'!COMP_CALENDARIZE_PERCENTAGES,H53:J53)*I$81*'3'!COMP_FX,"N/A") -> 2834.6 | I16: =IF(J$80>0,SUMPRODUCT('3'!COMP_CALENDARIZE_PERCENTAGES,I53:K53)*J$81*'3'!COMP_FX,"N/A") -> 3132.8 | J16: =IF(K$80>0,SUMPRODUCT('3'!COMP_CALENDARIZE_PERCENTAGES,J53:L53)*K$81*'3'!COMP_FX,"N/A") -> N/A | K16: =IF(L$80>0,SUMPRODUCT('3'!COMP_CALENDARIZE_PERCENTAGES,K53:M53)*L$81*'3'!COMP_FX,"N/A") -> N/A
B17: 52 week low | C17: 50.93 | E17: EPS | H17: =IF(I$80>0,SUMPRODUCT('3'!COMP_CALENDARIZE_PERCENTAGES,H56:J56)*I$81*'3'!COMP_FX,"N/A") -> 2.26 | I17: =IF(J$80>0,SUMPRODUCT('3'!COMP_CALENDARIZE_PERCENTAGES,I56:K56)*J$81*'3'!COMP_FX,"N/A") -> 2.55 | J17: =IF(K$80>0,SUMPRODUCT('3'!COMP_CALENDARIZE_PERCENTAGES,J56:L56)*K$81*'3'!COMP_FX,"N/A") -> N/A | K17: =IF(L$80>0,SUMPRODUCT('3'!COMP_CALENDARIZE_PERCENTAGES,K56:M56)*L$81*'3'!COMP_FX,"N/A") -> N/A
B18: 52 week high | C18: 83.98
B19: Credit rating | C19: N/A | E19: Calendarized multiples to December 31
B20: Beta | C20: 0.63 | G20: =G13 -> LTM | H20: =H13 -> 2026e | I20: =I13 -> 2027e | J20: =J13 -> 2028e | K20: =K13 -> 2029e
B21: 5 year EPS forward growth | C21: 0.125 | E21: EV / Revenue | G21: =IF(G14<>0,$H$10/G14,"N/A") -> 10.041734 | H21: =IF(ISNUMBER(H14),$H$10/H14,"N/A") -> 8.8916443 | I21: =IF(ISNUMBER(I14),$H$10/I14,"N/A") -> 8.1557447 | J21: =IF(ISNUMBER(J14),$H$10/J14,"N/A") -> N/A | K21: =IFERROR($H$10/K14,"N/A") -> N/A
B22: LTM EBIT margin | C22: =G53/G44 -> 0.30724041 | E22: EV / EBITDA | G22: =IF(G15<>0,$H$10/G15,"N/A") -> 31.369686 | H22: =IF(ISNUMBER(H15),$H$10/H15,"N/A") -> 27.477579 | I22: =IF(ISNUMBER(I15),$H$10/I15,"N/A") -> 24.927213 | J22: =IF(ISNUMBER(J15),$H$10/J15,"N/A") -> N/A | K22: =IFERROR($H$10/K15,"N/A") -> N/A
B23: Return on invested capital | C23: =G53*(1-'3'!COMP_MTR)/D39 -> 0.40274074 | E23: EV / EBIT | G23: =IF(G16<>0,$H$10/G16,"N/A") -> 32.683636 | H23: =IF(ISNUMBER(H16),$H$10/H16,"N/A") -> 28.253069 | I23: =IF(ISNUMBER(I16),$H$10/I16,"N/A") -> 25.563761 | J23: =IF(ISNUMBER(J16),$H$10/J16,"N/A") -> N/A | K23: =IFERROR($H$10/K16,"N/A") -> N/A
E24: PE | H24: =IF(ISNUMBER(H17),($C$16*'3'!COMP_FX)/H17,"N/A") -> 37.061947 | I24: =IF(ISNUMBER(I17),($C$16*'3'!COMP_FX)/I17,"N/A") -> 32.847059 | J24: =IF(ISNUMBER(J17),($C$16*'3'!COMP_FX)/J17,"N/A") -> N/A | K24: =IFERROR(($C$16*'3'!COMP_FX)/K17,"N/A") -> N/A
E25: P / BV | G25: =D36/D37 -> 10.719775
E26: Total debt / LTM EBITDA | G26: =IF(G15=0,"N/A",H7/G15) -> 0
A28: Enterprise value calculation (home currency) | M28: Share options and RSUs
M29: Tranche | N29: Number | O29: Strike | P29: New shares
B30: Equity valuation | E30: Financial liabilities calculation | H30: Financial assets calculation | M30: Options | N30: 24.074 | O30: 41.45 | P30: =MAX(('3'!COMP_SHAREPRICE-O30)/'3'!COMP_SHAREPRICE*N30,0) -> 12.160589
B31: Shares outstanding as of | D31: 45961 | E31: Debt - short term | G31: 0 | H31: Cash and ST investments | J31: =2292.939+286.391 -> 2579.33 | M31: RSUs and Performance share units | N31: 2.039 | O31: 0 | P31: =MAX(('3'!COMP_SHAREPRICE-O31)/'3'!COMP_SHAREPRICE*N31,0) -> 2.039
B32: Basic shares outstanding | D32: 977.02122 | E32: Debt - current maturities | G32: 0 | H32: Marketable securities | J32: 0 | M32: Tranche 3 | N32: 0 | O32: 0 | P32: =MAX(('3'!COMP_SHAREPRICE-O32)/'3'!COMP_SHAREPRICE*N32,0) -> 0
B33: Other adjustments | D33: 0 | E33: Debt - long term | G33: 0 | H33: Equity method investments | J33: 359.174 | M33: Tranche 4 | N33: 0 | O33: 0 | P33: =MAX(('3'!COMP_SHAREPRICE-O33)/'3'!COMP_SHAREPRICE*N33,0) -> 0
B34: Dilution from share options | D34: =P38 -> 14.199589 | E34: Preferred equity | G34: 0 | H34: Other investments | J34: 0 | M34: Tranche 5 | N34: 0 | O34: 0 | P34: =MAX(('3'!COMP_SHAREPRICE-O34)/'3'!COMP_SHAREPRICE*N34,0) -> 0
B35: Diluted shares outstanding | D35: =SUM(D32:D34) -> 991.22081 | E35: NCI | G35: 0 | H35: Other | J35: 0 | M35: Tranche 6 | N35: 0 | O35: 0 | P35: =MAX(('3'!COMP_SHAREPRICE-O35)/'3'!COMP_SHAREPRICE*N35,0) -> 0
B36: Diluted equity value | D36: =D35*'3'!COMP_SHAREPRICE -> 83024.655 | E36: Other | G36: 0 | H36: Other | J36: 0 | M36: Tranche 7 | N36: 0 | O36: 0 | P36: =MAX(('3'!COMP_SHAREPRICE-O36)/'3'!COMP_SHAREPRICE*N36,0) -> 0
B37: Shareholders' equity | D37: 7745 | E37: Other | G37: 0 | H37: Other | J37: 0 | M37: Tranche 8 | N37: 0 | O37: 0 | P37: =MAX(('3'!COMP_SHAREPRICE-O37)/'3'!COMP_SHAREPRICE*N37,0) -> 0
B38: Net debt and other adjustments | D38: =G39-J39 -> -2938.504 | M38: Total | P38: =SUM(P30:P37) -> 14.199589
B39: Invested capital | D39: =D37+D38 -> 4806.496 | E39: Total financial liabilities | G39: =SUM(G31:G37) -> 0 | H39: Total financial assets | J39: =SUM(J31:J37) -> 2938.504
A41: Earnings (home currency) | I41: Consensus estimates
C42: Annual | D42: Last 9 months 2024 | E42: Last 9 months 2025 | F42: Other adjustments | G42: Adj. LTM | H42: Fiscal Year | I42: FY +1 | J42: FY +2 | K42: FY +3 | L42: FY +4
B43: Date | C43: =C11 -> 45657 | D43: 45565 | E43: 45930 | G43: =C13 -> 45930 | H43: =C43 -> 45657 | I43: =EDATE(C43,12) -> 46022 | J43: =EDATE(I43,12) -> 46387 | K43: =EDATE(J43,12) -> 46752 | L43: =EDATE(K43,12) -> 47118
B44: Revenue | C44: 7492.709 | D44: 5680.668 | E44: 6163.29 | F44: 0 | G44: =C44-D44+E44+F44 -> 7975.331 | H44: =C44 -> 7492.709 | I44: 8207 | J44: 9006.9 | K44: 9819.6
B45: CapIQ EBIT | C45: 1902 | D45: 0 | E45: 0
B46: Adjusted operating profit | C46: 2103.783 | D46: 1618.411 | E46: 1964.972
B47: Further adjustments | C47: 0 | D47: 0 | E47: 0
B48: Further adjustments | C48: 0 | D48: 0 | E48: 0
B49: Further adjustments | C49: 0 | D49: 0 | E49: 0
A50: 1 | B50: Further adjustments | C50: 0 | D50: 0 | E50: 0
B51: Further adjustments | C51: 0 | D51: 0 | E51: 0
B52: Further adjustments | C52: 0 | D52: 0 | E52: 0
B53: EBIT | C53: =SUM(C46:C52) -> 2103.783 | D53: =SUM(D46:D52) -> 1618.411 | E53: =SUM(E46:E52) -> 1964.972 | F53: =SUM(F46:F52) -> 0 | G53: =C53-D53+E53+F53 -> 2450.344 | H53: =C53 -> 2103.783 | I53: =I55-I54 -> 2537.9 | J53: =J55-J54 -> 2834.6 | K53: =K55-K54 -> 3132.8
B54: Depreciation and amortization | C54: 80.434 | D54: 59.822 | E54: 82.023 | F54: 0 | G54: =C54-D54+E54+F54 -> 102.635 | H54: =C54 -> 80.434 | I54: 80 | J54: 80 | K54: 80 | L54: N/A
B55: EBITDA (consolidated) | C55: =C53+C54 -> 2184.217 | D55: =D53+D54 -> 1678.233 | E55: =E53+E54 -> 2046.995 | G55: =C55-D55+E55+F55 -> 2552.979 | H55: =C55 -> 2184.217 | I55: 2617.9 | J55: 2914.6 | K55: 3212.8
B56: EPS | I56: 1.99 | J56: 2.26 | K56: 2.55
A58: Lease adjustments for US and IFRS comparability
C59: =C42 -> Annual | D59: =D42 -> Last 9 months 2024 | E59: =E42 -> Last 9 months 2025 | F59: =F42 -> Other adjustments | G59: =G42 -> Adj. LTM | H59: =H42 -> Fiscal Year | I59: =I42 -> FY +1 | J59: =J42 -> FY +2 | ... L59: =L42 -> FY +4
C60: =C43 -> 45657 | D60: =D43 -> 45565 | E60: =E43 -> 45930 | G60: =C13 -> 45930 | H60: =C60 -> 45657 | I60: =EDATE(C60,12) -> 46022 | J60: =EDATE(I60,12) -> 46387 | K60: =EDATE(J60,12) -> 46752 | L60: =EDATE(K60,12) -> 47118
B61: Lease interest % lease rental expense (from S&P) | C61: 0.333
B62: Operating lease rental expense in home currency | C62: 15.796 | D62: 0 | E62: 0 | G62: =C62-D62+E62+F62 -> 15.796 | H62: =C62 -> 15.796 | I62: =H62/H44*I44 -> 17.301856 | J62: =I62/I44*J44 -> 18.988191 | K62: =J62/J44*K44 -> 20.701512 | L62: N/A
B63: EBITDAR (adj for op lease rental expense) in home currency | C63: =C55+C62 -> 2200.013 | D63: =D55+D62 -> 1678.233 | E63: =E55+E62 -> 2046.995 | G63: =C63-D63+E63+F63 -> 2568.775 | H63: =C63 -> 2200.013 | I63: =I55+I62 -> 2635.2019 | J63: =J55+J62 -> 2933.5882 | K63: =K55+K62 -> 3233.5015 | L63: N/A
B64: EBITR (adj for op lease interest) in home currency | C64: =C53+$C$61*C62 -> 2109.0431 | D64: =D53+$C$61*D62 -> 1618.411 | E64: =E53+$C$61*E62 -> 1964.972 | G64: =C64-D64+E64+F64 -> 2455.6041 | H64: =C64 -> 2109.0431 | I64: =I53+$C$61*I62 -> 2543.6615 | J64: =J53+$C$61*J62 -> 2840.9231 | K64: =K53+$C$61*K62 -> 3139.6936 | L64: N/A
B65: Operating lease liabilities in home currency | G65: 56.387
B67: ="Calendarized EBITDAR in "&MAIN_CURRENCY&" MM" -> Calendarized EBITDAR in USD MM | G67: =G63*COMP_FX -> 2568.775 | I67: =IF(I$80>0,SUMPRODUCT('3'!COMP_CALENDARIZE_PERCENTAGES,H63:J63)*I$81*'3'!COMP_FX,"N/A") -> 2933.5882 | J67: =IF(J$80>0,SUMPRODUCT('3'!COMP_CALENDARIZE_PERCENTAGES,I63:K63)*J$81*'3'!COMP_FX,"N/A") -> 3233.5015 | K67: =IF(K$80>0,SUMPRODUCT('3'!COMP_CALENDARIZE_PERCENTAGES,J63:L63)*K$81*'3'!COMP_FX,"N/A") -> N/A
B68: ="Calendarized EBITR in "&MAIN_CURRENCY&" MM" -> Calendarized EBITR in USD MM | G68: =G64*COMP_FX -> 2455.6041 | I68: =IF(I$80>0,SUMPRODUCT('3'!COMP_CALENDARIZE_PERCENTAGES,H64:J64)*I$81*'3'!COMP_FX,"N/A") -> 2840.9231 | J68: =IF(J$80>0,SUMPRODUCT('3'!COMP_CALENDARIZE_PERCENTAGES,I64:K64)*J$81*'3'!COMP_FX,"N/A") -> 3139.6936 | K68: =IF(K$80>0,SUMPRODUCT('3'!COMP_CALENDARIZE_PERCENTAGES,J64:L64)*K$81*'3'!COMP_FX,"N/A") -> N/A
B69: ="Operating lease liabilities in "&MAIN_CURRENCY&" MM" -> Operating lease liabilities in USD MM | G69: =G65*COMP_FX -> 56.387
B71: ="EVR in "&MAIN_CURRENCY&" MM" -> EVR in USD MM | G71: =COMP_EV+(G69*COMP_FX) -> 80142.538
B72: EVR / EBITDAR | G72: =IF(ISNUMBER(G67),EVR/G67,"N/A") -> 31.198738 | I72: =IF(ISNUMBER(I67),EVR/I67,"N/A") -> 27.318946 | J72: =IF(ISNUMBER(J67),EVR/J67,"N/A") -> 24.785063 | K72: =IF(ISNUMBER(K67),EVR/K67,"N/A") -> N/A | L72: N/A
B73: EVR / EBITR | G73: =IF(ISNUMBER(G68),EVR/G68,"N/A") -> 32.636588 | I73: =IF(ISNUMBER(I68),EVR/I68,"N/A") -> 28.210034 | J73: =IF(ISNUMBER(J68),EVR/J68,"N/A") -> 25.525592 | K73: =IF(ISNUMBER(K68),EVR/K68,"N/A") -> N/A | L73: N/A
E76: Calendarization workings
E78: Fiscal year | G78: =C11 -> 45657 | I78: % last year | J78: % curr. year | K78: % next year
E79: Calendarize to | G79: =C8 -> 46022 | I79: =-MIN((G79-G78)/365,0) -> 0 | J79: =1-I79-K79 -> 0 | K79: =MAX((G79-G78)/365,0) -> 1
E80: Calendarize? | I80: =IF(SUMPRODUCT('3'!COMP_CALENDARIZE_PERCENTAGES,H81:J81)=1,1,0) -> 1 | J80: =IF(SUMPRODUCT('3'!COMP_CALENDARIZE_PERCENTAGES,I81:K81)=1,1,0) -> 1 | K80: =IF(SUMPRODUCT('3'!COMP_CALENDARIZE_PERCENTAGES,J81:L81)=1,1,0) -> 0 | L80: =IF(SUMPRODUCT('3'!COMP_CALENDARIZE_PERCENTAGES,K81:M81)=1,1,0) -> 0
E81: Data? | H81: =IF(OR(H44=0,H44="N/A"),0,1) -> 1 | I81: =IF(OR(I44=0,I44="N/A"),0,1) -> 1 | J81: =IF(OR(J44=0,J44="N/A"),0,1) -> 1 | K81: =IF(OR(K44=0,K44="N/A"),0,1) -> 1 | L81: =IF(OR(L44=0,L44="N/A"),0,1) -> 0
A83: End

Sheet Transaction_comps
A1: Transaction comparables
A2: All figures in USDm unless stated
C3: Acquirer | D3: Announcement | E3: Transaction | F3: Transaction | G3: Enterprise | H3: LTM | I3: LTM | J3: LTM EBITDA | N3: Synergies % | O3: Target | P3: Reason for
B4: Target | C4: Acquirer | D4: Date | E4: Status | F4: Value (MM) | G4: Value | H4: Revenue | I4: EBITDA | J4: margin | K4: EV/Revenue | L4: EV/EBITDA | M4: Synergies | N4: LTM revenues | O4: Country | P4: excluding | Q4: Synopsis
A6: Transactions longlist
B7: SABMiller Plc | C7: Anheuser-Busch InBev SA /Old/ | D7: 42263 | E7: Complete | F7: 123394.26 | G7: 123394.26 | H7: 22129.999 | I7: =G7/L7 -> 5307 | J7: =I7/H7 -> 0.23981022 | K7: =G7/H7 -> 5.5758817 | L7: 23.251226 | M7: 1400 | N7: =M7/H7 -> 0.063262542 | O7: UK | Q7: Anheuser-Busch InBev SA acquired SABMiller Plc for GBP73.1 billion (US$112.2 billion) in cash, via a pre-conditional scheme of arrangement. Under the terms of the transaction, the bidder paid a revised price of GBP45 (US$69.1155) in cash per target share, with a partial share alternative which comprises up to 326 million shares for approximately 41.6% of SABMiller's share capital, was subject to pre-conditions. The offer represents a 53% premium to SABMiller's closing share price of GBP29.34 (US$45.1) on September 14, 2015. SABMiller shareholders who will elect for the partial share alternative will receive 0.483969 AB InBev restricted shares for every 1 SABmiller share, plus GBP4.6588 (US$7.1555) in cash per target share. The cash offer was financed through existing cash resources and new third party debt. The acquisition would enhance AB InBev's market presence in Colombia, Peru and Africa. Moreover, both parties announced the sale of SABmiller's 58% majority stake in MillerCoors LLC to Molson Coors Brewing Co.
B8: SABMiller Ltd | C8: Asahi Group Holdings Ltd. | D8: 42717 | E8: Complete | F8: 7744.2049 | G8: 7744.2049 | H8: - | I8: =G8/L8 -> 523.84773 | J8: NA | K8: NA | L8: 14.783313 | O8: Germany | Q8: Asahi Group Holdings Ltd acquired 8 Central & Eastern European subsidiaries of SABMiller Ltd, a subsidiary of Anheuser-Busch InBev SA/NV for approximately EUR7.3 billion (US$7.7 billion) in cash, funded by bank loans. Approximately EUR23.7 million (US$25.1 million) was also be paid for advisory and related fees. The 8 subsidiaries were mainly located in Czech Republic, Slovakia, Poland, Hungary, and Romania and engages in manufacturing and distributing beers and beverages. Earlier in June 2016, several companies were rumored to be interested to acquire the Central and Eastern European Business.
B9: Refresco Group BV (Old) | C9: BC Investment Management Corp.; PAI Partners SAS; Refresco Group NV /Private Group/ | D9: 42837 | E9: Complete | F9: 2409.7496 | G9: 2409.7496 | H9: 2395.8742 | I9: =G9/L9 -> 244.317 | J9: =I9/H9 -> 0.10197405 | K9: =G9/H9 -> 1.0057914 | L9: 9.863209 | O9: Netherlands | Q9: A private group led by the private equity arm of PAI Partners SAS and BC Investment Management Corp acquired Refresco Group NV for a revised offer of EUR1.6 billion (US$1.7 billion) in cash. The acquisition was funded via debt and equity financing. PAI Partners SAS paid EUR20 (US$21.3) cash for every target share sought, representing a premium of 22% over Refresco Group NV's closing price on July 25, 2017. Refresco Group NV is located in Rotterdam, Zuid-Holland, the Netherlands and engages in the bottling of beverages for retailers and brands. The company has approximately 5,500 employees. On April 3, 2018 the offer closed with 80,655,933 shares, representing 99.4% of Refresco Group NV, tendered. PAI Partners SAS intends to launch a compulsory acquisition procedure to acquire the remaining shares not tendered in the offer.
B10: Saigon Beer Alcohol Beverage Corp | C10: Thai Beverage Public Co., Ltd.; Vietnam Beverage Co. Ltd. | D10: 43086 | E10: Complete | F10: 4840.1643 | G10: 8638.2876 | H10: 1433.7143 | I10: =G10/L10 -> 242.27152 | J10: =I10/H10 -> 0.16898173 | K10: =G10/H10 -> 6.025111 | L10: 35.655398 | O10: Vietnam | Q10: Vietnam Beverage Co Ltd, indirectly owned by Thai Beverage Public Co Ltd, acquired a 53.6% majority stake in Saigon Beer Alcohol Beverage Corp from the Government of Vietnam for VND110 trillion (US$4.8 billion) in cash. Under the terms, Vietnam Beverage Co Ltd paid VND0.32 million (US$14.09) cash per share. The offer price was funded through a mix of its existing equity capital and loans. The transaction will enhance the business portfolio of both companies. Based in Ho Chi Minh City, Vietnam, Saigon Beer Alcohol Beverage Corp engages in the manufacture and trading of beer, alcohol and beverages.
B11: Dr Pepper Snapple Group, Inc | C11: Keurig Green Mountain, Inc. | D11: 43129 | E11: Complete | F11: 27024.926 | G11: 27024.926 | H11: 6704 | I11: =G11/L11 -> 1580.405 | J11: =I11/H11 -> 0.23574061 | K11: =G11/H11 -> 4.0311644 | L11: 17.1 | M11: 600 | N11: =M11/H11 -> 0.089498807 | O11: USA | Q11: Keurig Green Mountain Inc, acquired Dr Pepper Snapple Group Inc for US$22.7 billion in special cash dividend and stock. Under the terms of the transaction, shareholders of Dr. Pepper Snapple Group Inc received US$103.75 special cash dividend for every share owned. The transaction will be funded through senior notes and borrowings under new credit facilities. The acquisition creates a new beverage company to be called Keurig Dr. Pepper and begins trading on the New York Stock Exchange on July 10 under the symbol "KDP". Located in Plano, Texas, United States, Dr. Pepper Snapple Group Inc manufactures and markets non-alcoholic beverages. Following completion of the deal, Keurig Green Mountain Inc and its investors will hold 87% in the new company and Dr. Pepper Snapple Group Inc will hold the remaining 13%.
B12: Sichuan Swellfun Co Ltd | C12: Grand Metropolitan International Holdings Ltd.; Grand Metropolitan Ltd. | D12: 43276 | E12: Complete | F12: 946.22564 | G12: 4551.0063 | H12: 306.95899 | I12: =G12/L12 -> 83.88854 | J12: =I12/H12 -> 0.27328909 | K12: =G12/H12 -> 14.826106 | L12: 54.250632 | O12: China | Q12: Grand Metropolitan International Holdings Ltd, owned by Diageo Plc, acquired an additional 20.3% minority stake in Sichuan Swellfun Co Ltd for RMB6.1 billion (US$936.8 million) in cash, via a partial tender offer. Under the terms of the transaction, the bidder paid RMB61.38 (US$9.5) cash for the shares of the target. The offer price represents a 22.6% premium over the closing price of Sichuan Swellfun Co Ltd on June 25, 2018. Upon completion of the offer, Diageo Plc will have a 60% majority stake ownership in the target. Sichuan Swellfun Co Ltd is located in Chengdu, Sichuan, China and manufactures and distributes antibiotics. The company is also engaged in liquor production and distribution.
B13: Sodastream International | C13: PepsiCo | D13: 43332 | E13: Complete | F13: 3307.95 | G13: 3136.249 | H13: 612.572 | I13: 126.741 | J13: =I13/H13 -> 0.20689976 | K13: =G13/H13 -> 5.1198047 | L13: =G13/I13 -> 24.745339 | O13: Israel | Q13: PepsiCo announces plans to acquire at-home carbonated drink maker SodaStream for $3.2 billion. PepsiCo will pay $144.00 per share in cash for SodaStream’s outstanding stock, which is a 32 percent premium to its 30-day volume weighted average price. The deal gives Pepsi a new line through which it can reach customers in their homes, rather than through stores. Sodastream helped create the market for in-home soda making, but in recent years it has promoted the product as a tool to make carbonated water, accommodating for changing tastes.
B14: The Fuller's Beer Co Ltd | C14: Asahi Europe Ltd. | D14: 43490 | E14: Complete | F14: 326.1 | G14: 326.1 | H14: - | I14: =G14/L14 -> 13.82664 | J14: NA | K14: NA | L14: 23.584905 | O14: UK | Q14: Asahi Europe, a subsidiary of Asahi Group Holdings, acquired the business related to beer production and manufacturing from Fuller Smith & Turner Plc for GBP250 million (US$326.1 million)in cash. In addition, GBP4.2 million (US$5.5 million) will be paid for advisory related fees. The assets to be acquired are located in United Kingdom and produce and brew beer, cider and soft drinks and which collectively had an EBITDA of GBP10.6 million (US$13.8 million) in the period ending in March 2018.
B15: CUB Pty Ltd. | C15: Asahi Group Holdings Ltd. | D15: 43665 | E15: Complete | F15: 11264.8 | G15: 11264.8 | H15: - | I15: =G15/L15 -> 756.8538 | J15: NA | K15: NA | L15: 14.88372 | N15: 0.06 | O15: Australia | Q15: Asahi Group Holdings agreed to acquire CUB Pty Ltd, a subsidiary of Fosters Group Pty Ltd and ultimately owned by Anheuser-Busch InBev SA/NV, for an enterprise value of AUD16 billion (US$11.3 billion). CUB Pty Ltd is located in Victoria, Australia and operates breweries. The company has around 1,310 employees and has an EBITDA of AUD1.1 billion (US$774.5 million) for the fiscal year ended December 2018.
B16: Primo Water Corp. | C16: Cott Corp. (Canada) | D16: 43843 | E16: Complete | F16: 765.5626 | G16: 765.5626 | H16: 307.156 | I16: =G16/L16 -> 45.536002 | J16: =I16/H16 -> 0.14825041 | K16: =G16/H16 -> 2.4924227 | L16: 16.812249 | M16: 35 | N16: =M16/H16 -> 0.11394861 | O16: USA | Q16: Cott Corp entered into a definitive agreement to acquire Primo Water Corp for US$564.3 million in cash and stock. The acquisition will be funded through Cott Corp's sales and revenues, debt financing and by issuing new shares. The acquisition will expand Cott Corp's channel diversification and consumer reach. Primo Water Corp is located in Winston-Salem, North Carolina, United States and manufactures and markets purified bottled water.
B17: Rockstar, Inc. | C17: PepsiCo, Inc. | D17: 43901 | E17: Complete | F17: 3850 | G17: 3850 | H17: - | I17: NA | J17: NA | K17: NA | L17: NA | O17: USA | Q17: PepsiCo Inc acquired Rockstar Inc, doing business as Rockstar Energy Drink, for US$3.85 billion. The transaction accelerates PepsiCo Inc's capabilities to expand its presence in existing brands such as Mountain Dew. Founded in 2001, Rockstar Inc is located in Las Vegas, Nevada, United States and provides energy drinks to athletes and rock stars.
B18: Coca-Cola Amatil Ltd. | C18: Coca-Cola European Partners Plc | D18: 44129 | E18: Complete | F18: 5946.8855 | G18: 8056.9584 | H18: 3269.3145 | I18: =G18/L18 -> 576.13114 | J18: =I18/H18 -> 0.17622384 | K18: =G18/H18 -> 2.4644183 | L18: 13.984591 | O18: Australia | Q18: Coca-Cola European Partners Plc acquired the remaining 69.2% stake not yet owned in Coca-Cola Amatil Ltd for a revised amount of AUD6.7 billion (US$4.7 billion), representing a 23% premium to the 1-week volume weighted average price. Both companies are bottlers of Coca-Cola products. Coca-Cola Amatil Ltd is located in North Sydney, New South Wales (NSW), Australia.
B19: CANarchy Craft Brewery Collective LLC | C19: Monster Beverage Corporation | D19: 44213 | E19: Complete | F19: 330 | G19: 330 | H19: 129.12 | I19: NA | J19: NA | K19: =G19/H19 -> 2.5557621 | L19: =K19/$D$41 -> 8.3888209 | O19: USA | Q19: Monster Beverage Corporation announced today that it has entered into a definitive agreement to acquire CANarchy Craft Brewery Collective LLC, a craft beer and hard seltzer company for $330 million in cash. CANarchy will function independently, retaining its own organizational structure and team. Evercore served as financial advisor to Monster.
B20: Nestle Waters North America, Inc. | C20: Round Hill Investments LLC; One Rock Capital Partners LLC; Nestle SA /North American Water Brands/ /Private Group/ | D20: 44243 | E20: Complete | F20: 4300 | G20: 4300 | H20: 3820.65 | I20: NA | J20: NA | K20: =G20/H20 -> 1.1254629 | L20: =K20/$D$41 -> 3.694126 | O20: USA | Q20: A private group led by One Rock Capital Partners LLC and Round Hill Investments LLC acquired Nestle Waters North America Inc from Nestlé SA for US$4.3 billion in cash. The transaction was funded through secured and unsecured debt. The transaction also includes Poland Spring, Pure Life, Deer Park, Poland Spring, Ozarka, Ice Mountain, Zephyrhills and Arrowhead brands to be sold. Nestlé SA's international premium brands including Perrier, S.Pellegrino and Acqua Panna are not part of the deal. Nestle Waters North America, Inc is located in Stamford, Connecticut and produces, markets, and distributes bottled water. It has around 7,000 employees in United States and more than 230 in Canada.
B21: HyEdge, Inc. | C21: Ficaar, Inc. | D21: 44357 | E21: Complete | F21: 308.9553 | G21: 308.9553 | H21: 2.279297 | I21: NA | J21: NA | K21: =G21/H21 -> 135.5485 | L21: =K21/$D$41 -> 444.91314 | O21: USA | Q21: Ficaar Inc acquired HyEdge Inc for US$772.4 million in stock. Incorporated in 2014, HyEdge Inc is located in Pennsylvania, United States and manufactures and supplies hydrogen infused water products and other consumer goods. For the year ended December 31, 2021, Hydge Inc generated a net revenue of US$2.3 million.
B22: BodyArmor | C22: Coca-Cola Company | D22: 44501 | E22: Complete | F22: 6600 | G22: 6600 | H22: 1400 | I22: NA | J22: NA | K22: =G22/H22 -> 4.7142857 | L22: =K22/$D$41 -> 15.473779 | O22: USA | Q22: The Coca-Cola Company confirms acquisition of remaining 85% stake in BODYARMOR for $5.6B in cash, valuing BodyArmor at $6.6B. The Company acquired the remaining ownership interest in BA Sports Nutrition, LLC (“BodyArmor”).
B23: Refresco Group BV | C23: Kohlberg Kravis Roberts & Co LP | D23: 44614 | E23: Complete | F23: 7900 | G23: 10896.52 | H23: 5012.78 | I23: =G23/L23 -> 808.34718 | J23: =I23/H23 -> 0.16125726 | K23: =G23/H23 -> 2.1737479 | L23: 13.48 | O23: Netherlands | Q23: KKR acquired an undisclosed majority stake in Refresco Group BV, a portfolio company of British Columbia Investment Corp and PAI Partners SAS, for EUR7 billion (US$7.9 billion). The acquisition is in line with global expansion strategy of Refresco Group BV. Following the transaction, British Columbia Investment Corp and PAI Partners SAS would hold minority stake in Refresco Group BV. Founded in 1999, Refresco Group BV is located in Rotterdam, Zuid-Holland, The Netherlands and engages in the bottling of beverages for retailers and brands. The deal was subject to closing conditions. On June 30, 2022, it was announced that, European Commission has approved the transaction.
B24: Vital Pharmaceuticals, Inc. | C24: Monster Beverage Corp. | D24: 45110 | E24: Complete | F24: 362 | G24: 362 | H24: 1400 | I24: NA | J24: NA | K24: =G24/H24 -> 0.25857143 | L24: =K24/$D$41 -> 0.84871335 | O24: USA | Q24: Monster acquired Vital Pharmaceuticals Inc, known as Bang Energy and VPX Sports, for US$362 million via insolvency. The transaction also includes a beverage production facility located in Phoenix, AZ. The transaction was subject to obtaining Bankruptcy Court approval. The acquisition was a significant event in the beverage industry. The low price can be attributed to: bankruptcy and financial distress; Bang Energy had a failed distribution deal, contributing to declining market share; and lawsuits against Bang Energy. The move by Monster strengthened its position in the energy drink market and took advantage of Bang Energy’s established brand and product line.
B25: Vrumona BV | C25: Royal Unibrew A/S | D25: 45110 | E25: Complete | F25: 327.3 | G25: 327.3 | H25: 218.2 | I25: 27.3 | J25: =I25/H25 -> 0.12511457 | K25: =G25/H25 -> 1.5 | L25: =G25/I25 -> 11.989011 | O25: Netherlands | Q25: Royal Unibrew A/S acquired Vrumona BV from Heineken NV for EUR300 million (US$327.3 million) in cash on a debt free basis. Vrumona BV is located in Utrecht, the Netherlands and manufactures and supplies soft drinks. It had generated approximately revenues of EUR200 million (US$218.2 million), adjusted EBITDA was EUR25 million (US$27.3 million)
B26: The Beverage Co. (South Africa) | C26: Varun Beverages Ltd. | D26: 45279 | E26: Pending | F26: 161.00337 | G26: 161.00337 | H26: 194.00906 | I26: NA | J26: NA | K26: =G26/H26 -> 0.82987552 | L26: =K26/$D$41 -> 2.7239144 | O26: South Africa | Q26: Varun Beverages Ltd (one of PepsiCo's largest franchise bottlers worldwide) agreed to acquire The Beverage Co Ltd for ZAR3 billion (US$161 million) in cash. The Beverage Co Ltd is located in Johannesburg, South Africa and manufactures and distributes non-alcoholic beverages. The deal is expected to close on or before July 31, 2024.
A30: Comparable transactions shortlist
B31: =B11 -> Dr Pepper Snapple Group, Inc | C31: =C11 -> Keurig Green Mountain, Inc. | D31: =D11 -> 43129 | E31: =E11 -> Complete | F31: =F11 -> 27024.926 | G31: =G11 -> 27024.926 | H31: =H11 -> 6704 | I31: =I11 -> 1580.405 | ... P31: =P11 -> 0
B32: =B13 -> Sodastream International | C32: =C13 -> PepsiCo | D32: =D13 -> 43332 | E32: =E13 -> Complete | F32: =F13 -> 3307.95 | G32: =G13 -> 3136.249 | H32: =H13 -> 612.572 | I32: =I13 -> 126.741 | ... P32: =P13 -> 0
B33: =B16 -> Primo Water Corp. | C33: =C16 -> Cott Corp. (Canada) | D33: =D16 -> 43843 | E33: =E16 -> Complete | F33: =F16 -> 765.5626 | G33: =G16 -> 765.5626 | H33: =H16 -> 307.156 | I33: =I16 -> 45.536002 | ... P33: =P16 -> 0
B34: =B22 -> BodyArmor | C34: =C22 -> Coca-Cola Company | D34: =D22 -> 44501 | E34: =E22 -> Complete | F34: =F22 -> 6600 | G34: =G22 -> 6600 | H34: =H22 -> 1400 | I34: =I22 -> NA | ... P34: =P22 -> 0
D36: LTM / Actual
D37: ='Red Bull Model'!H3 -> 46022
B39: Red Bull revenue | D39: ='Red Bull Model'!H54 -> 12196
B40: Red Bull EBITDA | D40: ='Red Bull Model'!H60 -> 3715.6681
B41: Red Bull EBITDA margin | D41: =D40/D39 -> 0.30466285
D43: Min | E43: Max | F43: Median
B44: EV / LTM EBITDA | D44: =MIN(L31:L34) -> 15.473779 | E44: =MAX(L31:L34) -> 24.745339 | F44: =MEDIAN(L31:L34) -> 16.956125
B45: Implied enterprise value | D45: =D44*$D$40 -> 57495.429 | E45: =E44*$D$40 -> 91945.467 | F45: =F44*$D$40 -> 63003.331
A47: End

Sheet Valuation_summary
A1: Valuation Summary
A2: All figures in EURm unless otherwise stated
A4: Key data
B5: Total debt | C5: ='Red Bull Model'!H88+'Red Bull Model'!H84 -> 462.4
B6: Total cash and financial assets | C6: ='Red Bull Model'!H74+'Red Bull Model'!H81 -> 2666.7257
C8: LTM / Actual | D8: CY1 | E8: CY2
C9: =YEAR('Red Bull Model'!H3) -> 2025 | D9: =YEAR('Red Bull Model'!I3) -> 2026 | E9: =YEAR('Red Bull Model'!J3) -> 2027
B10: Revenue | C10: ='Red Bull Model'!H54 -> 12196 | D10: ='Red Bull Model'!I54 -> 13252.445 | E10: ='Red Bull Model'!J54 -> 14351.415
B11: EBITDA | C11: ='Red Bull Model'!H60 -> 3715.6681 | D11: ='Red Bull Model'!I60 -> 4174.5202 | E11: ='Red Bull Model'!J60 -> 4664.2097
A13: Trading comparables
C14: Min | D14: Max
C15: =OFFSET(Trading_comps!$C$27,MATCH(C16,Trading_comps!$AG$28:$AG$29,0),0) -> Coca-Cola Company | D15: =OFFSET(Trading_comps!$C$27,MATCH(D16,Trading_comps!$AG$28:$AG$29,0),0) -> Monster Beverage
B16: EV / CY2 Revenue | C16: =MIN(Trading_comps!$AG$28:$AG$29) -> 7.1480363 | D16: =MAX(Trading_comps!$AG$28:$AG$29) -> 8.1557447
B17: Implied enterprise value | C17: =C16*$E$10 -> 102584.43 | D17: =D16*$E$10 -> 117046.47
C19: Min | D19: Max
C20: =OFFSET(Trading_comps!$C$27,MATCH(Valuation_summary!C21,Trading_comps!$AK$28:$AK$29,0),0) -> Coca-Cola Company | D20: =OFFSET(Trading_comps!$C$27,MATCH(Valuation_summary!D21,Trading_comps!$AK$28:$AK$29,0),0) -> Monster Beverage
B21: EV / CY2 EBITDA | C21: =MIN(Trading_comps!$AK$28:$AK$29) -> 19.512756 | D21: =MAX(Trading_comps!$AK$28:$AK$29) -> 24.927213
B22: Implied enterprise value | C22: =C21*$E$11 -> 91011.584 | D22: =D21*$E$11 -> 116265.75
A24: DCF
C25: Min | D25: Max
C26: ="WACC "&TEXT(MIN(DCF!E56:E60),"0.0%")&" and LT growth "&TEXT(MIN(DCF!F55:J55),"0.0%") -> WACC 5.4% and LT growth 2.4% | D26: ="WACC "&TEXT(MAX(DCF!E56:E60),"0.0%")&" and LT growth "&TEXT(MAX(DCF!F55:J55),"0.0%") -> WACC 5.8% and LT growth 2.8%
B27: Implied enterprise value | C27: =MIN(DCF!$G$57:$I$59) -> 109527.32 | D27: =MAX(DCF!$G$57:$I$59) -> 124132.72
B29: Average synergies % of target LTM revenue | C29: =Synergies!$H$10 -> 0.08167749 | D29: =Synergies!$H$10 -> 0.08167749
B30: Value of synergies DCF method | C30: =Synergies!$H$26 -> 20361.606 | D30: =Synergies!$H$26 -> 20361.606
B31: Implied EV including synergies | C31: =C27+C30 -> 129888.93 | D31: =D27+D30 -> 144494.33
A33: Transaction multiples
C34: ="Acquirer: "&OFFSET(Transaction_comps!$C$30,MATCH(C36,Transaction_comps!$L$31:$L$34,0),0) -> Acquirer: Coca-Cola Company | D34: ="Acquirer: "&OFFSET(Transaction_comps!$C$30,MATCH(D36,Transaction_comps!$L$31:$L$34,0),0) -> Acquirer: PepsiCo
C35: Min | D35: Max
B36: EV / LTM EBITDA | C36: =MIN(Transaction_comps!$L$31:$L$34) -> 15.473779 | D36: =MAX(Transaction_comps!$L$31:$L$34) -> 24.745339
B37: Implied enterprise value | C37: =C36*$C$11 -> 57495.429 | D37: =D36*$C$11 -> 91945.467
A39: LBO
B40: IRR range for year 4 exit | C40: 0.22 | D40: 0.2
B41: EV / LTM EBITDA multiple | C41: =LBO!C88 -> 15.25 | D41: =LBO!C90 -> 17.25
B42: Implied enterprise value | C42: =$C$11*C41 -> 56663.939 | D42: =$C$11*D41 -> 64095.275
A44: Football field summary
B46: Method | C46: Min | D46: Difference | E46: Max
B47: =B16 -> EV / CY2 Revenue | C47: =C17 -> 102584.43 | D47: =E47-C47 -> 14462.041 | E47: =D17 -> 117046.47
B48: =B21 -> EV / CY2 EBITDA | C48: =C22 -> 91011.584 | D48: =E48-C48 -> 25254.166 | E48: =D22 -> 116265.75
B49: =A24&" WACC "&TEXT(DCF!E59,"0.0%")&" - "&TEXT(DCF!E57,"0.0%")&", LT growth "&TEXT(DCF!G55,"0.0%")&" - "&TEXT(DCF!I55,"0.0%") -> DCF WACC 5.5% - 5.7%, LT growth 2.5% - 2.7% | C49: =C27 -> 109527.32 | D49: =E49-C49 -> 14605.398 | E49: =D27 -> 124132.72
B50: =A24&" with synergies "&TEXT(C29,"0.0%")&" of revenue" -> DCF with synergies 8.2% of revenue | C50: =C31 -> 129888.93 | D50: =E50-C50 -> 14605.398 | E50: =D31 -> 144494.33
B51: Transaction multiples EV | C51: =C37 -> 57495.429 | D51: =E51-C51 -> 34450.038 | E51: =D37 -> 91945.467
B52: =A39&", IRR "&TEXT(D40,"0.0%")&" to "&TEXT(C40,"0.0%") -> LBO, IRR 20.0% to 22.0% | C52: =C42 -> 56663.939 | D52: =E52-C52 -> 7431.3362 | E52: =D42 -> 64095.275
H53: Standalone valuation range
H54: Y | I54: X
H55: 0 | I55: 95000
H56: =COUNTA($B$47:$B$52) -> 6 | I56: 95000
H58: 0 | I58: 110000
H59: =COUNTA($B$47:$B$52) -> 6 | I59: 110000
A79: End

Sheet Synergies
A1: ="Synergy valuation for "&Info!N5 -> Synergy valuation for Red Bull
C2: ='Red Bull Model'!C2 -> Actual | D2: ='Red Bull Model'!D2 -> Actual | E2: ='Red Bull Model'!E2 -> Actual | F2: ='Red Bull Model'!F2 -> Actual | G2: ='Red Bull Model'!G2 -> Actual / Est. | H2: ='Red Bull Model'!H2 -> Actual / Est. | I2: ='Red Bull Model'!I2 -> Projected | J2: ='Red Bull Model'!J2 -> Projected | K2: ='Red Bull Model'!K2 -> Projected
C3: ='Red Bull Model'!C3 -> 44196 | D3: =EDATE(C3,12) -> 44561 | E3: =EDATE(D3,12) -> 44926 | F3: =EDATE(E3,12) -> 45291 | G3: =EDATE(F3,12) -> 45657 | H3: =EDATE(G3,12) -> 46022 | I3: =EDATE(H3,12) -> 46387 | J3: =EDATE(I3,12) -> 46752 | K3: =EDATE(J3,12) -> 47118
A4: All numbers in EURm unless otherwise stated
B6: Marginal tax rate | H6: ='Red Bull Model'!H20 -> 0.23
B7: WACC | H7: =WACC!D31 -> 0.055612559
B9: LTM revenue | H9: ='Red Bull Model'!H54 -> 12196
B10: Average synergies % LTM revenue | H10: =AVERAGE(Transaction_comps!N7:N26) -> 0.08167749
A12: Synergy value - DCF method
B13: Synergies per annum average (no growth) | I13: =$H$10*$H$9 -> 996.13867 | J13: =$H$10*$H$9 -> 996.13867 | K13: =$H$10*$H$9 -> 996.13867
B14: Synergies % realization | I14: 0.2 | J14: 0.5 | K14: 1
B15: Synergies achieved | I15: =I14*I13 -> 199.22773 | J15: =J14*J13 -> 498.06934 | K15: =K14*K13 -> 996.13867
B16: Synergies post tax | I16: =I15*(1-$H$6) -> 153.40536 | J16: =J15*(1-$H$6) -> 383.51339 | K16: =K15*(1-$H$6) -> 767.02678
B17: Synergies discount rate | H17: =H7 -> 0.055612559
B18: Long term growth rate (inflation only) | H18: 0.02
B19: Terminal value | K19: =K16*(1+H18)/(H17-H18) -> 21968.86
B21: Year | I21: 0.5 | J21: =I21+1 -> 1.5 | K21: =J21+1 -> 2.5
B22: Discount factor | I22: =1/(1+$H$17)^I21 -> 0.97330225 | J22: =1/(1+$H$17)^J21 -> 0.92202602 | K22: =1/(1+$H$17)^K21 -> 0.87345117
B23: Present value | I23: =I22*I16 -> 149.30978 | J23: =J22*J16 -> 353.60932 | K23: =K22*K16 -> 669.96043
B24: Present value of Y1-Y3 | H24: =SUM(I23:K23) -> 1172.8795
B25: Present value of terminal value | H25: =K19*K22 -> 19188.726
B26: Present value of synergies | H26: =SUM(H24:H25) -> 20361.606
A28: End

Sheet M&A
A1: ="M&A analysis for "&C6 -> M&A analysis for Red Bull
A2: All figures in USDm unless otherwise stated
A4: Valuation
B5: Target | J5: Acquirer
B6: Company name | C6: Red Bull | J6: Company name | M6: ='1'!COMPANY_NAME -> Coca-Cola Company
J7: Share price local currency | M7: ='1'!C16 -> 79.84
B8: Exchange rate 1 EUR / X USD | C8: 1.1804 | J8: Exchange rate USD / USD | M8: ='1'!C15 -> 1
J9: Share price US$ | M9: =M7/M8 -> 79.84
B10: Marginal tax rate | C10: ='Red Bull Model'!G20 -> 0.23 | J10: =B10 -> Marginal tax rate | M10: ='1'!COMP_MTR -> 0.223
B12: Max entry EV / LTM EBITDA multiple | C12: 25 | J12: Diluted shares outstanding | M12: ='1'!DSO -> 4316.0291
B13: LTM EBITDA | C13: ='Red Bull Model'!F60*FX -> 3699.4317 | J13: Diluted equity value | M13: ='1'!D36 -> 344591.76
B14: Debt and equivalents | C14: =('Red Bull Model'!F88+'Red Bull Model'!F84)*FX -> 559.03744 | J14: Debt and equivalents | M14: ='1'!G31+'1'!G32+'1'!G33 -> 45492
B15: Cash | C15: ='Red Bull Model'!F74*FX -> 705.99724 | J15: Cash | M15: =('1'!J31+'1'!J32) -> 15806
B16: Financial assets | C16: ='Red Bull Model'!F81*FX -> 1423.3263 | J16: Other adjustments | M16: =('1'!G35-'1'!J34-'1'!J33)*-1 -> 18129
B17: Acquisition enterprise value | C17: =C13*C12 -> 92485.791 | J17: Acquirer enterprise value | M17: =SUM(M13:M14)-SUM(M15:M16) -> 356148.76
A19: Earnings (USD)
B20: Date | C20: LTM | D20: CY1 | E20: CY2 | F20: CY3 | J20: Date | M20: =C20 -> LTM | N20: =D20 -> CY1 | O20: =E20 -> CY2 | P20: =F20 -> CY3
B21: Revenue | C21: ='Red Bull Model'!H54*FX -> 14396.158 | D21: ='Red Bull Model'!I54*FX -> 15643.186 | E21: ='Red Bull Model'!J54*FX -> 16940.41 | F21: ='Red Bull Model'!K54*FX -> 18244.411 | J21: Revenue | M21: ='1'!H44 -> 48062 | N21: ='1'!I44 -> 49005 | O21: ='1'!J44 -> 49824.7 | P21: ='1'!K44 -> 52528.6
B22: EBITDA | C22: ='Red Bull Model'!H60*FX -> 4385.9746 | D22: ='Red Bull Model'!I60*FX -> 4927.6037 | E22: ='Red Bull Model'!J60*FX -> 5505.6331 | F22: ='Red Bull Model'!K60*FX -> 6093.6332 | J22: EBITDA | M22: ='1'!H55 -> 16063 | N22: ='1'!I55 -> 17272.8 | O22: ='1'!J55 -> 18252.1 | P22: ='1'!K55 -> 19728.3
B23: EBIT | C23: ='Red Bull Model'!H63*FX -> 3799.5361 | D23: ='Red Bull Model'!I63*FX -> 4274.4401 | E23: ='Red Bull Model'!J63*FX -> 4782.6721 | F23: ='Red Bull Model'!K63*FX -> 5315.0236 | J23: EBIT | M23: ='1'!G53 -> 15013 | N23: ='1'!H53 -> 15013 | O23: ='1'!I53 -> 16172.8 | P23: ='1'!J53 -> 17152.1
B24: Net income | C24: ='Red Bull Model'!H71*FX -> 2847.9698 | D24: ='Red Bull Model'!I71*FX -> 3209.789 | E24: ='Red Bull Model'!J71*FX -> 3584.288 | F24: ='Red Bull Model'!K71*FX -> 3989.953 | J24: EPS | N24: ='1'!I56 -> 3.23 | O24: ='1'!J56 -> 3.46 | P24: ='1'!K56 -> 3.7
A26: Key assumptions
B27: Fees % enterprise value | C27: 0.01
B28: Equity financing % | C28: 0.7
B29: Cost of debt | C29: 0.05
B30: Interest rate on cash | C30: 0.03
B31: Synergies % LTM target revenue | D31: =Synergies!$H$10 -> 0.08167749 | E31: =Synergies!$H$10 -> 0.08167749 | F31: =Synergies!$H$10 -> 0.08167749
B32: Synergies run rate | D32: =Synergies!I14 -> 0.2 | E32: =Synergies!J14 -> 0.5 | F32: =Synergies!K14 -> 1
A34: Sources and uses of funds
B35: Acquisition equity value | C35: =C17+C15+C16-C14 -> 94056.078 | F35: Equity financing | H35: =C28*C35 -> 65839.254
B36: Fees | C36: =C27*C17 -> 924.85791 | F36: Target cash | H36: =C15 -> 705.99724
B37: Refinanced target debt | C37: =C14 -> 559.03744 | F37: Debt financing | H37: =C38-H36-H35 -> 28994.721
B38: Total uses of funds | C38: =SUM(C35:C37) -> 95539.973 | F38: Total sources of funds | H38: =SUM(H35:H37) -> 95539.973
A40: Income statement combination | C40: LTM | D40: CY1 | E40: CY2 | F40: CY3
B41: Acquirer EBITDA | C41: =M22 -> 16063 | D41: =N22 -> 17272.8 | E41: =O22 -> 18252.1 | F41: =P22 -> 19728.3
B42: Target EBITDA | C42: =C22 -> 4385.9746 | D42: =D22 -> 4927.6037 | E42: =E22 -> 5505.6331 | F42: =F22 -> 6093.6332
B43: Synergies | D43: =$D$31*D21*D32 -> 255.53924 | E43: =$D$31*E21*E32 -> 691.82507 | F43: =$D$31*F21*F32 -> 1490.1577
B44: Pro-forma EBITDA | C44: =SUM(C41:C43) -> 20448.975 | D44: =SUM(D41:D43) -> 22455.943 | E44: =SUM(E41:E43) -> 24449.558 | F44: =SUM(F41:F43) -> 27312.091
B46: Acquirer net income | D46: =N24*$M$12 -> 13940.774 | E46: =O24*$M$12 -> 14933.461 | F46: =P24*$M$12 -> 15969.308
B47: Target net income | D47: =D24 -> 3209.789 | E47: =E24 -> 3584.288 | F47: =F24 -> 3989.953
B48: Synergies post-tax | D48: =D43*(1-$C$10) -> 196.76521 | E48: =E43*(1-$C$10) -> 532.70531 | F48: =F43*(1-$C$10) -> 1147.4214
B49: Interest expense on acquisition debt, after tax | D49: =$C$29*$H$37*(1-$M$10)*-1 -> -1126.4449 | E49: =$C$29*$H$37*(1-$M$10)*-1 -> -1126.4449 | F49: =$C$29*$H$37*(1-$M$10)*-1 -> -1126.4449
B50: Interest expense saved on refinanced target debt, after tax | D50: =$C$37*(1-$C$10)*$C$29 -> 21.522941 | E50: =$C$37*(1-$C$10)*$C$29 -> 21.522941 | F50: =$C$37*(1-$C$10)*$C$29 -> 21.522941
B51: Interest income foregone on target cash used, after tax | D51: =$H$36*$C$30*(1-$C$10)*-1 -> -16.308536 | E51: =$H$36*$C$30*(1-$C$10)*-1 -> -16.308536 | F51: =$H$36*$C$30*(1-$C$10)*-1 -> -16.308536
B52: Pro-forma net income | D52: =SUM(D46:D51) -> 16226.098 | E52: =SUM(E46:E51) -> 17929.223 | F52: =SUM(F46:F51) -> 19985.452
B54: Acquirer diluted shares outstanding | D54: =$M$12 -> 4316.0291 | E54: =$M$12 -> 4316.0291 | F54: =$M$12 -> 4316.0291
B55: New shares issued | D55: =$H$35/$M$7 -> 824.63996 | E55: =$H$35/$M$7 -> 824.63996 | F55: =$H$35/$M$7 -> 824.63996
B56: Pro-forma diluted shares outstanding | D56: =SUM(D54:D55) -> 5140.6691 | E56: =SUM(E54:E55) -> 5140.6691 | F56: =SUM(F54:F55) -> 5140.6691
B58: Pre-deal EPS | D58: =N24 -> 3.23 | E58: =O24 -> 3.46 | F58: =P24 -> 3.7
B59: Pro-forma EPS | D59: =D52/D56 -> 3.1564175 | E59: =E52/E56 -> 3.4877218 | F59: =F52/F56 -> 3.8877141
B60: Accretion (dilution) % | D60: =D59/D58-1 -> -0.022780963 | E60: =E59/E58-1 -> 0.0080120747 | F60: =F59/F58-1 -> 0.050733539
B61: Additional synergies to breakeven | D61: =(D58-D59)*D56/(1-$C$10) -> 491.25108 | E61: =(E58-E59)*E56/(1-$C$10) -> -185.07596 | F61: =(F58-F59)*F56/(1-$C$10) -> -1253.2156
A63: Sensitivity
B64: Analysis of CY3 EPS accretion / dilution arising from sensitizing EV multiple and capital structure | K64: Red Bull LTM EBITDA | M64: =C42 -> 4385.9746
F66: % equity financing | O66: % equity financing
C67: =F60 -> 0.050733539 | D67: =E67-0.1 -> 0.5 | E67: =F67-0.1 -> 0.6 | F67: 0.7 | G67: =F67+0.1 -> 0.8 | H67: =G67+0.1 -> 0.9 | L67: =F60 -> 0.050733539 | M67: =N67-0.1 -> 0.5 | N67: =O67-0.1 -> 0.6 | O67: 0.7 | P67: =O67+0.1 -> 0.8 | Q67: =P67+0.1 -> 0.9
C68: =C69-1 -> 21 | D68: 0.097833153 | E68: 0.092588029 | F68: 0.087550727 | G68: 0.082709136 | H68: 0.078052067 | L68: =C68*$M$64 -> 92105.467 | M68: 0.061867523 | N68: 0.05664269 | O68: 0.051656513 | P68: 0.046893005 | Q68: 0.042337576
C69: =C70-1 -> 22 | D69: 0.088476456 | E69: 0.083214237 | F69: 0.078168846 | G69: 0.073327152 | H69: 0.068677063 | L69: =C69*$M$64 -> 96491.442 | M69: 0.051187609 | N69: 0.046013421 | O69: 0.041084802 | P69: 0.036384676 | Q69: 0.031897513
C70: =C71-1 -> 23 | D70: 0.07920899 | E70: 0.073945374 | F70: 0.068906867 | G70: 0.064079332 | H70: 0.059449789 | L70: =C70*$M$64 -> 100877.42 | M70: 0.040626038 | N70: 0.035521923 | O70: 0.03066902 | P70: 0.026049229 | Q70: 0.021646148
B71: Acquisition EV / EBITDA multiple | C71: =C72-1 -> 24 | D71: 0.070029484 | E71: 0.064779687 | F71: 0.059762507 | G71: 0.054962818 | H71: 0.050366779 | K71: Acquisition EV | L71: =C71*$M$64 -> 105263.39 | M71: 0.030180853 | N71: 0.025165536 | O71: 0.020405743 | P71: 0.015882433 | Q71: 0.011578408
C72: 25 | D72: 0.060936692 | E72: 0.055715464 | F72: 0.050733539 | G72: 0.045974834 | H72: 0.041424676 | L72: =C72*$M$64 -> 109649.37 | M72: 0.019850142 | N72: 0.014941666 | O72: 0.010291646 | P72: 0.0058801927 | Q72: 0.001689406
C73: =C72+1 -> 26 | D73: 0.051929391 | E73: 0.046751028 | F73: 0.041817792 | G73: 0.037112681 | H73: 0.032620228 | L73: =C73*$M$64 -> 114035.34 | M73: 0.0096320319 | N73: 0.0048477853 | O73: 0.00032349895 | P73: -0.0039614548 | Q73: -0.0080255776
C74: =C73+1 -> 27 | D74: 0.043006382 | E74: 0.037884742 | F74: 0.033013151 | G74: 0.028373734 | H74: 0.02395028 | L74: =C74*$M$64 -> 118421.32 | M74: -0.00047530754 | N74: -0.0051185686 | O74: -0.009501834 | P74: -0.013646346 | Q74: -0.017571096
C75: =C74+1 -> 28 | D75: 0.034166486 | E75: 0.029115001 | F75: 0.024317551 | G75: 0.019755442 | H75: 0.015411773 | L75: =C75*$M$64 -> 122807.29 | M75: -0.010473668 | N75: -0.014959798 | O75: -0.0191874 | P75: -0.023178198 | Q75: -0.026951544
C76: =C75+1 -> 29 | D76: 0.025408547 | E76: 0.020440238 | F76: 0.015728979 | G76: 0.011255324 | H76: 0.0070017401 | L76: =C76*$M$64 -> 127193.26 | M76: -0.020364803 | N76: -0.024678244 | O76: -0.028736161 | P76: -0.032560607 | Q76: -0.036171168
A78: Leverage ratios
C79: LTM | D79: CY1 | E79: CY2 | F79: CY3
B80: Acquirer net debt pre-deal | C80: =$M$14-$M$15 -> 29686 | D80: =$M$14-$M$15 -> 29686 | E80: =$M$14-$M$15 -> 29686 | F80: =$M$14-$M$15 -> 29686
B81: Acquirer EBITDA pre deal | C81: =M22 -> 16063 | D81: =N22 -> 17272.8 | E81: =O22 -> 18252.1 | F81: =P22 -> 19728.3
B82: Acquirer net debt / EBITDA | C82: =C80/C81 -> 1.8480981 | D82: =D80/D81 -> 1.7186559 | E82: =E80/E81 -> 1.626443 | F82: =F80/F81 -> 1.5047419
B84: Acquisition debt | D84: =$H$37 -> 28994.721 | E84: =$H$37 -> 28994.721 | F84: =$H$37 -> 28994.721
B85: Pro-forma net debt | D85: =D84+D80 -> 58680.721 | E85: =E84+E80 -> 58680.721 | F85: =F84+F80 -> 58680.721
B86: Pro-forma EBITDA | D86: =D44 -> 22455.943 | E86: =E44 -> 24449.558 | F86: =F44 -> 27312.091
B87: Pro-forma net debt / EBITDA | D87: =D85/D86 -> 2.6131488 | E87: =E85/E86 -> 2.4000729 | F87: =F85/F86 -> 2.1485254
B89: Current acquirer credit rating | C89: ='1'!$C$19 -> A+ | D89: ='1'!$C$19 -> A+ | E89: ='1'!$C$19 -> A+ | F89: ='1'!$C$19 -> A+
A91: Price earnings analysis
B92: Acquirer P/E | D92: =$M$9/N24 -> 24.718266 | E92: =$M$9/O24 -> 23.075145 | F92: =$M$9/P24 -> 21.578378
B93: Debt P/E | D93: =1/($C$29*(1-$M$10)) -> 25.740026 | E93: =1/($C$29*(1-$M$10)) -> 25.740026 | F93: =1/($C$29*(1-$M$10)) -> 25.740026
B94: Acquisition P/E | D94: =$C$35/D24 -> 29.302885 | E94: =$C$35/E24 -> 26.241217 | F94: =$C$35/F24 -> 23.57323
A96: Return on capital analysis
B97: Acquisition equity value | C97: =$C$35 -> 94056.078
B98: Fees | C98: =C36 -> 924.85791
B99: Net debt | C99: =C37 -> 559.03744
B100: Invested capital | C100: =SUM(C97:C99) -> 95539.973
B102: EBIT | D102: ='Red Bull Model'!G63*FX -> 3462.512
B103: Synergies | D103: =D43 -> 255.53924
B104: NOPAT with synergies | D104: =SUM(D102:D103)*(1-C10) -> 2862.8994
B106: Return on invested capital | D106: =D104/C100 -> 0.029965462
B107: WACC | D107: =WACC!D31 -> 0.055612559
A109: Analysis at various prices
B111: Acquisition EV / EBITDA multiple | C111: LTM EBITDA | D111: EV
B112: 15 | C112: =$C$42 -> 4385.9746 | D112: =C112*B112 -> 65789.62
B113: =B112+1 -> 16 | C113: =$C$42 -> 4385.9746 | D113: =C113*B113 -> 70175.594
B114: =B113+1 -> 17 | C114: =$C$42 -> 4385.9746 | D114: =C114*B114 -> 74561.569
B115: =B114+1 -> 18 | C115: =$C$42 -> 4385.9746 | D115: =C115*B115 -> 78947.544
B116: =B115+1 -> 19 | C116: =$C$42 -> 4385.9746 | D116: =C116*B116 -> 83333.518
B117: =B116+1 -> 20 | C117: =$C$42 -> 4385.9746 | D117: =C117*B117 -> 87719.493
B118: =B117+1 -> 21 | C118: =$C$42 -> 4385.9746 | D118: =C118*B118 -> 92105.467
B119: =B118+1 -> 22 | C119: =$C$42 -> 4385.9746 | D119: =C119*B119 -> 96491.442
B120: =B119+1 -> 23 | C120: =$C$42 -> 4385.9746 | D120: =C120*B120 -> 100877.42
...

Sheet LBO
A1: ="LBO valuation for "&Info!N5 -> LBO valuation for Red Bull
C2: ='Red Bull Model'!C2 -> Actual | D2: ='Red Bull Model'!D2 -> Actual | E2: ='Red Bull Model'!E2 -> Actual | F2: ='Red Bull Model'!F2 -> Actual | G2: ='Red Bull Model'!G2 -> Actual / Est. | H2: ='Red Bull Model'!H2 -> Actual / Est. | I2: ='Red Bull Model'!I2 -> Projected | J2: ='Red Bull Model'!J2 -> Projected | ... P2: ='Red Bull Model'!P2 -> Projected
C3: ='Red Bull Model'!C3 -> 44196 | D3: ='Red Bull Model'!D3 -> 44561 | E3: ='Red Bull Model'!E3 -> 44926 | F3: ='Red Bull Model'!F3 -> 45291 | G3: ='Red Bull Model'!G3 -> 45657 | H3: ='Red Bull Model'!H3 -> 46022 | I3: ='Red Bull Model'!I3 -> 46387 | J3: ='Red Bull Model'!J3 -> 46752 | ... P3: ='Red Bull Model'!P3 -> 48944
A4: All numbers in EURm unless otherwise stated
A6: Assumptions | I6: Sources and uses of funds | O6: X LTM EBITDA
B7: LTM EBITDA | H7: ='Red Bull Model'!H60 -> 3715.6681 | I7: Enterprise value | K7: =H7*H9 -> 92891.703 | M7: Senior debt | O7: 4 | P7: =O7*H7 -> 14862.672
B8: Max debt / EBITDA multiple | H8: 6 | I8: Fees | K8: =G17*K7 -> 928.91703 | M8: Unsecured notes | O8: =H8-O7 -> 2 | P8: =O8*H7 -> 7431.3362
B9: Max entry EV / LTM EBITDA multiple | H9: 25 | I9: Total uses of funds | K9: =SUM(K7:K8) -> 93820.62 | M9: Equity | P9: =K9-P8-P7 -> 71526.611
B10: Max exit EV / LTM EBITDA multiple | H10: =H9 -> 25 | M10: Total sources of funds | P10: =SUM(P7:P9) -> 93820.62
B12: Cost of debt financing - spread | G12: 0.03
B13: Risk free rate | G13: =WACC!D17 -> 0.027
B14: Cost of senior debt | G14: =SUM(G12:G13) -> 0.057
B15: Cost of unsecured notes | G15: 0.0725
B16: Interest rate on cash | G16: 0.03
B17: Fees % of enterprise value | G17: 0.01
B18: Exit year | G18: 4
A20: Key numbers
B21: Revenue | I21: ='Red Bull Model'!I54 -> 13252.445 | J21: ='Red Bull Model'!J54 -> 14351.415 | K21: ='Red Bull Model'!K54 -> 15456.126 | L21: ='Red Bull Model'!L54 -> 16603.762 | M21: ='Red Bull Model'!M54 -> 17718.971 | N21: ='Red Bull Model'!N54 -> 18653.217 | O21: ='Red Bull Model'!O54 -> 19264.34 | P21: ='Red Bull Model'!P54 -> 19765.213
B22: Cost savings % revenue | G22: 0.01 | H22: 0.01 | I22: 0.01 | J22: 0.01 | K22: 0.01 | L22: 0.01 | M22: 0.01 | N22: 0.01 | O22: 0.01 | P22: 0.01
B23: Cost savings | I23: =I21*I22 -> 132.52445 | J23: =J21*J22 -> 143.51415 | K23: =K21*K22 -> 154.56126 | L23: =L21*L22 -> 166.03762 | M23: =M21*M22 -> 177.18971 | N23: =N21*N22 -> 186.53217 | O23: =O21*O22 -> 192.6434 | P23: =P21*P22 -> 197.65213
B24: EBITDA | I24: ='Red Bull Model'!I60 -> 4174.5202 | J24: ='Red Bull Model'!J60 -> 4664.2097 | K24: ='Red Bull Model'!K60 -> 5162.346 | L24: ='Red Bull Model'!L60 -> 5545.6566 | M24: ='Red Bull Model'!M60 -> 5918.1364 | N24: ='Red Bull Model'!N60 -> 6230.1745 | O24: ='Red Bull Model'!O60 -> 6434.2896 | P24: ='Red Bull Model'!P60 -> 6601.5812
B25: Adjusted EBITDA | I25: =I24+I23 -> 4307.0447 | J25: =J24+J23 -> 4807.7239 | K25: =K24+K23 -> 5316.9073 | L25: =L24+L23 -> 5711.6942 | M25: =M24+M23 -> 6095.3261 | N25: =N24+N23 -> 6416.7066 | O25: =O24+O23 -> 6626.933 | P25: =P24+P23 -> 6799.2333
B26: Adjusted EBITDA margin | I26: =I25/I21 -> 0.325 | J26: =J25/J21 -> 0.335 | K26: =K25/K21 -> 0.344 | L26: =L25/L21 -> 0.344 | M26: =M25/M21 -> 0.344 | N26: =N25/N21 -> 0.344 | O26: =O25/O21 -> 0.344 | P26: =P25/P21 -> 0.344
B27: Long-term effective tax rate | I27: ='Red Bull Model'!I19 -> 0.255 | J27: ='Red Bull Model'!J19 -> 0.255 | K27: ='Red Bull Model'!K19 -> 0.255 | L27: ='Red Bull Model'!L19 -> 0.255 | M27: ='Red Bull Model'!M19 -> 0.255 | N27: ='Red Bull Model'!N19 -> 0.255 | O27: ='Red Bull Model'!O19 -> 0.255 | P27: ='Red Bull Model'!P19 -> 0.255
A29: Income statement
B30: Revenue | I30: =I21 -> 13252.445 | J30: =J21 -> 14351.415 | K30: =K21 -> 15456.126 | L30: =L21 -> 16603.762 | M30: =M21 -> 17718.971 | N30: =N21 -> 18653.217 | O30: =O21 -> 19264.34 | P30: =P21 -> 19765.213
B31: EBIT pre cost savings | I31: ='Red Bull Model'!I63 -> 3621.1793 | J31: ='Red Bull Model'!J63 -> 4051.7385 | K31: ='Red Bull Model'!K63 -> 4502.731 | L31: ='Red Bull Model'!L63 -> 4877.0561 | M31: ='Red Bull Model'!M63 -> 5191.8026 | N31: ='Red Bull Model'!N63 -> 5464.1272 | O31: ='Red Bull Model'!O63 -> 5626.6616 | P31: ='Red Bull Model'!P63 -> 5765.9766
B32: Cost savings | I32: =I23 -> 132.52445 | J32: =J23 -> 143.51415 | K32: =K23 -> 154.56126 | L32: =L23 -> 166.03762 | M32: =M23 -> 177.18971 | N32: =N23 -> 186.53217 | O32: =O23 -> 192.6434 | P32: =P23 -> 197.65213
B33: Interest expense | I33: =IF(Circswitch=1,I50+I57,0) -> -1344.577 | J33: =IF(Circswitch=1,J50+J57,0) -> -1250.195 | K33: =IF(Circswitch=1,K50+K57,0) -> -1131.8263 | L33: =IF(Circswitch=1,L50+L57,0) -> -991.19237 | M33: =IF(Circswitch=1,M50+M57,0) -> -827.0035 | N33: =IF(Circswitch=1,N50+N57,0) -> -639.48259 | O33: =IF(Circswitch=1,O50+O57,0) -> -401.49672 | P33: =IF(Circswitch=1,P50+P57,0) -> -131.06146
B34: Interest income | I34: =IF(Circswitch=1,I60,0) -> 0 | J34: =IF(Circswitch=1,J60,0) -> 0 | K34: =IF(Circswitch=1,K60,0) -> 0 | L34: =IF(Circswitch=1,L60,0) -> 0 | M34: =IF(Circswitch=1,M60,0) -> 0 | N34: =IF(Circswitch=1,N60,0) -> 0 | O34: =IF(Circswitch=1,O60,0) -> 0 | P34: =IF(Circswitch=1,P60,0) -> 8.346006
B35: Profit before tax | I35: =SUM(I31:I34) -> 2409.1268 | J35: =SUM(J31:J34) -> 2945.0576 | K35: =SUM(K31:K34) -> 3525.4659 | L35: =SUM(L31:L34) -> 4051.9013 | M35: =SUM(M31:M34) -> 4541.9888 | N35: =SUM(N31:N34) -> 5011.1768 | O35: =SUM(O31:O34) -> 5417.8083 | P35: =SUM(P31:P34) -> 5840.9133
B36: Tax expense | I36: =I35*I27*-1 -> -614.32733 | J36: =J35*J27*-1 -> -750.9897 | K36: =K35*K27*-1 -> -898.9938 | L36: =L35*L27*-1 -> -1033.2348 | M36: =M35*M27*-1 -> -1158.2071 | N36: =N35*N27*-1 -> -1277.8501 | O36: =O35*O27*-1 -> -1381.5411 | P36: =P35*P27*-1 -> -1489.4329
B37: Net income | I37: =SUM(I35:I36) -> 1794.7995 | J37: =SUM(J35:J36) -> 2194.0679 | K37: =SUM(K35:K36) -> 2626.4721 | L37: =SUM(L35:L36) -> 3018.6665 | M37: =SUM(M35:M36) -> 3383.7817 | N37: =SUM(N35:N36) -> 3733.3267 | O37: =SUM(O35:O36) -> 4036.2672 | P37: =SUM(P35:P36) -> 4351.4804
A39: Cash flows to service debt
B40: Net income | I40: =I37 -> 1794.7995 | J40: =J37 -> 2194.0679 | K40: =K37 -> 2626.4721 | L40: =L37 -> 3018.6665 | M40: =M37 -> 3383.7817 | N40: =N37 -> 3733.3267 | O40: =O37 -> 4036.2672 | P40: =P37 -> 4351.4804
B41: Depreciation | I41: ='Red Bull Model'!I98 -> 553.34092 | J41: ='Red Bull Model'!J98 -> 612.47123 | K41: ='Red Bull Model'!K98 -> 659.61503 | L41: ='Red Bull Model'!L98 -> 668.60051 | M41: ='Red Bull Model'!M98 -> 726.33375 | N41: ='Red Bull Model'!N98 -> 766.04729 | O41: ='Red Bull Model'!O98 -> 807.62803 | P41: ='Red Bull Model'!P98 -> 835.60457
B42: (Increase) decrease in operating working capital | I42: =SUM('Red Bull Model'!I99:I102) -> 4.5079714 | J42: =SUM('Red Bull Model'!J99:J102) -> -56.585502 | K42: =SUM('Red Bull Model'!K99:K102) -> -34.68711 | L42: =SUM('Red Bull Model'!L99:L102) -> -16.428493 | M42: =SUM('Red Bull Model'!M99:M102) -> -15.964293 | N42: =SUM('Red Bull Model'!N99:N102) -> -13.373794 | O42: =SUM('Red Bull Model'!O99:O102) -> -8.7482706 | P42: =SUM('Red Bull Model'!P99:P102) -> -7.1700291
B43: (Capital expenditure) | I43: ='Red Bull Model'!I105 -> -901.16627 | J43: ='Red Bull Model'!J105 -> -889.7877 | K43: ='Red Bull Model'!K105 -> -958.2798 | L43: ='Red Bull Model'!L105 -> -1029.4333 | M43: ='Red Bull Model'!M105 -> -974.54341 | N43: ='Red Bull Model'!N105 -> -1025.9269 | O43: ='Red Bull Model'!O105 -> -982.48135 | P43: ='Red Bull Model'!P105 -> -1008.0259
B44: Cash flow available for debt repayment | I44: =SUM(I40:I43) -> 1451.4821 | J44: =SUM(J40:J43) -> 1860.166 | K44: =SUM(K40:K43) -> 2293.1202 | L44: =SUM(L40:L43) -> 2641.4052 | M44: =SUM(M40:M43) -> 3119.6077 | N44: =SUM(N40:N43) -> 3460.0733 | O44: =SUM(O40:O43) -> 3852.6656 | P44: =SUM(P40:P43) -> 4171.8891
A46: Debt servicing
B47: Beginning senior debt balance | I47: =H49 -> 14862.672 | J47: =I49 -> 13411.19 | K47: =J49 -> 11551.024 | L47: =K49 -> 9257.9042 | M47: =L49 -> 6616.499 | N47: =M49 -> 3496.8913 | O47: =N49 -> 36.81801 | P47: =O49 -> 0
B48: Issuance (repayment) | I48: =-MIN(I44,I47) -> -1451.4821 | J48: =-MIN(J44,J47) -> -1860.166 | K48: =-MIN(K44,K47) -> -2293.1202 | L48: =-MIN(L44,L47) -> -2641.4052 | M48: =-MIN(M44,M47) -> -3119.6077 | N48: =-MIN(N44,N47) -> -3460.0733 | O48: =-MIN(O44,O47) -> -36.81801 | P48: =-MIN(P44,P47) -> 0
B49: Ending senior debt balance | H49: =P7 -> 14862.672 | I49: =SUM(I47:I48) -> 13411.19 | J49: =SUM(J47:J48) -> 11551.024 | K49: =SUM(K47:K48) -> 9257.9042 | L49: =SUM(L47:L48) -> 6616.499 | M49: =SUM(M47:M48) -> 3496.8913 | N49: =SUM(N47:N48) -> 36.81801 | O49: =SUM(O47:O48) -> 0 | P49: =SUM(P47:P48) -> 0
B50: Interest expense | I50: =$G$14*AVERAGE(H49:I49)*-1 -> -805.80509 | J50: =$G$14*AVERAGE(I49:J49)*-1 -> -711.42312 | K50: =$G$14*AVERAGE(J49:K49)*-1 -> -593.05447 | L50: =$G$14*AVERAGE(K49:L49)*-1 -> -452.42049 | M50: =$G$14*AVERAGE(L49:M49)*-1 -> -288.23162 | N50: =$G$14*AVERAGE(M49:N49)*-1 -> -100.71071 | O50: =$G$14*AVERAGE(N49:O49)*-1 -> -1.0493133 | P50: =$G$14*AVERAGE(O49:P49)*-1 -> 0
B52: Cash flow available for debt, after senior debt repayment | I52: =I44+I48 -> 0 | J52: =J44+J48 -> 0 | K52: =K44+K48 -> 0 | L52: =L44+L48 -> 0 | M52: =M44+M48 -> 0 | N52: =N44+N48 -> 0 | O52: =O44+O48 -> 3815.8476 | P52: =P44+P48 -> 4171.8891
B54: Beginning unsecured notes | I54: =H56 -> 7431.3362 | J54: =I56 -> 7431.3362 | K54: =J56 -> 7431.3362 | L54: =K56 -> 7431.3362 | M54: =L56 -> 7431.3362 | N54: =M56 -> 7431.3362 | O54: =N56 -> 7431.3362 | P54: =O56 -> 3615.4887
B55: Issuance (repayment) | I55: =-MIN(I52,I54) -> 0 | J55: =-MIN(J52,J54) -> 0 | K55: =-MIN(K52,K54) -> 0 | L55: =-MIN(L52,L54) -> 0 | M55: =-MIN(M52,M54) -> 0 | N55: =-MIN(N52,N54) -> 0 | O55: =-MIN(O52,O54) -> -3815.8476 | P55: =-MIN(P52,P54) -> -3615.4887
B56: Ending unsecured notes | H56: =P8 -> 7431.3362 | I56: =SUM(I54:I55) -> 7431.3362 | J56: =SUM(J54:J55) -> 7431.3362 | K56: =SUM(K54:K55) -> 7431.3362 | L56: =SUM(L54:L55) -> 7431.3362 | M56: =SUM(M54:M55) -> 7431.3362 | N56: =SUM(N54:N55) -> 7431.3362 | O56: =SUM(O54:O55) -> 3615.4887 | P56: =SUM(P54:P55) -> 0
B57: Interest expense | I57: =$G$15*AVERAGE(H56:I56)*-1 -> -538.77188 | J57: =$G$15*AVERAGE(I56:J56)*-1 -> -538.77188 | K57: =$G$15*AVERAGE(J56:K56)*-1 -> -538.77188 | L57: =$G$15*AVERAGE(K56:L56)*-1 -> -538.77188 | M57: =$G$15*AVERAGE(L56:M56)*-1 -> -538.77188 | N57: =$G$15*AVERAGE(M56:N56)*-1 -> -538.77188 | O57: =$G$15*AVERAGE(N56:O56)*-1 -> -400.4474 | P57: =$G$15*AVERAGE(O56:P56)*-1 -> -131.06146
B59: Ending cash | H59: 0 | I59: =H59+I44+I48+I55 -> 0 | J59: =I59+J44+J48+J55 -> 0 | K59: =J59+K44+K48+K55 -> 0 | L59: =K59+L44+L48+L55 -> 0 | M59: =L59+M44+M48+M55 -> 0 | N59: =M59+N44+N48+N55 -> 0 | O59: =N59+O44+O48+O55 -> 0 | P59: =O59+P44+P48+P55 -> 556.4004
B60: Interest income | I60: =$G$16*AVERAGE(H59:I59) -> 0 | J60: =$G$16*AVERAGE(I59:J59) -> 0 | K60: =$G$16*AVERAGE(J59:K59) -> 0 | L60: =$G$16*AVERAGE(K59:L59) -> 0 | M60: =$G$16*AVERAGE(L59:M59) -> 0 | N60: =$G$16*AVERAGE(M59:N59) -> 0 | O60: =$G$16*AVERAGE(N59:O59) -> 0 | P60: =$G$16*AVERAGE(O59:P59) -> 8.346006
B62: Beginning debt repaid | I62: =H65 -> 0 | J62: =I65 -> 1451.4821 | K62: =J65 -> 3311.648 | L62: =K65 -> 5604.7683 | M62: =L65 -> 8246.1735 | N62: =M65 -> 11365.781 | O62: =N65 -> 14825.854 | P62: =O65 -> 18678.52
B63: Senior debt repayment | I63: =I48*-1 -> 1451.4821 | J63: =J48*-1 -> 1860.166 | K63: =K48*-1 -> 2293.1202 | L63: =L48*-1 -> 2641.4052 | M63: =M48*-1 -> 3119.6077 | N63: =N48*-1 -> 3460.0733 | O63: =O48*-1 -> 36.81801 | P63: =P48*-1 -> 0
B64: Unsecured notes repayment | I64: =I55*-1 -> 0 | J64: =J55*-1 -> 0 | K64: =K55*-1 -> 0 | L64: =L55*-1 -> 0 | M64: =M55*-1 -> 0 | N64: =N55*-1 -> 0 | O64: =O55*-1 -> 3815.8476 | P64: =P55*-1 -> 3615.4887
B65: Ending debt repaid | H65: 0 | I65: =SUM(I62:I64) -> 1451.4821 | J65: =SUM(J62:J64) -> 3311.648 | K65: =SUM(K62:K64) -> 5604.7683 | L65: =SUM(L62:L64) -> 8246.1735 | M65: =SUM(M62:M64) -> 11365.781 | N65: =SUM(N62:N64) -> 14825.854 | O65: =SUM(O62:O64) -> 18678.52 | P65: =SUM(P62:P64) -> 22294.009
B67: Total debt at acquisition | H67: =$P$7+$P$8 -> 22294.009 | I67: =$P$7+$P$8 -> 22294.009 | J67: =$P$7+$P$8 -> 22294.009 | K67: =$P$7+$P$8 -> 22294.009 | L67: =$P$7+$P$8 -> 22294.009 | M67: =$P$7+$P$8 -> 22294.009 | N67: =$P$7+$P$8 -> 22294.009 | O67: =$P$7+$P$8 -> 22294.009 | P67: =$P$7+$P$8 -> 22294.009
B68: Debt paydown % of total debt | I68: =I65/I67 -> 0.065106374 | J68: =J65/J67 -> 0.14854431 | K68: =K65/K67 -> 0.25140244 | L68: =L65/L67 -> 0.36988294 | M68: =M65/M67 -> 0.50981326 | N68: =N65/N67 -> 0.66501519 | O68: =O65/O67 -> 0.83782689 | P68: =P65/P67 -> 1
A70: Returns to equity holders
B71: Year count | I71: 1 | J71: =I71+1 -> 2 | K71: =J71+1 -> 3 | L71: =K71+1 -> 4 | M71: =L71+1 -> 5 | N71: =M71+1 -> 6 | O71: =N71+1 -> 7 | P71: =O71+1 -> 8
B72: Enterprise value | I72: =$H$10*I25 -> 107676.12 | J72: =$H$10*J25 -> 120193.1 | K72: =$H$10*K25 -> 132922.68 | L72: =$H$10*L25 -> 142792.35 | M72: =$H$10*M25 -> 152383.15 | N72: =$H$10*N25 -> 160417.67 | O72: =$H$10*O25 -> 165673.33 | P72: =$H$10*P25 -> 169980.83
B73: Net debt | I73: =I49+I56-I59 -> 20842.527 | J73: =J49+J56-J59 -> 18982.361 | K73: =K49+K56-K59 -> 16689.24 | L73: =L49+L56-L59 -> 14047.835 | M73: =M49+M56-M59 -> 10928.227 | N73: =N49+N56-N59 -> 7468.1542 | O73: =O49+O56-O59 -> 3615.4887 | P73: =P49+P56-P59 -> -556.4004
B74: Equity value | I74: =I72-I73 -> 86833.59 | J74: =J72-J73 -> 101210.74 | K74: =K72-K73 -> 116233.44 | L74: =L72-L73 -> 128744.52 | M74: =M72-M73 -> 141454.92 | N74: =N72-N73 -> 152949.51 | O74: =O72-O73 -> 162057.84 | P74: =P72-P73 -> 170537.23
B76: Cash flows to equity holders | H76: =P9*-1 -> -71526.611 | I76: =IF($G$18=I71,I74,0) -> 0 | J76: =IF($G$18=J71,J74,0) -> 0 | K76: =IF($G$18=K71,K74,0) -> 0 | L76: =IF($G$18=L71,L74,0) -> 128744.52 | M76: =IF($G$18=M71,M74,0) -> 0 | N76: =IF($G$18=N71,N74,0) -> 0 | O76: =IF($G$18=O71,O74,0) -> 0 | P76: =IF($G$18=P71,P74,0) -> 0
B77: IRR | H77: =IRR(H76:P76) -> 0.15828458
A79: Sensitivity analysis
B80: IRR assuming changes in entry multiple and exit year
E81: Exit year
C82: =H77 -> 0.15828458 | D82: 3 | E82: 4 | F82: 5 | G82: 6
C83: 11 | D83: 0.30085292 | E83: 0.26604102 | F83: 0.24203126 | G83: 0.22164917
C84: =C83+0.25 -> 11.25 | D84: 0.29353506 | E84: 0.25992224 | F84: 0.23671681 | G84: 0.21694837
C85: =C84+1 -> 12.25 | D85: 0.26948541 | E85: 0.23966949 | F85: 0.21902441 | G85: 0.2012248
C86: =C85+1 -> 13.25 | D86: 0.25142753 | E86: 0.22431077 | F86: 0.20549762 | G86: 0.18912242
C87: =C86+1 -> 14.25 | D87: 0.23735967 | E87: 0.21225044 | F87: 0.19480552 | G87: 0.17950352
C88: =C87+1 -> 15.25 | D88: 0.22608564 | E88: 0.20252238 | F88: 0.18613391 | G88: 0.17166642
B89: Entry multiple | C89: =C88+1 -> 16.25 | D89: 0.21684547 | E89: 0.19450607 | F89: 0.17895525 | G89: 0.16515328
C90: =C89+1 -> 17.25 | D90: 0.20913267 | E90: 0.18778416 | F90: 0.17291206 | G90: 0.15965193
C91: =C90+1 -> 18.25 | D91: 0.20259648 | E91: 0.18206526 | F91: 0.16775314 | G91: 0.15494186
C92: =C91+1 -> 19.25 | D92: 0.1969861 | E92: 0.17713966 | F92: 0.16329667 | G92: 0.1508627
C93: =C92+1 -> 20.25 | D93: 0.19211744 | E93: 0.17285246 | F93: 0.15940766 | G93: 0.1472949
C94: =C93+1 -> 21.25 | D94: 0.18785226 | E94: 0.16908676 | F94: 0.15598379 | G94: 0.14414747
C95: =C94+1 -> 22.25 | D95: 0.18408473 | E95: 0.1657526 | F95: 0.15294602 | G95: 0.1413499
C96: =C95+1 -> 23.25 | D96: 0.18073241 | E96: 0.16277966 | F96: 0.1502323 | G96: 0.13884667
C97: =C96+1 -> 24.25 | D97: 0.17773017 | E97: 0.16011213 | F97: 0.14779325 | G97: 0.13659347
C98: =C97+1 -> 25.25 | D98: 0.17502582 | E98: 0.15770514 | F98: 0.14558907 | G98: 0.1345545
C99: =C98+1 -> 26.25 | D99: 0.17257707 | E99: 0.15552225 | F99: 0.14358731 | G99: 0.13270048
C100: =C99+1 -> 27.25 | D100: 0.17034928 | E100: 0.15353349 | F100: 0.14176124 | G100: 0.13100726
C101: =C100+1 -> 28.25 | D101: 0.16831381 | E101: 0.15171404 | F101: 0.14008865 | G101: 0.12945474
... C103: =C102+1 -> 30.25 | D103: 0.16472804 | E103: 0.14850323 | F103: 0.13713239 | G103: 0.12670686
A109: End

Sheet Scratchpad
A1: Scratchpad for additional workings
B3: Leveraged Structure
B4: Total debt / LTM EBITDA | C4: <6x
B5: Senior debt (term B tranche) | C5: Paid off within 7 years
B6: Total debt | C6: 50% paid off within 7 years
B7: Equity to be at least | C7: 0.25 | D7: Of the initial captial structure
B8: Adjustmenents to LTM EBITDA | C8: No greater than 25% of the base EBITDA or unadjusted EBITDA
B10: Equity returns
B11: Returns within a range of 20-25% IRR
B12: Low risk transactions e.g. infrastructure assets a high teens IRR

Sheet Factset codes
A1: Factset codes
B2: Summary sheet code name | T2: Delete sheet on new target ticker
A4: Key data
B5: Ticker | D5: TUMI-US
B6: Country | D6: United States
B7: Analysis date | D7: 42482
B8: Historical year end | D8: 31/12/2015
B9: Last filing date | D9: 01-Jun-16
B10: Calendarize to | D10: 42369
B11: Home currency | D11: USD
B12: Trading information
B13: ="Closing price as at "&TEXT(D7,"dd-mmm-yy") -> Closing price as at 22-Apr-16 | D13: #N/A
B14: 52 week low | D14: #N/A
B15: 52 week high | D15: #N/A
B16: Free float (MM) | D16: #N/A
B17: LTM dividend yield | D17: NA
B18: Historical 5 year beta | D18: 0.6389551
B19: Marginal tax rate | D19: #N/A
B21: Credit rating
B22: 5 year EPS forward growth | D22: -
A24: Balance sheet data
B25: NCI book value | D25: 0
B26: Historical income statement NCI | D26: 0
B27: Basic shares outstanding | D27: 67.661362
B28: Shareholders' equity | D28: 510.953
B29: Balance sheet ST debt | D29: 6.611
B30: Balance sheet LT debt | D30: 0
B31: Financial derivative liabilities | D31: 0
B32: Preferred equity | D32: 0
B33: Balance sheet cash and equivalents | D33: 113.082
B34: ST financial investments | D34: 0
B35: LT financial investments | D35: 1.84
B36: Non-core assets | D36: 0
A38: Earnings and estimates
D39: Latest annual | F39: Old 10-Q/Interim | H39: New 10-Q/interim | L39: FY +1 | N39: FY +2 | P39: FY +3 | R39: FY +4
B40: Date | D40: =D8 -> 31/12/2015 | F40: =EDATE(H40,-12) -> 42094 | H40: 42460 | L40: =EDATE(D40,12) -> 42735 | N40: =EDATE(L40,12) -> 43100 | P40: =EDATE(N40,12) -> 43465 | R40: =EDATE(P40,12) -> 43830
B41: Revenues | D41: 547.655 | F41: 138.52 | H41: 147.517 | L41: #N/A | N41: #N/A | P41: #N/A | R41: #N/A
B42: EBIT | D42: 100.141 | F42: 25.919 | H42: 22.269 | L42: #N/A | N42: #N/A | P42: #N/A | R42: #N/A
B43: Depreciation and amortization | D43: 21.494 | F43: 5.067 | H43: 6.152 | L43: =L44-L42 -> #N/A | N43: =N44-N42 -> #N/A | P43: =P44-P42 -> #N/A | R43: =R44-R42 -> #N/A
B44: EBITDA | D44: =D42+D43 -> 121.635 | F44: =F42+F43 -> 30.986 | H44: =H42+H43 -> 28.421 | L44: #N/A | N44: #N/A | P44: #N/A | R44: #N/A
B45: Gross interest expense | D45: 0.347 | F45: 0.08 | H45: 0 | L45: #N/A | N45: #N/A | P45: #N/A | R45: #N/A
B46: Free cash flow | D46: 50.619 | F46: 16.303 | H46: 50.619 | L46: #N/A | N46: #N/A | P46: #N/A | R46: #N/A
A49: Share options and restricted stock units
B50: Tranche | D50: Number | F50: WA strike price
B51: CapIQ - total options year end | D51: 0 | F51: 0
B52: CapIQ - total options quarter end | D52: 0 | F52: 0
B53: CapIQ options used | D53: 0 | F53: 0
B54: Manual tranche 1 | D54: 0 | F54: 0
B55: Manual tranche 2 | D55: 0 | F55: 0
B56: Manual tranche 3 | D56: 0 | F56: 0
B57: Manual tranche 4 | D57: 0 | F57: 0
B58: Manual tranche 5 | D58: 0 | F58: 0
B59: Total
B61: Projected benefit obligation | F61: 0
B62: Fair value of plan assets | F62: 0
B63: Total pension and OPEB expense | F63: 0
B64: Pension service cost | F64: 0
B65: Interest expense | F65: 0
B66: Return on plan assets | F66: 0
B67: LTM rent expense | F67: 39.268
